Workbook

Sheet 販売１
B1: 予算表
B3: 期：
B5: 部署：
B7: 項目 | J7: 年間計 | P7: １０月 | U7: １１月 | Z7: １２月 | AE7: １０月～１２月合計 | AK7: １月 | AP7: ２月 | AU7: ３月 | AZ7: １月～３月合計 | BF7: ４月 | BK7: ５月 | BP7: ６月 | BU7: ４月～６月合計 | CA7: ７月 | CF7: ８月 | CK7: ９月 | CP7: ７月～９月合計
A8: LineNo
J9: 計画 | K9: 前年実績 | L9: 指標 | M9: 差 | N9: 前年比 | P9: 計画 | Q9: 前年実績 | R9: 指標 | S9: 差 | T9: 前年比 | U9: 計画 | V9: 前年実績 | W9: 指標 | X9: 差 | Y9: 前年比 | Z9: 計画 | AA9: 前年実績 | AB9: 指標 | AC9: 差 | AD9: 前年比 | AE9: 計画 | AF9: 前年実績 | AG9: 指標 | AH9: 差 | AI9: 前年比 | AK9: 計画 | AL9: 前年実績 | AM9: 指標 | AN9: 差 | AO9: 前年比 | AP9: 計画 | AQ9: 前年実績 | AR9: 指標 | AS9: 差 | AT9: 前年比 | AU9: 計画 | AV9: 前年実績 | AW9: 指標 | AX9: 差 | AY9: 前年比 | AZ9: 計画 | BA9: 前年実績 | BB9: 指標 | BC9: 差 | BD9: 前年比 | BF9: 計画 | BG9: 前年実績 | BH9: 指標 | BI9: 差 | BJ9: 前年比 | BK9: 計画 | BL9: 前年実績 | BM9: 指標 | BN9: 差 | BO9: 前年比 | BP9: 計画 | BQ9: 前年実績 | BR9: 指標 | BS9: 差 | BT9: 前年比 | BU9: 計画 | BV9: 前年実績 | BW9: 指標 | BX9: 差 | BY9: 前年比 | CA9: 計画 | CB9: 前年実績 | CC9: 指標 | CD9: 差 | CE9: 前年比 | CF9: 計画 | CG9: 前年実績 | CH9: 指標 | CI9: 差 | CJ9: 前年比 | CK9: 計画 | CL9: 前年実績 | CM9: 指標 | CN9: 差 | CO9: 前年比 | CP9: 計画 | CQ9: 前年実績 | CR9: 指標 | CS9: 差 | CT9: 前年比
A10: 1 | B10: 営業スタッフ数 | J10: =SUM(P10,U10,Z10,AK10,AP10,AU10,BF10,BK10,BP10,CA10,CF10,CK10) -> 0 | K10: =SUM(Q10,V10,AA10,AL10,AQ10,AV10,BG10,BL10,BQ10,CB10,CG10,CL10) -> 0 | L10: =SUM(R10,W10,AB10,AM10,AR10,AW10,BH10,BM10,BR10,CC10,CH10,CM10) -> 0 | M10: =SUM(S10,X10,AC10,AN10,AS10,AX10,BI10,BN10,BS10,CD10,CI10,CN10) -> 0 | N10: =SUM(T10,Y10,AD10,AO10,AT10,AY10,BJ10,BO10,BT10,CE10,CJ10,CO10) -> 0 | S10: =P10-Q10 -> 0 | X10: =U10-V10 -> 0 | AD10: =AA10-AB10 -> 0 | AH10: =AE10-AF10 -> 0 | AN10: =AK10-AL10 -> 0 | AS10: =AP10-AQ10 -> 0 | AX10: =AU10-AV10 -> 0 | BC10: =AZ10-BA10 -> 0 | BI10: =BF10-BG10 -> 0 | BN10: =BK10-BL10 -> 0 | BS10: =BP10-BQ10 -> 0 | BX10: =BU10-BV10 -> 0 | CD10: =CA10-CB10 -> 0 | CI10: =CF10-CG10 -> 0 | CN10: =CK10-CL10 -> 0 | CS10: =CP10-CQ10 -> 0
A11: 2 | B11: 自新直顧客数 | J11: =SUM(P11,U11,Z11,AK11,AP11,AU11,BF11,BK11,BP11,CA11,CF11,CK11) -> 0 | K11: =SUM(Q11,V11,AA11,AL11,AQ11,AV11,BG11,BL11,BQ11,CB11,CG11,CL11) -> 0 | L11: =SUM(R11,W11,AB11,AM11,AR11,AW11,BH11,BM11,BR11,CC11,CH11,CM11) -> 0 | M11: =SUM(S11,X11,AC11,AN11,AS11,AX11,BI11,BN11,BS11,CD11,CI11,CN11) -> 0 | N11: =SUM(T11,Y11,AD11,AO11,AT11,AY11,BJ11,BO11,BT11,CE11,CJ11,CO11) -> 0 | S11: =P11-Q11 -> 0 | X11: =U11-V11 -> 0 | AD11: =AA11-AB11 -> 0 | AH11: =AE11-AF11 -> 0 | AN11: =AK11-AL11 -> 0 | AS11: =AP11-AQ11 -> 0 | AX11: =AU11-AV11 -> 0 | BC11: =AZ11-BA11 -> 0 | BI11: =BF11-BG11 -> 0 | BN11: =BK11-BL11 -> 0 | BS11: =BP11-BQ11 -> 0 | BX11: =BU11-BV11 -> 0 | CD11: =CA11-CB11 -> 0 | CI11: =CF11-CG11 -> 0 | CN11: =CK11-CL11 -> 0 | CS11: =CP11-CQ11 -> 0
A12: 3 | B12: 顧客代替台数 | J12: =SUM(P12,U12,Z12,AK12,AP12,AU12,BF12,BK12,BP12,CA12,CF12,CK12) -> 0 | K12: =SUM(Q12,V12,AA12,AL12,AQ12,AV12,BG12,BL12,BQ12,CB12,CG12,CL12) -> 0 | L12: =SUM(R12,W12,AB12,AM12,AR12,AW12,BH12,BM12,BR12,CC12,CH12,CM12) -> 0 | M12: =SUM(S12,X12,AC12,AN12,AS12,AX12,BI12,BN12,BS12,CD12,CI12,CN12) -> 0 | N12: =SUM(T12,Y12,AD12,AO12,AT12,AY12,BJ12,BO12,BT12,CE12,CJ12,CO12) -> 0 | S12: =P12-Q12 -> 0 | X12: =U12-V12 -> 0 | AD12: =AA12-AB12 -> 0 | AH12: =AE12-AF12 -> 0 | AN12: =AK12-AL12 -> 0 | AS12: =AP12-AQ12 -> 0 | AX12: =AU12-AV12 -> 0 | BC12: =AZ12-BA12 -> 0 | BI12: =BF12-BG12 -> 0 | BN12: =BK12-BL12 -> 0 | BS12: =BP12-BQ12 -> 0 | BX12: =BU12-BV12 -> 0 | CD12: =CA12-CB12 -> 0 | CI12: =CF12-CG12 -> 0 | CN12: =CK12-CL12 -> 0 | CS12: =CP12-CQ12 -> 0
A13: 4 | B13: 自中直顧客数 | J13: =SUM(P13,U13,Z13,AK13,AP13,AU13,BF13,BK13,BP13,CA13,CF13,CK13) -> 0 | K13: =SUM(Q13,V13,AA13,AL13,AQ13,AV13,BG13,BL13,BQ13,CB13,CG13,CL13) -> 0 | L13: =SUM(R13,W13,AB13,AM13,AR13,AW13,BH13,BM13,BR13,CC13,CH13,CM13) -> 0 | M13: =SUM(S13,X13,AC13,AN13,AS13,AX13,BI13,BN13,BS13,CD13,CI13,CN13) -> 0 | N13: =SUM(T13,Y13,AD13,AO13,AT13,AY13,BJ13,BO13,BT13,CE13,CJ13,CO13) -> 0 | S13: =P13-Q13 -> 0 | X13: =U13-V13 -> 0 | AD13: =AA13-AB13 -> 0 | AH13: =AE13-AF13 -> 0 | AN13: =AK13-AL13 -> 0 | AS13: =AP13-AQ13 -> 0 | AX13: =AU13-AV13 -> 0 | BC13: =AZ13-BA13 -> 0 | BI13: =BF13-BG13 -> 0 | BN13: =BK13-BL13 -> 0 | BS13: =BP13-BQ13 -> 0 | BX13: =BU13-BV13 -> 0 | CD13: =CA13-CB13 -> 0 | CI13: =CF13-CG13 -> 0 | CN13: =CK13-CL13 -> 0 | CS13: =CP13-CQ13 -> 0
A14: 5 | B14: サービス直人員 | J14: =SUM(P14,U14,Z14,AK14,AP14,AU14,BF14,BK14,BP14,CA14,CF14,CK14) -> 0 | K14: =SUM(Q14,V14,AA14,AL14,AQ14,AV14,BG14,BL14,BQ14,CB14,CG14,CL14) -> 0 | L14: =SUM(R14,W14,AB14,AM14,AR14,AW14,BH14,BM14,BR14,CC14,CH14,CM14) -> 0 | M14: =SUM(S14,X14,AC14,AN14,AS14,AX14,BI14,BN14,BS14,CD14,CI14,CN14) -> 0 | N14: =SUM(T14,Y14,AD14,AO14,AT14,AY14,BJ14,BO14,BT14,CE14,CJ14,CO14) -> 0 | S14: =P14-Q14 -> 0 | X14: =U14-V14 -> 0 | AD14: =AA14-AB14 -> 0 | AH14: =AE14-AF14 -> 0 | AN14: =AK14-AL14 -> 0 | AS14: =AP14-AQ14 -> 0 | AX14: =AU14-AV14 -> 0 | BC14: =AZ14-BA14 -> 0 | BI14: =BF14-BG14 -> 0 | BN14: =BK14-BL14 -> 0 | BS14: =BP14-BQ14 -> 0 | BX14: =BU14-BV14 -> 0 | CD14: =CA14-CB14 -> 0 | CI14: =CF14-CG14 -> 0 | CN14: =CK14-CL14 -> 0 | CS14: =CP14-CQ14 -> 0
A15: 6 | B15: サービス管理顧客数 | J15: =SUM(P15,U15,Z15,AK15,AP15,AU15,BF15,BK15,BP15,CA15,CF15,CK15) -> 0 | K15: =SUM(Q15,V15,AA15,AL15,AQ15,AV15,BG15,BL15,BQ15,CB15,CG15,CL15) -> 0 | L15: =SUM(R15,W15,AB15,AM15,AR15,AW15,BH15,BM15,BR15,CC15,CH15,CM15) -> 0 | M15: =SUM(S15,X15,AC15,AN15,AS15,AX15,BI15,BN15,BS15,CD15,CI15,CN15) -> 0 | N15: =SUM(T15,Y15,AD15,AO15,AT15,AY15,BJ15,BO15,BT15,CE15,CJ15,CO15) -> 0 | S15: =P15-Q15 -> 0 | X15: =U15-V15 -> 0 | AD15: =AA15-AB15 -> 0 | AH15: =AE15-AF15 -> 0 | AN15: =AK15-AL15 -> 0 | AS15: =AP15-AQ15 -> 0 | AX15: =AU15-AV15 -> 0 | BC15: =AZ15-BA15 -> 0 | BI15: =BF15-BG15 -> 0 | BN15: =BK15-BL15 -> 0 | BS15: =BP15-BQ15 -> 0 | BX15: =BU15-BV15 -> 0 | CD15: =CA15-CB15 -> 0 | CI15: =CF15-CG15 -> 0 | CN15: =CK15-CL15 -> 0 | CS15: =CP15-CQ15 -> 0
A16: 7 | B16: 車検対象台数 | J16: =SUM(P16,U16,Z16,AK16,AP16,AU16,BF16,BK16,BP16,CA16,CF16,CK16) -> 0 | K16: =SUM(Q16,V16,AA16,AL16,AQ16,AV16,BG16,BL16,BQ16,CB16,CG16,CL16) -> 0 | L16: =SUM(R16,W16,AB16,AM16,AR16,AW16,BH16,BM16,BR16,CC16,CH16,CM16) -> 0 | M16: =SUM(S16,X16,AC16,AN16,AS16,AX16,BI16,BN16,BS16,CD16,CI16,CN16) -> 0 | N16: =SUM(T16,Y16,AD16,AO16,AT16,AY16,BJ16,BO16,BT16,CE16,CJ16,CO16) -> 0 | S16: =P16-Q16 -> 0 | X16: =U16-V16 -> 0 | AD16: =AA16-AB16 -> 0 | AH16: =AE16-AF16 -> 0 | AN16: =AK16-AL16 -> 0 | AS16: =AP16-AQ16 -> 0 | AX16: =AU16-AV16 -> 0 | BC16: =AZ16-BA16 -> 0 | BI16: =BF16-BG16 -> 0 | BN16: =BK16-BL16 -> 0 | BS16: =BP16-BQ16 -> 0 | BX16: =BU16-BV16 -> 0 | CD16: =CA16-CB16 -> 0 | CI16: =CF16-CG16 -> 0 | CN16: =CK16-CL16 -> 0 | CS16: =CP16-CQ16 -> 0
A17: 8 | C17: 内初回車検対象台数 | J17: =SUM(P17,U17,Z17,AK17,AP17,AU17,BF17,BK17,BP17,CA17,CF17,CK17) -> 0 | K17: =SUM(Q17,V17,AA17,AL17,AQ17,AV17,BG17,BL17,BQ17,CB17,CG17,CL17) -> 0 | L17: =SUM(R17,W17,AB17,AM17,AR17,AW17,BH17,BM17,BR17,CC17,CH17,CM17) -> 0 | M17: =SUM(S17,X17,AC17,AN17,AS17,AX17,BI17,BN17,BS17,CD17,CI17,CN17) -> 0 | N17: =SUM(T17,Y17,AD17,AO17,AT17,AY17,BJ17,BO17,BT17,CE17,CJ17,CO17) -> 0 | S17: =P17-Q17 -> 0 | X17: =U17-V17 -> 0 | AD17: =AA17-AB17 -> 0 | AH17: =AE17-AF17 -> 0 | AN17: =AK17-AL17 -> 0 | AS17: =AP17-AQ17 -> 0 | AX17: =AU17-AV17 -> 0 | BC17: =AZ17-BA17 -> 0 | BI17: =BF17-BG17 -> 0 | BN17: =BK17-BL17 -> 0 | BS17: =BP17-BQ17 -> 0 | BX17: =BU17-BV17 -> 0 | CD17: =CA17-CB17 -> 0 | CI17: =CF17-CG17 -> 0 | CN17: =CK17-CL17 -> 0 | CS17: =CP17-CQ17 -> 0
A18: 9 | B18: 初回車検入庫 | J18: =SUM(P18,U18,Z18,AK18,AP18,AU18,BF18,BK18,BP18,CA18,CF18,CK18) -> 0 | K18: =SUM(Q18,V18,AA18,AL18,AQ18,AV18,BG18,BL18,BQ18,CB18,CG18,CL18) -> 0 | L18: =SUM(R18,W18,AB18,AM18,AR18,AW18,BH18,BM18,BR18,CC18,CH18,CM18) -> 0 | M18: =SUM(S18,X18,AC18,AN18,AS18,AX18,BI18,BN18,BS18,CD18,CI18,CN18) -> 0 | N18: =SUM(T18,Y18,AD18,AO18,AT18,AY18,BJ18,BO18,BT18,CE18,CJ18,CO18) -> 0 | S18: =P18-Q18 -> 0 | X18: =U18-V18 -> 0 | AD18: =AA18-AB18 -> 0 | AH18: =AE18-AF18 -> 0 | AN18: =AK18-AL18 -> 0 | AS18: =AP18-AQ18 -> 0 | AX18: =AU18-AV18 -> 0 | BC18: =AZ18-BA18 -> 0 | BI18: =BF18-BG18 -> 0 | BN18: =BK18-BL18 -> 0 | BS18: =BP18-BQ18 -> 0 | BX18: =BU18-BV18 -> 0 | CD18: =CA18-CB18 -> 0 | CI18: =CF18-CG18 -> 0 | CN18: =CK18-CL18 -> 0 | CS18: =CP18-CQ18 -> 0
A19: 10 | B19: 有償入庫台数 | J19: =SUM(P19,U19,Z19,AK19,AP19,AU19,BF19,BK19,BP19,CA19,CF19,CK19) -> 0 | K19: =SUM(Q19,V19,AA19,AL19,AQ19,AV19,BG19,BL19,BQ19,CB19,CG19,CL19) -> 0 | L19: =SUM(R19,W19,AB19,AM19,AR19,AW19,BH19,BM19,BR19,CC19,CH19,CM19) -> 0 | M19: =SUM(S19,X19,AC19,AN19,AS19,AX19,BI19,BN19,BS19,CD19,CI19,CN19) -> 0 | N19: =SUM(T19,Y19,AD19,AO19,AT19,AY19,BJ19,BO19,BT19,CE19,CJ19,CO19) -> 0 | S19: =P19-Q19 -> 0 | X19: =U19-V19 -> 0 | AD19: =AA19-AB19 -> 0 | AH19: =AE19-AF19 -> 0 | AN19: =AK19-AL19 -> 0 | AS19: =AP19-AQ19 -> 0 | AX19: =AU19-AV19 -> 0 | BC19: =AZ19-BA19 -> 0 | BI19: =BF19-BG19 -> 0 | BN19: =BK19-BL19 -> 0 | BS19: =BP19-BQ19 -> 0 | BX19: =BU19-BV19 -> 0 | CD19: =CA19-CB19 -> 0 | CI19: =CF19-CG19 -> 0 | CN19: =CK19-CL19 -> 0 | CS19: =CP19-CQ19 -> 0
A20: 11 | B20: 新規獲得件数 | J20: =SUM(P20,U20,Z20,AK20,AP20,AU20,BF20,BK20,BP20,CA20,CF20,CK20) -> 0 | K20: =SUM(Q20,V20,AA20,AL20,AQ20,AV20,BG20,BL20,BQ20,CB20,CG20,CL20) -> 0 | L20: =SUM(R20,W20,AB20,AM20,AR20,AW20,BH20,BM20,BR20,CC20,CH20,CM20) -> 0 | M20: =SUM(S20,X20,AC20,AN20,AS20,AX20,BI20,BN20,BS20,CD20,CI20,CN20) -> 0 | N20: =SUM(T20,Y20,AD20,AO20,AT20,AY20,BJ20,BO20,BT20,CE20,CJ20,CO20) -> 0 | S20: =P20-Q20 -> 0 | X20: =U20-V20 -> 0 | AD20: =AA20-AB20 -> 0 | AH20: =AE20-AF20 -> 0 | AN20: =AK20-AL20 -> 0 | AS20: =AP20-AQ20 -> 0 | AX20: =AU20-AV20 -> 0 | BC20: =AZ20-BA20 -> 0 | BI20: =BF20-BG20 -> 0 | BN20: =BK20-BL20 -> 0 | BS20: =BP20-BQ20 -> 0 | BX20: =BU20-BV20 -> 0 | CD20: =CA20-CB20 -> 0 | CI20: =CF20-CG20 -> 0 | CN20: =CK20-CL20 -> 0 | CS20: =CP20-CQ20 -> 0
A21: 12 | B21: 継続対象件数 | J21: =SUM(P21,U21,Z21,AK21,AP21,AU21,BF21,BK21,BP21,CA21,CF21,CK21) -> 0 | K21: =SUM(Q21,V21,AA21,AL21,AQ21,AV21,BG21,BL21,BQ21,CB21,CG21,CL21) -> 0 | L21: =SUM(R21,W21,AB21,AM21,AR21,AW21,BH21,BM21,BR21,CC21,CH21,CM21) -> 0 | M21: =SUM(S21,X21,AC21,AN21,AS21,AX21,BI21,BN21,BS21,CD21,CI21,CN21) -> 0 | N21: =SUM(T21,Y21,AD21,AO21,AT21,AY21,BJ21,BO21,BT21,CE21,CJ21,CO21) -> 0 | S21: =P21-Q21 -> 0 | X21: =U21-V21 -> 0 | AD21: =AA21-AB21 -> 0 | AH21: =AE21-AF21 -> 0 | AN21: =AK21-AL21 -> 0 | AS21: =AP21-AQ21 -> 0 | AX21: =AU21-AV21 -> 0 | BC21: =AZ21-BA21 -> 0 | BI21: =BF21-BG21 -> 0 | BN21: =BK21-BL21 -> 0 | BS21: =BP21-BQ21 -> 0 | BX21: =BU21-BV21 -> 0 | CD21: =CA21-CB21 -> 0 | CI21: =CF21-CG21 -> 0 | CN21: =CK21-CL21 -> 0 | CS21: =CP21-CQ21 -> 0
A22: 13 | B22: 継続件数 | J22: =SUM(P22,U22,Z22,AK22,AP22,AU22,BF22,BK22,BP22,CA22,CF22,CK22) -> 0 | K22: =SUM(Q22,V22,AA22,AL22,AQ22,AV22,BG22,BL22,BQ22,CB22,CG22,CL22) -> 0 | L22: =SUM(R22,W22,AB22,AM22,AR22,AW22,BH22,BM22,BR22,CC22,CH22,CM22) -> 0 | M22: =SUM(S22,X22,AC22,AN22,AS22,AX22,BI22,BN22,BS22,CD22,CI22,CN22) -> 0 | N22: =SUM(T22,Y22,AD22,AO22,AT22,AY22,BJ22,BO22,BT22,CE22,CJ22,CO22) -> 0 | S22: =P22-Q22 -> 0 | X22: =U22-V22 -> 0 | AD22: =AA22-AB22 -> 0 | AH22: =AE22-AF22 -> 0 | AN22: =AK22-AL22 -> 0 | AS22: =AP22-AQ22 -> 0 | AX22: =AU22-AV22 -> 0 | BC22: =AZ22-BA22 -> 0 | BI22: =BF22-BG22 -> 0 | BN22: =BK22-BL22 -> 0 | BS22: =BP22-BQ22 -> 0 | BX22: =BU22-BV22 -> 0 | CD22: =CA22-CB22 -> 0 | CI22: =CF22-CG22 -> 0 | CN22: =CK22-CL22 -> 0 | CS22: =CP22-CQ22 -> 0
A23: 14 | B23: 車両保険件数 | J23: =SUM(P23,U23,Z23,AK23,AP23,AU23,BF23,BK23,BP23,CA23,CF23,CK23) -> 0 | K23: =SUM(Q23,V23,AA23,AL23,AQ23,AV23,BG23,BL23,BQ23,CB23,CG23,CL23) -> 0 | L23: =SUM(R23,W23,AB23,AM23,AR23,AW23,BH23,BM23,BR23,CC23,CH23,CM23) -> 0 | M23: =SUM(S23,X23,AC23,AN23,AS23,AX23,BI23,BN23,BS23,CD23,CI23,CN23) -> 0 | N23: =SUM(T23,Y23,AD23,AO23,AT23,AY23,BJ23,BO23,BT23,CE23,CJ23,CO23) -> 0 | S23: =P23-Q23 -> 0 | X23: =U23-V23 -> 0 | AD23: =AA23-AB23 -> 0 | AH23: =AE23-AF23 -> 0 | AN23: =AK23-AL23 -> 0 | AS23: =AP23-AQ23 -> 0 | AX23: =AU23-AV23 -> 0 | BC23: =AZ23-BA23 -> 0 | BI23: =BF23-BG23 -> 0 | BN23: =BK23-BL23 -> 0 | BS23: =BP23-BQ23 -> 0 | BX23: =BU23-BV23 -> 0 | CD23: =CA23-CB23 -> 0 | CI23: =CF23-CG23 -> 0 | CN23: =CK23-CL23 -> 0 | CS23: =CP23-CQ23 -> 0
A24: 15 | B24: 収保 | J24: =SUM(P24,U24,Z24,AK24,AP24,AU24,BF24,BK24,BP24,CA24,CF24,CK24) -> 0 | K24: =SUM(Q24,V24,AA24,AL24,AQ24,AV24,BG24,BL24,BQ24,CB24,CG24,CL24) -> 0 | L24: =SUM(R24,W24,AB24,AM24,AR24,AW24,BH24,BM24,BR24,CC24,CH24,CM24) -> 0 | M24: =SUM(S24,X24,AC24,AN24,AS24,AX24,BI24,BN24,BS24,CD24,CI24,CN24) -> 0 | N24: =SUM(T24,Y24,AD24,AO24,AT24,AY24,BJ24,BO24,BT24,CE24,CJ24,CO24) -> 0 | S24: =P24-Q24 -> 0 | X24: =U24-V24 -> 0 | AD24: =AA24-AB24 -> 0 | AH24: =AE24-AF24 -> 0 | AN24: =AK24-AL24 -> 0 | AS24: =AP24-AQ24 -> 0 | AX24: =AU24-AV24 -> 0 | BC24: =AZ24-BA24 -> 0 | BI24: =BF24-BG24 -> 0 | BN24: =BK24-BL24 -> 0 | BS24: =BP24-BQ24 -> 0 | BX24: =BU24-BV24 -> 0 | CD24: =CA24-CB24 -> 0 | CI24: =CF24-CG24 -> 0 | CN24: =CK24-CL24 -> 0 | CS24: =CP24-CQ24 -> 0
A25: 16 | B25: 総限界利益 | C25: 総利益合計 | D25: 新車 | E25: 新車台数 | J25: =SUM(P25,U25,Z25,AK25,AP25,AU25,BF25,BK25,BP25,CA25,CF25,CK25) -> 0 | K25: =SUM(Q25,V25,AA25,AL25,AQ25,AV25,BG25,BL25,BQ25,CB25,CG25,CL25) -> 0 | L25: =SUM(R25,W25,AB25,AM25,AR25,AW25,BH25,BM25,BR25,CC25,CH25,CM25) -> 0 | M25: =SUM(S25,X25,AC25,AN25,AS25,AX25,BI25,BN25,BS25,CD25,CI25,CN25) -> 0 | N25: =SUM(T25,Y25,AD25,AO25,AT25,AY25,BJ25,BO25,BT25,CE25,CJ25,CO25) -> 0 | S25: =P25-Q25 -> 0 | X25: =U25-V25 -> 0 | AD25: =AA25-AB25 -> 0 | AH25: =AE25-AF25 -> 0 | AN25: =AK25-AL25 -> 0 | AS25: =AP25-AQ25 -> 0 | AX25: =AU25-AV25 -> 0 | BC25: =AZ25-BA25 -> 0 | BI25: =BF25-BG25 -> 0 | BN25: =BK25-BL25 -> 0 | BS25: =BP25-BQ25 -> 0 | BX25: =BU25-BV25 -> 0 | CD25: =CA25-CB25 -> 0 | CI25: =CF25-CG25 -> 0 | CN25: =CK25-CL25 -> 0 | CS25: =CP25-CQ25 -> 0
A26: 17 | E26: 売上金額（架装売上含む） | J26: =SUM(P26,U26,Z26,AK26,AP26,AU26,BF26,BK26,BP26,CA26,CF26,CK26) -> 0 | K26: =SUM(Q26,V26,AA26,AL26,AQ26,AV26,BG26,BL26,BQ26,CB26,CG26,CL26) -> 0 | L26: =SUM(R26,W26,AB26,AM26,AR26,AW26,BH26,BM26,BR26,CC26,CH26,CM26) -> 0 | M26: =SUM(S26,X26,AC26,AN26,AS26,AX26,BI26,BN26,BS26,CD26,CI26,CN26) -> 0 | N26: =SUM(T26,Y26,AD26,AO26,AT26,AY26,BJ26,BO26,BT26,CE26,CJ26,CO26) -> 0 | S26: =P26-Q26 -> 0 | X26: =U26-V26 -> 0 | AD26: =AA26-AB26 -> 0 | AH26: =AE26-AF26 -> 0 | AN26: =AK26-AL26 -> 0 | AS26: =AP26-AQ26 -> 0 | AX26: =AU26-AV26 -> 0 | BC26: =AZ26-BA26 -> 0 | BI26: =BF26-BG26 -> 0 | BN26: =BK26-BL26 -> 0 | BS26: =BP26-BQ26 -> 0 | BX26: =BU26-BV26 -> 0 | CD26: =CA26-CB26 -> 0 | CI26: =CF26-CG26 -> 0 | CN26: =CK26-CL26 -> 0 | CS26: =CP26-CQ26 -> 0
A27: 18 | F27: ＜内車両値引＞ | J27: =SUM(P27,U27,Z27,AK27,AP27,AU27,BF27,BK27,BP27,CA27,CF27,CK27) -> 0 | K27: =SUM(Q27,V27,AA27,AL27,AQ27,AV27,BG27,BL27,BQ27,CB27,CG27,CL27) -> 0 | L27: =SUM(R27,W27,AB27,AM27,AR27,AW27,BH27,BM27,BR27,CC27,CH27,CM27) -> 0 | M27: =SUM(S27,X27,AC27,AN27,AS27,AX27,BI27,BN27,BS27,CD27,CI27,CN27) -> 0 | N27: =SUM(T27,Y27,AD27,AO27,AT27,AY27,BJ27,BO27,BT27,CE27,CJ27,CO27) -> 0 | S27: =P27-Q27 -> 0 | X27: =U27-V27 -> 0 | AD27: =AA27-AB27 -> 0 | AH27: =AE27-AF27 -> 0 | AN27: =AK27-AL27 -> 0 | AS27: =AP27-AQ27 -> 0 | AX27: =AU27-AV27 -> 0 | BC27: =AZ27-BA27 -> 0 | BI27: =BF27-BG27 -> 0 | BN27: =BK27-BL27 -> 0 | BS27: =BP27-BQ27 -> 0 | BX27: =BU27-BV27 -> 0 | CD27: =CA27-CB27 -> 0 | CI27: =CF27-CG27 -> 0 | CN27: =CK27-CL27 -> 0 | CS27: =CP27-CQ27 -> 0
A28: 19 | F28: 車両本体利益 | J28: =SUM(P28,U28,Z28,AK28,AP28,AU28,BF28,BK28,BP28,CA28,CF28,CK28) -> 0 | K28: =SUM(Q28,V28,AA28,AL28,AQ28,AV28,BG28,BL28,BQ28,CB28,CG28,CL28) -> 0 | L28: =SUM(R28,W28,AB28,AM28,AR28,AW28,BH28,BM28,BR28,CC28,CH28,CM28) -> 0 | M28: =SUM(S28,X28,AC28,AN28,AS28,AX28,BI28,BN28,BS28,CD28,CI28,CN28) -> 0 | N28: =SUM(T28,Y28,AD28,AO28,AT28,AY28,BJ28,BO28,BT28,CE28,CJ28,CO28) -> 0 | S28: =P28-Q28 -> 0 | X28: =U28-V28 -> 0 | AD28: =AA28-AB28 -> 0 | AH28: =AE28-AF28 -> 0 | AN28: =AK28-AL28 -> 0 | AS28: =AP28-AQ28 -> 0 | AX28: =AU28-AV28 -> 0 | BC28: =AZ28-BA28 -> 0 | BI28: =BF28-BG28 -> 0 | BN28: =BK28-BL28 -> 0 | BS28: =BP28-BQ28 -> 0 | BX28: =BU28-BV28 -> 0 | CD28: =CA28-CB28 -> 0 | CI28: =CF28-CG28 -> 0 | CN28: =CK28-CL28 -> 0 | CS28: =CP28-CQ28 -> 0
A29: 20 | F29: 架装付属品利益 | J29: =SUM(P29,U29,Z29,AK29,AP29,AU29,BF29,BK29,BP29,CA29,CF29,CK29) -> 0 | K29: =SUM(Q29,V29,AA29,AL29,AQ29,AV29,BG29,BL29,BQ29,CB29,CG29,CL29) -> 0 | L29: =SUM(R29,W29,AB29,AM29,AR29,AW29,BH29,BM29,BR29,CC29,CH29,CM29) -> 0 | M29: =SUM(S29,X29,AC29,AN29,AS29,AX29,BI29,BN29,BS29,CD29,CI29,CN29) -> 0 | N29: =SUM(T29,Y29,AD29,AO29,AT29,AY29,BJ29,BO29,BT29,CE29,CJ29,CO29) -> 0 | S29: =P29-Q29 -> 0 | X29: =U29-V29 -> 0 | AD29: =AA29-AB29 -> 0 | AH29: =AE29-AF29 -> 0 | AN29: =AK29-AL29 -> 0 | AS29: =AP29-AQ29 -> 0 | AX29: =AU29-AV29 -> 0 | BC29: =AZ29-BA29 -> 0 | BI29: =BF29-BG29 -> 0 | BN29: =BK29-BL29 -> 0 | BS29: =BP29-BQ29 -> 0 | BX29: =BU29-BV29 -> 0 | CD29: =CA29-CB29 -> 0 | CI29: =CF29-CG29 -> 0 | CN29: =CK29-CL29 -> 0 | CS29: =CP29-CQ29 -> 0
A30: 21 | F30: 車両収入手数料 | J30: =SUM(P30,U30,Z30,AK30,AP30,AU30,BF30,BK30,BP30,CA30,CF30,CK30) -> 0 | K30: =SUM(Q30,V30,AA30,AL30,AQ30,AV30,BG30,BL30,BQ30,CB30,CG30,CL30) -> 0 | L30: =SUM(R30,W30,AB30,AM30,AR30,AW30,BH30,BM30,BR30,CC30,CH30,CM30) -> 0 | M30: =SUM(S30,X30,AC30,AN30,AS30,AX30,BI30,BN30,BS30,CD30,CI30,CN30) -> 0 | N30: =SUM(T30,Y30,AD30,AO30,AT30,AY30,BJ30,BO30,BT30,CE30,CJ30,CO30) -> 0 | S30: =P30-Q30 -> 0 | X30: =U30-V30 -> 0 | AD30: =AA30-AB30 -> 0 | AH30: =AE30-AF30 -> 0 | AN30: =AK30-AL30 -> 0 | AS30: =AP30-AQ30 -> 0 | AX30: =AU30-AV30 -> 0 | BC30: =AZ30-BA30 -> 0 | BI30: =BF30-BG30 -> 0 | BN30: =BK30-BL30 -> 0 | BS30: =BP30-BQ30 -> 0 | BX30: =BU30-BV30 -> 0 | CD30: =CA30-CB30 -> 0 | CI30: =CF30-CG30 -> 0 | CN30: =CK30-CL30 -> 0 | CS30: =CP30-CQ30 -> 0
A31: 22 | F31: 登録収入手数料 | J31: =SUM(P31,U31,Z31,AK31,AP31,AU31,BF31,BK31,BP31,CA31,CF31,CK31) -> 0 | K31: =SUM(Q31,V31,AA31,AL31,AQ31,AV31,BG31,BL31,BQ31,CB31,CG31,CL31) -> 0 | L31: =SUM(R31,W31,AB31,AM31,AR31,AW31,BH31,BM31,BR31,CC31,CH31,CM31) -> 0 | M31: =SUM(S31,X31,AC31,AN31,AS31,AX31,BI31,BN31,BS31,CD31,CI31,CN31) -> 0 | N31: =SUM(T31,Y31,AD31,AO31,AT31,AY31,BJ31,BO31,BT31,CE31,CJ31,CO31) -> 0 | S31: =P31-Q31 -> 0 | X31: =U31-V31 -> 0 | AD31: =AA31-AB31 -> 0 | AH31: =AE31-AF31 -> 0 | AN31: =AK31-AL31 -> 0 | AS31: =AP31-AQ31 -> 0 | AX31: =AU31-AV31 -> 0 | BC31: =AZ31-BA31 -> 0 | BI31: =BF31-BG31 -> 0 | BN31: =BK31-BL31 -> 0 | BS31: =BP31-BQ31 -> 0 | BX31: =BU31-BV31 -> 0 | CD31: =CA31-CB31 -> 0 | CI31: =CF31-CG31 -> 0 | CN31: =CK31-CL31 -> 0 | CS31: =CP31-CQ31 -> 0
A32: 23 | F32: クレジット利益 | J32: =SUM(P32,U32,Z32,AK32,AP32,AU32,BF32,BK32,BP32,CA32,CF32,CK32) -> 0 | K32: =SUM(Q32,V32,AA32,AL32,AQ32,AV32,BG32,BL32,BQ32,CB32,CG32,CL32) -> 0 | L32: =SUM(R32,W32,AB32,AM32,AR32,AW32,BH32,BM32,BR32,CC32,CH32,CM32) -> 0 | M32: =SUM(S32,X32,AC32,AN32,AS32,AX32,BI32,BN32,BS32,CD32,CI32,CN32) -> 0 | N32: =SUM(T32,Y32,AD32,AO32,AT32,AY32,BJ32,BO32,BT32,CE32,CJ32,CO32) -> 0 | S32: =P32-Q32 -> 0 | X32: =U32-V32 -> 0 | AD32: =AA32-AB32 -> 0 | AH32: =AE32-AF32 -> 0 | AN32: =AK32-AL32 -> 0 | AS32: =AP32-AQ32 -> 0 | AX32: =AU32-AV32 -> 0 | BC32: =AZ32-BA32 -> 0 | BI32: =BF32-BG32 -> 0 | BN32: =BK32-BL32 -> 0 | BS32: =BP32-BQ32 -> 0 | BX32: =BU32-BV32 -> 0 | CD32: =CA32-CB32 -> 0 | CI32: =CF32-CG32 -> 0 | CN32: =CK32-CL32 -> 0 | CS32: =CP32-CQ32 -> 0
A33: 24 | F33: 販売手数料 | J33: =SUM(P33,U33,Z33,AK33,AP33,AU33,BF33,BK33,BP33,CA33,CF33,CK33) -> 0 | K33: =SUM(Q33,V33,AA33,AL33,AQ33,AV33,BG33,BL33,BQ33,CB33,CG33,CL33) -> 0 | L33: =SUM(R33,W33,AB33,AM33,AR33,AW33,BH33,BM33,BR33,CC33,CH33,CM33) -> 0 | M33: =SUM(S33,X33,AC33,AN33,AS33,AX33,BI33,BN33,BS33,CD33,CI33,CN33) -> 0 | N33: =SUM(T33,Y33,AD33,AO33,AT33,AY33,BJ33,BO33,BT33,CE33,CJ33,CO33) -> 0 | S33: =P33-Q33 -> 0 | X33: =U33-V33 -> 0 | AD33: =AA33-AB33 -> 0 | AH33: =AE33-AF33 -> 0 | AN33: =AK33-AL33 -> 0 | AS33: =AP33-AQ33 -> 0 | AX33: =AU33-AV33 -> 0 | BC33: =AZ33-BA33 -> 0 | BI33: =BF33-BG33 -> 0 | BN33: =BK33-BL33 -> 0 | BS33: =BP33-BQ33 -> 0 | BX33: =BU33-BV33 -> 0 | CD33: =CA33-CB33 -> 0 | CI33: =CF33-CG33 -> 0 | CN33: =CK33-CL33 -> 0 | CS33: =CP33-CQ33 -> 0
A34: 25 | E34: 新車総粗利 | J34: =SUM(P34,U34,Z34,AK34,AP34,AU34,BF34,BK34,BP34,CA34,CF34,CK34) -> 0 | K34: =SUM(Q34,V34,AA34,AL34,AQ34,AV34,BG34,BL34,BQ34,CB34,CG34,CL34) -> 0 | L34: =SUM(R34,W34,AB34,AM34,AR34,AW34,BH34,BM34,BR34,CC34,CH34,CM34) -> 0 | M34: =SUM(S34,X34,AC34,AN34,AS34,AX34,BI34,BN34,BS34,CD34,CI34,CN34) -> 0 | N34: =SUM(T34,Y34,AD34,AO34,AT34,AY34,BJ34,BO34,BT34,CE34,CJ34,CO34) -> 0 | S34: =P34-Q34 -> 0 | X34: =U34-V34 -> 0 | AD34: =AA34-AB34 -> 0 | AH34: =AE34-AF34 -> 0 | AN34: =AK34-AL34 -> 0 | AS34: =AP34-AQ34 -> 0 | AX34: =AU34-AV34 -> 0 | BC34: =AZ34-BA34 -> 0 | BI34: =BF34-BG34 -> 0 | BN34: =BK34-BL34 -> 0 | BS34: =BP34-BQ34 -> 0 | BX34: =BU34-BV34 -> 0 | CD34: =CA34-CB34 -> 0 | CI34: =CF34-CG34 -> 0 | CN34: =CK34-CL34 -> 0 | CS34: =CP34-CQ34 -> 0
A35: 26 | E35: 販売費 | F35: 販手・サービス・雑費 | J35: =SUM(P35,U35,Z35,AK35,AP35,AU35,BF35,BK35,BP35,CA35,CF35,CK35) -> 0 | K35: =SUM(Q35,V35,AA35,AL35,AQ35,AV35,BG35,BL35,BQ35,CB35,CG35,CL35) -> 0 | L35: =SUM(R35,W35,AB35,AM35,AR35,AW35,BH35,BM35,BR35,CC35,CH35,CM35) -> 0 | M35: =SUM(S35,X35,AC35,AN35,AS35,AX35,BI35,BN35,BS35,CD35,CI35,CN35) -> 0 | N35: =SUM(T35,Y35,AD35,AO35,AT35,AY35,BJ35,BO35,BT35,CE35,CJ35,CO35) -> 0 | S35: =P35-Q35 -> 0 | X35: =U35-V35 -> 0 | AD35: =AA35-AB35 -> 0 | AH35: =AE35-AF35 -> 0 | AN35: =AK35-AL35 -> 0 | AS35: =AP35-AQ35 -> 0 | AX35: =AU35-AV35 -> 0 | BC35: =AZ35-BA35 -> 0 | BI35: =BF35-BG35 -> 0 | BN35: =BK35-BL35 -> 0 | BS35: =BP35-BQ35 -> 0 | BX35: =BU35-BV35 -> 0 | CD35: =CA35-CB35 -> 0 | CI35: =CF35-CG35 -> 0 | CN35: =CK35-CL35 -> 0 | CS35: =CP35-CQ35 -> 0
A36: 27 | F36: 納車費・運送保管費 | J36: =SUM(P36,U36,Z36,AK36,AP36,AU36,BF36,BK36,BP36,CA36,CF36,CK36) -> 0 | K36: =SUM(Q36,V36,AA36,AL36,AQ36,AV36,BG36,BL36,BQ36,CB36,CG36,CL36) -> 0 | L36: =SUM(R36,W36,AB36,AM36,AR36,AW36,BH36,BM36,BR36,CC36,CH36,CM36) -> 0 | M36: =SUM(S36,X36,AC36,AN36,AS36,AX36,BI36,BN36,BS36,CD36,CI36,CN36) -> 0 | N36: =SUM(T36,Y36,AD36,AO36,AT36,AY36,BJ36,BO36,BT36,CE36,CJ36,CO36) -> 0 | S36: =P36-Q36 -> 0 | X36: =U36-V36 -> 0 | AD36: =AA36-AB36 -> 0 | AH36: =AE36-AF36 -> 0 | AN36: =AK36-AL36 -> 0 | AS36: =AP36-AQ36 -> 0 | AX36: =AU36-AV36 -> 0 | BC36: =AZ36-BA36 -> 0 | BI36: =BF36-BG36 -> 0 | BN36: =BK36-BL36 -> 0 | BS36: =BP36-BQ36 -> 0 | BX36: =BU36-BV36 -> 0 | CD36: =CA36-CB36 -> 0 | CI36: =CF36-CG36 -> 0 | CN36: =CK36-CL36 -> 0 | CS36: =CP36-CQ36 -> 0
A37: 28 | F37: 広告宣伝費 | J37: =SUM(P37,U37,Z37,AK37,AP37,AU37,BF37,BK37,BP37,CA37,CF37,CK37) -> 0 | K37: =SUM(Q37,V37,AA37,AL37,AQ37,AV37,BG37,BL37,BQ37,CB37,CG37,CL37) -> 0 | L37: =SUM(R37,W37,AB37,AM37,AR37,AW37,BH37,BM37,BR37,CC37,CH37,CM37) -> 0 | M37: =SUM(S37,X37,AC37,AN37,AS37,AX37,BI37,BN37,BS37,CD37,CI37,CN37) -> 0 | N37: =SUM(T37,Y37,AD37,AO37,AT37,AY37,BJ37,BO37,BT37,CE37,CJ37,CO37) -> 0 | S37: =P37-Q37 -> 0 | X37: =U37-V37 -> 0 | AD37: =AA37-AB37 -> 0 | AH37: =AE37-AF37 -> 0 | AN37: =AK37-AL37 -> 0 | AS37: =AP37-AQ37 -> 0 | AX37: =AU37-AV37 -> 0 | BC37: =AZ37-BA37 -> 0 | BI37: =BF37-BG37 -> 0 | BN37: =BK37-BL37 -> 0 | BS37: =BP37-BQ37 -> 0 | BX37: =BU37-BV37 -> 0 | CD37: =CA37-CB37 -> 0 | CI37: =CF37-CG37 -> 0 | CN37: =CK37-CL37 -> 0 | CS37: =CP37-CQ37 -> 0
A38: 29 | F38: デモカー・代車費 | J38: =SUM(P38,U38,Z38,AK38,AP38,AU38,BF38,BK38,BP38,CA38,CF38,CK38) -> 0 | K38: =SUM(Q38,V38,AA38,AL38,AQ38,AV38,BG38,BL38,BQ38,CB38,CG38,CL38) -> 0 | L38: =SUM(R38,W38,AB38,AM38,AR38,AW38,BH38,BM38,BR38,CC38,CH38,CM38) -> 0 | M38: =SUM(S38,X38,AC38,AN38,AS38,AX38,BI38,BN38,BS38,CD38,CI38,CN38) -> 0 | N38: =SUM(T38,Y38,AD38,AO38,AT38,AY38,BJ38,BO38,BT38,CE38,CJ38,CO38) -> 0 | S38: =P38-Q38 -> 0 | X38: =U38-V38 -> 0 | AD38: =AA38-AB38 -> 0 | AH38: =AE38-AF38 -> 0 | AN38: =AK38-AL38 -> 0 | AS38: =AP38-AQ38 -> 0 | AX38: =AU38-AV38 -> 0 | BC38: =AZ38-BA38 -> 0 | BI38: =BF38-BG38 -> 0 | BN38: =BK38-BL38 -> 0 | BS38: =BP38-BQ38 -> 0 | BX38: =BU38-BV38 -> 0 | CD38: =CA38-CB38 -> 0 | CI38: =CF38-CG38 -> 0 | CN38: =CK38-CL38 -> 0 | CS38: =CP38-CQ38 -> 0
A39: 30 | F39: 本部負担金 | J39: =SUM(P39,U39,Z39,AK39,AP39,AU39,BF39,BK39,BP39,CA39,CF39,CK39) -> 0 | K39: =SUM(Q39,V39,AA39,AL39,AQ39,AV39,BG39,BL39,BQ39,CB39,CG39,CL39) -> 0 | L39: =SUM(R39,W39,AB39,AM39,AR39,AW39,BH39,BM39,BR39,CC39,CH39,CM39) -> 0 | M39: =SUM(S39,X39,AC39,AN39,AS39,AX39,BI39,BN39,BS39,CD39,CI39,CN39) -> 0 | N39: =SUM(T39,Y39,AD39,AO39,AT39,AY39,BJ39,BO39,BT39,CE39,CJ39,CO39) -> 0 | S39: =P39-Q39 -> 0 | X39: =U39-V39 -> 0 | AD39: =AA39-AB39 -> 0 | AH39: =AE39-AF39 -> 0 | AN39: =AK39-AL39 -> 0 | AS39: =AP39-AQ39 -> 0 | AX39: =AU39-AV39 -> 0 | BC39: =AZ39-BA39 -> 0 | BI39: =BF39-BG39 -> 0 | BN39: =BK39-BL39 -> 0 | BS39: =BP39-BQ39 -> 0 | BX39: =BU39-BV39 -> 0 | CD39: =CA39-CB39 -> 0 | CI39: =CF39-CG39 -> 0 | CN39: =CK39-CL39 -> 0 | CS39: =CP39-CQ39 -> 0
A40: 31 | F40: 小計 | J40: =SUM(P40,U40,Z40,AK40,AP40,AU40,BF40,BK40,BP40,CA40,CF40,CK40) -> 0 | K40: =SUM(Q40,V40,AA40,AL40,AQ40,AV40,BG40,BL40,BQ40,CB40,CG40,CL40) -> 0 | L40: =SUM(R40,W40,AB40,AM40,AR40,AW40,BH40,BM40,BR40,CC40,CH40,CM40) -> 0 | M40: =SUM(S40,X40,AC40,AN40,AS40,AX40,BI40,BN40,BS40,CD40,CI40,CN40) -> 0 | N40: =SUM(T40,Y40,AD40,AO40,AT40,AY40,BJ40,BO40,BT40,CE40,CJ40,CO40) -> 0 | S40: =P40-Q40 -> 0 | X40: =U40-V40 -> 0 | AD40: =AA40-AB40 -> 0 | AH40: =AE40-AF40 -> 0 | AN40: =AK40-AL40 -> 0 | AS40: =AP40-AQ40 -> 0 | AX40: =AU40-AV40 -> 0 | BC40: =AZ40-BA40 -> 0 | BI40: =BF40-BG40 -> 0 | BN40: =BK40-BL40 -> 0 | BS40: =BP40-BQ40 -> 0 | BX40: =BU40-BV40 -> 0 | CD40: =CA40-CB40 -> 0 | CI40: =CF40-CG40 -> 0 | CN40: =CK40-CL40 -> 0 | CS40: =CP40-CQ40 -> 0
A41: 32 | E41: 新車限界利益 | J41: =SUM(P41,U41,Z41,AK41,AP41,AU41,BF41,BK41,BP41,CA41,CF41,CK41) -> 0 | K41: =SUM(Q41,V41,AA41,AL41,AQ41,AV41,BG41,BL41,BQ41,CB41,CG41,CL41) -> 0 | L41: =SUM(R41,W41,AB41,AM41,AR41,AW41,BH41,BM41,BR41,CC41,CH41,CM41) -> 0 | M41: =SUM(S41,X41,AC41,AN41,AS41,AX41,BI41,BN41,BS41,CD41,CI41,CN41) -> 0 | N41: =SUM(T41,Y41,AD41,AO41,AT41,AY41,BJ41,BO41,BT41,CE41,CJ41,CO41) -> 0 | S41: =P41-Q41 -> 0 | X41: =U41-V41 -> 0 | AD41: =AA41-AB41 -> 0 | AH41: =AE41-AF41 -> 0 | AN41: =AK41-AL41 -> 0 | AS41: =AP41-AQ41 -> 0 | AX41: =AU41-AV41 -> 0 | BC41: =AZ41-BA41 -> 0 | BI41: =BF41-BG41 -> 0 | BN41: =BK41-BL41 -> 0 | BS41: =BP41-BQ41 -> 0 | BX41: =BU41-BV41 -> 0 | CD41: =CA41-CB41 -> 0 | CI41: =CF41-CG41 -> 0 | CN41: =CK41-CL41 -> 0 | CS41: =CP41-CQ41 -> 0
A42: 33 | D42: 中古車 | E42: 直売 | F42: 直売台数 | J42: =SUM(P42,U42,Z42,AK42,AP42,AU42,BF42,BK42,BP42,CA42,CF42,CK42) -> 0 | K42: =SUM(Q42,V42,AA42,AL42,AQ42,AV42,BG42,BL42,BQ42,CB42,CG42,CL42) -> 0 | L42: =SUM(R42,W42,AB42,AM42,AR42,AW42,BH42,BM42,BR42,CC42,CH42,CM42) -> 0 | M42: =SUM(S42,X42,AC42,AN42,AS42,AX42,BI42,BN42,BS42,CD42,CI42,CN42) -> 0 | N42: =SUM(T42,Y42,AD42,AO42,AT42,AY42,BJ42,BO42,BT42,CE42,CJ42,CO42) -> 0 | S42: =P42-Q42 -> 0 | X42: =U42-V42 -> 0 | AD42: =AA42-AB42 -> 0 | AH42: =AE42-AF42 -> 0 | AN42: =AK42-AL42 -> 0 | AS42: =AP42-AQ42 -> 0 | AX42: =AU42-AV42 -> 0 | BC42: =AZ42-BA42 -> 0 | BI42: =BF42-BG42 -> 0 | BN42: =BK42-BL42 -> 0 | BS42: =BP42-BQ42 -> 0 | BX42: =BU42-BV42 -> 0 | CD42: =CA42-CB42 -> 0 | CI42: =CF42-CG42 -> 0 | CN42: =CK42-CL42 -> 0 | CS42: =CP42-CQ42 -> 0
A43: 34 | F43: 売上金額 | J43: =SUM(P43,U43,Z43,AK43,AP43,AU43,BF43,BK43,BP43,CA43,CF43,CK43) -> 0 | K43: =SUM(Q43,V43,AA43,AL43,AQ43,AV43,BG43,BL43,BQ43,CB43,CG43,CL43) -> 0 | L43: =SUM(R43,W43,AB43,AM43,AR43,AW43,BH43,BM43,BR43,CC43,CH43,CM43) -> 0 | M43: =SUM(S43,X43,AC43,AN43,AS43,AX43,BI43,BN43,BS43,CD43,CI43,CN43) -> 0 | N43: =SUM(T43,Y43,AD43,AO43,AT43,AY43,BJ43,BO43,BT43,CE43,CJ43,CO43) -> 0 | S43: =P43-Q43 -> 0 | X43: =U43-V43 -> 0 | AD43: =AA43-AB43 -> 0 | AH43: =AE43-AF43 -> 0 | AN43: =AK43-AL43 -> 0 | AS43: =AP43-AQ43 -> 0 | AX43: =AU43-AV43 -> 0 | BC43: =AZ43-BA43 -> 0 | BI43: =BF43-BG43 -> 0 | BN43: =BK43-BL43 -> 0 | BS43: =BP43-BQ43 -> 0 | BX43: =BU43-BV43 -> 0 | CD43: =CA43-CB43 -> 0 | CI43: =CF43-CG43 -> 0 | CN43: =CK43-CL43 -> 0 | CS43: =CP43-CQ43 -> 0
A44: 35 | F44: 車両本体利益 | J44: =SUM(P44,U44,Z44,AK44,AP44,AU44,BF44,BK44,BP44,CA44,CF44,CK44) -> 0 | K44: =SUM(Q44,V44,AA44,AL44,AQ44,AV44,BG44,BL44,BQ44,CB44,CG44,CL44) -> 0 | L44: =SUM(R44,W44,AB44,AM44,AR44,AW44,BH44,BM44,BR44,CC44,CH44,CM44) -> 0 | M44: =SUM(S44,X44,AC44,AN44,AS44,AX44,BI44,BN44,BS44,CD44,CI44,CN44) -> 0 | N44: =SUM(T44,Y44,AD44,AO44,AT44,AY44,BJ44,BO44,BT44,CE44,CJ44,CO44) -> 0 | S44: =P44-Q44 -> 0 | X44: =U44-V44 -> 0 | AD44: =AA44-AB44 -> 0 | AH44: =AE44-AF44 -> 0 | AN44: =AK44-AL44 -> 0 | AS44: =AP44-AQ44 -> 0 | AX44: =AU44-AV44 -> 0 | BC44: =AZ44-BA44 -> 0 | BI44: =BF44-BG44 -> 0 | BN44: =BK44-BL44 -> 0 | BS44: =BP44-BQ44 -> 0 | BX44: =BU44-BV44 -> 0 | CD44: =CA44-CB44 -> 0 | CI44: =CF44-CG44 -> 0 | CN44: =CK44-CL44 -> 0 | CS44: =CP44-CQ44 -> 0
A45: 36 | F45: 車両収入手数料 | J45: =SUM(P45,U45,Z45,AK45,AP45,AU45,BF45,BK45,BP45,CA45,CF45,CK45) -> 0 | K45: =SUM(Q45,V45,AA45,AL45,AQ45,AV45,BG45,BL45,BQ45,CB45,CG45,CL45) -> 0 | L45: =SUM(R45,W45,AB45,AM45,AR45,AW45,BH45,BM45,BR45,CC45,CH45,CM45) -> 0 | M45: =SUM(S45,X45,AC45,AN45,AS45,AX45,BI45,BN45,BS45,CD45,CI45,CN45) -> 0 | N45: =SUM(T45,Y45,AD45,AO45,AT45,AY45,BJ45,BO45,BT45,CE45,CJ45,CO45) -> 0 | S45: =P45-Q45 -> 0 | X45: =U45-V45 -> 0 | AD45: =AA45-AB45 -> 0 | AH45: =AE45-AF45 -> 0 | AN45: =AK45-AL45 -> 0 | AS45: =AP45-AQ45 -> 0 | AX45: =AU45-AV45 -> 0 | BC45: =AZ45-BA45 -> 0 | BI45: =BF45-BG45 -> 0 | BN45: =BK45-BL45 -> 0 | BS45: =BP45-BQ45 -> 0 | BX45: =BU45-BV45 -> 0 | CD45: =CA45-CB45 -> 0 | CI45: =CF45-CG45 -> 0 | CN45: =CK45-CL45 -> 0 | CS45: =CP45-CQ45 -> 0
A46: 37 | F46: 登録収入手数料 | J46: =SUM(P46,U46,Z46,AK46,AP46,AU46,BF46,BK46,BP46,CA46,CF46,CK46) -> 0 | K46: =SUM(Q46,V46,AA46,AL46,AQ46,AV46,BG46,BL46,BQ46,CB46,CG46,CL46) -> 0 | L46: =SUM(R46,W46,AB46,AM46,AR46,AW46,BH46,BM46,BR46,CC46,CH46,CM46) -> 0 | M46: =SUM(S46,X46,AC46,AN46,AS46,AX46,BI46,BN46,BS46,CD46,CI46,CN46) -> 0 | N46: =SUM(T46,Y46,AD46,AO46,AT46,AY46,BJ46,BO46,BT46,CE46,CJ46,CO46) -> 0 | S46: =P46-Q46 -> 0 | X46: =U46-V46 -> 0 | AD46: =AA46-AB46 -> 0 | AH46: =AE46-AF46 -> 0 | AN46: =AK46-AL46 -> 0 | AS46: =AP46-AQ46 -> 0 | AX46: =AU46-AV46 -> 0 | BC46: =AZ46-BA46 -> 0 | BI46: =BF46-BG46 -> 0 | BN46: =BK46-BL46 -> 0 | BS46: =BP46-BQ46 -> 0 | BX46: =BU46-BV46 -> 0 | CD46: =CA46-CB46 -> 0 | CI46: =CF46-CG46 -> 0 | CN46: =CK46-CL46 -> 0 | CS46: =CP46-CQ46 -> 0
A47: 38 | F47: クレジット利益 | J47: =SUM(P47,U47,Z47,AK47,AP47,AU47,BF47,BK47,BP47,CA47,CF47,CK47) -> 0 | K47: =SUM(Q47,V47,AA47,AL47,AQ47,AV47,BG47,BL47,BQ47,CB47,CG47,CL47) -> 0 | L47: =SUM(R47,W47,AB47,AM47,AR47,AW47,BH47,BM47,BR47,CC47,CH47,CM47) -> 0 | M47: =SUM(S47,X47,AC47,AN47,AS47,AX47,BI47,BN47,BS47,CD47,CI47,CN47) -> 0 | N47: =SUM(T47,Y47,AD47,AO47,AT47,AY47,BJ47,BO47,BT47,CE47,CJ47,CO47) -> 0 | S47: =P47-Q47 -> 0 | X47: =U47-V47 -> 0 | AD47: =AA47-AB47 -> 0 | AH47: =AE47-AF47 -> 0 | AN47: =AK47-AL47 -> 0 | AS47: =AP47-AQ47 -> 0 | AX47: =AU47-AV47 -> 0 | BC47: =AZ47-BA47 -> 0 | BI47: =BF47-BG47 -> 0 | BN47: =BK47-BL47 -> 0 | BS47: =BP47-BQ47 -> 0 | BX47: =BU47-BV47 -> 0 | CD47: =CA47-CB47 -> 0 | CI47: =CF47-CG47 -> 0 | CN47: =CK47-CL47 -> 0 | CS47: =CP47-CQ47 -> 0
A48: 39 | F48: 直売総粗利 | J48: =SUM(P48,U48,Z48,AK48,AP48,AU48,BF48,BK48,BP48,CA48,CF48,CK48) -> 0 | K48: =SUM(Q48,V48,AA48,AL48,AQ48,AV48,BG48,BL48,BQ48,CB48,CG48,CL48) -> 0 | L48: =SUM(R48,W48,AB48,AM48,AR48,AW48,BH48,BM48,BR48,CC48,CH48,CM48) -> 0 | M48: =SUM(S48,X48,AC48,AN48,AS48,AX48,BI48,BN48,BS48,CD48,CI48,CN48) -> 0 | N48: =SUM(T48,Y48,AD48,AO48,AT48,AY48,BJ48,BO48,BT48,CE48,CJ48,CO48) -> 0 | S48: =P48-Q48 -> 0 | X48: =U48-V48 -> 0 | AD48: =AA48-AB48 -> 0 | AH48: =AE48-AF48 -> 0 | AN48: =AK48-AL48 -> 0 | AS48: =AP48-AQ48 -> 0 | AX48: =AU48-AV48 -> 0 | BC48: =AZ48-BA48 -> 0 | BI48: =BF48-BG48 -> 0 | BN48: =BK48-BL48 -> 0 | BS48: =BP48-BQ48 -> 0 | BX48: =BU48-BV48 -> 0 | CD48: =CA48-CB48 -> 0 | CI48: =CF48-CG48 -> 0 | CN48: =CK48-CL48 -> 0 | CS48: =CP48-CQ48 -> 0
A49: 40 | E49: 業売 | F49: 業売台数 | J49: =SUM(P49,U49,Z49,AK49,AP49,AU49,BF49,BK49,BP49,CA49,CF49,CK49) -> 0 | K49: =SUM(Q49,V49,AA49,AL49,AQ49,AV49,BG49,BL49,BQ49,CB49,CG49,CL49) -> 0 | L49: =SUM(R49,W49,AB49,AM49,AR49,AW49,BH49,BM49,BR49,CC49,CH49,CM49) -> 0 | M49: =SUM(S49,X49,AC49,AN49,AS49,AX49,BI49,BN49,BS49,CD49,CI49,CN49) -> 0 | N49: =SUM(T49,Y49,AD49,AO49,AT49,AY49,BJ49,BO49,BT49,CE49,CJ49,CO49) -> 0 | S49: =P49-Q49 -> 0 | X49: =U49-V49 -> 0 | AD49: =AA49-AB49 -> 0 | AH49: =AE49-AF49 -> 0 | AN49: =AK49-AL49 -> 0 | AS49: =AP49-AQ49 -> 0 | AX49: =AU49-AV49 -> 0 | BC49: =AZ49-BA49 -> 0 | BI49: =BF49-BG49 -> 0 | BN49: =BK49-BL49 -> 0 | BS49: =BP49-BQ49 -> 0 | BX49: =BU49-BV49 -> 0 | CD49: =CA49-CB49 -> 0 | CI49: =CF49-CG49 -> 0 | CN49: =CK49-CL49 -> 0 | CS49: =CP49-CQ49 -> 0
A50: 41 | F50: 業売売上 | J50: =SUM(P50,U50,Z50,AK50,AP50,AU50,BF50,BK50,BP50,CA50,CF50,CK50) -> 0 | K50: =SUM(Q50,V50,AA50,AL50,AQ50,AV50,BG50,BL50,BQ50,CB50,CG50,CL50) -> 0 | L50: =SUM(R50,W50,AB50,AM50,AR50,AW50,BH50,BM50,BR50,CC50,CH50,CM50) -> 0 | M50: =SUM(S50,X50,AC50,AN50,AS50,AX50,BI50,BN50,BS50,CD50,CI50,CN50) -> 0 | N50: =SUM(T50,Y50,AD50,AO50,AT50,AY50,BJ50,BO50,BT50,CE50,CJ50,CO50) -> 0 | S50: =P50-Q50 -> 0 | X50: =U50-V50 -> 0 | AD50: =AA50-AB50 -> 0 | AH50: =AE50-AF50 -> 0 | AN50: =AK50-AL50 -> 0 | AS50: =AP50-AQ50 -> 0 | AX50: =AU50-AV50 -> 0 | BC50: =AZ50-BA50 -> 0 | BI50: =BF50-BG50 -> 0 | BN50: =BK50-BL50 -> 0 | BS50: =BP50-BQ50 -> 0 | BX50: =BU50-BV50 -> 0 | CD50: =CA50-CB50 -> 0 | CI50: =CF50-CG50 -> 0 | CN50: =CK50-CL50 -> 0 | CS50: =CP50-CQ50 -> 0
A51: 42 | F51: 業売放出台数 | J51: =SUM(P51,U51,Z51,AK51,AP51,AU51,BF51,BK51,BP51,CA51,CF51,CK51) -> 0 | K51: =SUM(Q51,V51,AA51,AL51,AQ51,AV51,BG51,BL51,BQ51,CB51,CG51,CL51) -> 0 | L51: =SUM(R51,W51,AB51,AM51,AR51,AW51,BH51,BM51,BR51,CC51,CH51,CM51) -> 0 | M51: =SUM(S51,X51,AC51,AN51,AS51,AX51,BI51,BN51,BS51,CD51,CI51,CN51) -> 0 | N51: =SUM(T51,Y51,AD51,AO51,AT51,AY51,BJ51,BO51,BT51,CE51,CJ51,CO51) -> 0 | S51: =P51-Q51 -> 0 | X51: =U51-V51 -> 0 | AD51: =AA51-AB51 -> 0 | AH51: =AE51-AF51 -> 0 | AN51: =AK51-AL51 -> 0 | AS51: =AP51-AQ51 -> 0 | AX51: =AU51-AV51 -> 0 | BC51: =AZ51-BA51 -> 0 | BI51: =BF51-BG51 -> 0 | BN51: =BK51-BL51 -> 0 | BS51: =BP51-BQ51 -> 0 | BX51: =BU51-BV51 -> 0 | CD51: =CA51-CB51 -> 0 | CI51: =CF51-CG51 -> 0 | CN51: =CK51-CL51 -> 0 | CS51: =CP51-CQ51 -> 0
A52: 43 | F52: 業売放出売上 | J52: =SUM(P52,U52,Z52,AK52,AP52,AU52,BF52,BK52,BP52,CA52,CF52,CK52) -> 0 | K52: =SUM(Q52,V52,AA52,AL52,AQ52,AV52,BG52,BL52,BQ52,CB52,CG52,CL52) -> 0 | L52: =SUM(R52,W52,AB52,AM52,AR52,AW52,BH52,BM52,BR52,CC52,CH52,CM52) -> 0 | M52: =SUM(S52,X52,AC52,AN52,AS52,AX52,BI52,BN52,BS52,CD52,CI52,CN52) -> 0 | N52: =SUM(T52,Y52,AD52,AO52,AT52,AY52,BJ52,BO52,BT52,CE52,CJ52,CO52) -> 0 | S52: =P52-Q52 -> 0 | X52: =U52-V52 -> 0 | AD52: =AA52-AB52 -> 0 | AH52: =AE52-AF52 -> 0 | AN52: =AK52-AL52 -> 0 | AS52: =AP52-AQ52 -> 0 | AX52: =AU52-AV52 -> 0 | BC52: =AZ52-BA52 -> 0 | BI52: =BF52-BG52 -> 0 | BN52: =BK52-BL52 -> 0 | BS52: =BP52-BQ52 -> 0 | BX52: =BU52-BV52 -> 0 | CD52: =CA52-CB52 -> 0 | CI52: =CF52-CG52 -> 0 | CN52: =CK52-CL52 -> 0 | CS52: =CP52-CQ52 -> 0
A53: 44 | F53: 業売スクラップ台数 | J53: =SUM(P53,U53,Z53,AK53,AP53,AU53,BF53,BK53,BP53,CA53,CF53,CK53) -> 0 | K53: =SUM(Q53,V53,AA53,AL53,AQ53,AV53,BG53,BL53,BQ53,CB53,CG53,CL53) -> 0 | L53: =SUM(R53,W53,AB53,AM53,AR53,AW53,BH53,BM53,BR53,CC53,CH53,CM53) -> 0 | M53: =SUM(S53,X53,AC53,AN53,AS53,AX53,BI53,BN53,BS53,CD53,CI53,CN53) -> 0 | N53: =SUM(T53,Y53,AD53,AO53,AT53,AY53,BJ53,BO53,BT53,CE53,CJ53,CO53) -> 0 | S53: =P53-Q53 -> 0 | X53: =U53-V53 -> 0 | AD53: =AA53-AB53 -> 0 | AH53: =AE53-AF53 -> 0 | AN53: =AK53-AL53 -> 0 | AS53: =AP53-AQ53 -> 0 | AX53: =AU53-AV53 -> 0 | BC53: =AZ53-BA53 -> 0 | BI53: =BF53-BG53 -> 0 | BN53: =BK53-BL53 -> 0 | BS53: =BP53-BQ53 -> 0 | BX53: =BU53-BV53 -> 0 | CD53: =CA53-CB53 -> 0 | CI53: =CF53-CG53 -> 0 | CN53: =CK53-CL53 -> 0 | CS53: =CP53-CQ53 -> 0
A54: 45 | F54: 業売スクラップ売上 | J54: =SUM(P54,U54,Z54,AK54,AP54,AU54,BF54,BK54,BP54,CA54,CF54,CK54) -> 0 | K54: =SUM(Q54,V54,AA54,AL54,AQ54,AV54,BG54,BL54,BQ54,CB54,CG54,CL54) -> 0 | L54: =SUM(R54,W54,AB54,AM54,AR54,AW54,BH54,BM54,BR54,CC54,CH54,CM54) -> 0 | M54: =SUM(S54,X54,AC54,AN54,AS54,AX54,BI54,BN54,BS54,CD54,CI54,CN54) -> 0 | N54: =SUM(T54,Y54,AD54,AO54,AT54,AY54,BJ54,BO54,BT54,CE54,CJ54,CO54) -> 0 | S54: =P54-Q54 -> 0 | X54: =U54-V54 -> 0 | AD54: =AA54-AB54 -> 0 | AH54: =AE54-AF54 -> 0 | AN54: =AK54-AL54 -> 0 | AS54: =AP54-AQ54 -> 0 | AX54: =AU54-AV54 -> 0 | BC54: =AZ54-BA54 -> 0 | BI54: =BF54-BG54 -> 0 | BN54: =BK54-BL54 -> 0 | BS54: =BP54-BQ54 -> 0 | BX54: =BU54-BV54 -> 0 | CD54: =CA54-CB54 -> 0 | CI54: =CF54-CG54 -> 0 | CN54: =CK54-CL54 -> 0 | CS54: =CP54-CQ54 -> 0
A55: 46 | F55: 業販粗利益 | J55: =SUM(P55,U55,Z55,AK55,AP55,AU55,BF55,BK55,BP55,CA55,CF55,CK55) -> 0 | K55: =SUM(Q55,V55,AA55,AL55,AQ55,AV55,BG55,BL55,BQ55,CB55,CG55,CL55) -> 0 | L55: =SUM(R55,W55,AB55,AM55,AR55,AW55,BH55,BM55,BR55,CC55,CH55,CM55) -> 0 | M55: =SUM(S55,X55,AC55,AN55,AS55,AX55,BI55,BN55,BS55,CD55,CI55,CN55) -> 0 | N55: =SUM(T55,Y55,AD55,AO55,AT55,AY55,BJ55,BO55,BT55,CE55,CJ55,CO55) -> 0 | S55: =P55-Q55 -> 0 | X55: =U55-V55 -> 0 | AD55: =AA55-AB55 -> 0 | AH55: =AE55-AF55 -> 0 | AN55: =AK55-AL55 -> 0 | AS55: =AP55-AQ55 -> 0 | AX55: =AU55-AV55 -> 0 | BC55: =AZ55-BA55 -> 0 | BI55: =BF55-BG55 -> 0 | BN55: =BK55-BL55 -> 0 | BS55: =BP55-BQ55 -> 0 | BX55: =BU55-BV55 -> 0 | CD55: =CA55-CB55 -> 0 | CI55: =CF55-CG55 -> 0 | CN55: =CK55-CL55 -> 0 | CS55: =CP55-CQ55 -> 0
A56: 47 | E56: 台数合計 | J56: =SUM(P56,U56,Z56,AK56,AP56,AU56,BF56,BK56,BP56,CA56,CF56,CK56) -> 0 | K56: =SUM(Q56,V56,AA56,AL56,AQ56,AV56,BG56,BL56,BQ56,CB56,CG56,CL56) -> 0 | L56: =SUM(R56,W56,AB56,AM56,AR56,AW56,BH56,BM56,BR56,CC56,CH56,CM56) -> 0 | M56: =SUM(S56,X56,AC56,AN56,AS56,AX56,BI56,BN56,BS56,CD56,CI56,CN56) -> 0 | N56: =SUM(T56,Y56,AD56,AO56,AT56,AY56,BJ56,BO56,BT56,CE56,CJ56,CO56) -> 0 | S56: =P56-Q56 -> 0 | X56: =U56-V56 -> 0 | AD56: =AA56-AB56 -> 0 | AH56: =AE56-AF56 -> 0 | AN56: =AK56-AL56 -> 0 | AS56: =AP56-AQ56 -> 0 | AX56: =AU56-AV56 -> 0 | BC56: =AZ56-BA56 -> 0 | BI56: =BF56-BG56 -> 0 | BN56: =BK56-BL56 -> 0 | BS56: =BP56-BQ56 -> 0 | BX56: =BU56-BV56 -> 0 | CD56: =CA56-CB56 -> 0 | CI56: =CF56-CG56 -> 0 | CN56: =CK56-CL56 -> 0 | CS56: =CP56-CQ56 -> 0
A57: 48 | E57: 粗利益計 | J57: =SUM(P57,U57,Z57,AK57,AP57,AU57,BF57,BK57,BP57,CA57,CF57,CK57) -> 0 | K57: =SUM(Q57,V57,AA57,AL57,AQ57,AV57,BG57,BL57,BQ57,CB57,CG57,CL57) -> 0 | L57: =SUM(R57,W57,AB57,AM57,AR57,AW57,BH57,BM57,BR57,CC57,CH57,CM57) -> 0 | M57: =SUM(S57,X57,AC57,AN57,AS57,AX57,BI57,BN57,BS57,CD57,CI57,CN57) -> 0 | N57: =SUM(T57,Y57,AD57,AO57,AT57,AY57,BJ57,BO57,BT57,CE57,CJ57,CO57) -> 0 | S57: =P57-Q57 -> 0 | X57: =U57-V57 -> 0 | AD57: =AA57-AB57 -> 0 | AH57: =AE57-AF57 -> 0 | AN57: =AK57-AL57 -> 0 | AS57: =AP57-AQ57 -> 0 | AX57: =AU57-AV57 -> 0 | BC57: =AZ57-BA57 -> 0 | BI57: =BF57-BG57 -> 0 | BN57: =BK57-BL57 -> 0 | BS57: =BP57-BQ57 -> 0 | BX57: =BU57-BV57 -> 0 | CD57: =CA57-CB57 -> 0 | CI57: =CF57-CG57 -> 0 | CN57: =CK57-CL57 -> 0 | CS57: =CP57-CQ57 -> 0
A58: 49 | E58: 車両収入手数料計 | J58: =SUM(P58,U58,Z58,AK58,AP58,AU58,BF58,BK58,BP58,CA58,CF58,CK58) -> 0 | K58: =SUM(Q58,V58,AA58,AL58,AQ58,AV58,BG58,BL58,BQ58,CB58,CG58,CL58) -> 0 | L58: =SUM(R58,W58,AB58,AM58,AR58,AW58,BH58,BM58,BR58,CC58,CH58,CM58) -> 0 | M58: =SUM(S58,X58,AC58,AN58,AS58,AX58,BI58,BN58,BS58,CD58,CI58,CN58) -> 0 | N58: =SUM(T58,Y58,AD58,AO58,AT58,AY58,BJ58,BO58,BT58,CE58,CJ58,CO58) -> 0 | S58: =P58-Q58 -> 0 | X58: =U58-V58 -> 0 | AD58: =AA58-AB58 -> 0 | AH58: =AE58-AF58 -> 0 | AN58: =AK58-AL58 -> 0 | AS58: =AP58-AQ58 -> 0 | AX58: =AU58-AV58 -> 0 | BC58: =AZ58-BA58 -> 0 | BI58: =BF58-BG58 -> 0 | BN58: =BK58-BL58 -> 0 | BS58: =BP58-BQ58 -> 0 | BX58: =BU58-BV58 -> 0 | CD58: =CA58-CB58 -> 0 | CI58: =CF58-CG58 -> 0 | CN58: =CK58-CL58 -> 0 | CS58: =CP58-CQ58 -> 0
A59: 50 | E59: 登録収入手数料計 | J59: =SUM(P59,U59,Z59,AK59,AP59,AU59,BF59,BK59,BP59,CA59,CF59,CK59) -> 0 | K59: =SUM(Q59,V59,AA59,AL59,AQ59,AV59,BG59,BL59,BQ59,CB59,CG59,CL59) -> 0 | L59: =SUM(R59,W59,AB59,AM59,AR59,AW59,BH59,BM59,BR59,CC59,CH59,CM59) -> 0 | M59: =SUM(S59,X59,AC59,AN59,AS59,AX59,BI59,BN59,BS59,CD59,CI59,CN59) -> 0 | N59: =SUM(T59,Y59,AD59,AO59,AT59,AY59,BJ59,BO59,BT59,CE59,CJ59,CO59) -> 0 | S59: =P59-Q59 -> 0 | X59: =U59-V59 -> 0 | AD59: =AA59-AB59 -> 0 | AH59: =AE59-AF59 -> 0 | AN59: =AK59-AL59 -> 0 | AS59: =AP59-AQ59 -> 0 | AX59: =AU59-AV59 -> 0 | BC59: =AZ59-BA59 -> 0 | BI59: =BF59-BG59 -> 0 | BN59: =BK59-BL59 -> 0 | BS59: =BP59-BQ59 -> 0 | BX59: =BU59-BV59 -> 0 | CD59: =CA59-CB59 -> 0 | CI59: =CF59-CG59 -> 0 | CN59: =CK59-CL59 -> 0 | CS59: =CP59-CQ59 -> 0
A60: 51 | E60: クレジット利益計 | J60: =SUM(P60,U60,Z60,AK60,AP60,AU60,BF60,BK60,BP60,CA60,CF60,CK60) -> 0 | K60: =SUM(Q60,V60,AA60,AL60,AQ60,AV60,BG60,BL60,BQ60,CB60,CG60,CL60) -> 0 | L60: =SUM(R60,W60,AB60,AM60,AR60,AW60,BH60,BM60,BR60,CC60,CH60,CM60) -> 0 | M60: =SUM(S60,X60,AC60,AN60,AS60,AX60,BI60,BN60,BS60,CD60,CI60,CN60) -> 0 | N60: =SUM(T60,Y60,AD60,AO60,AT60,AY60,BJ60,BO60,BT60,CE60,CJ60,CO60) -> 0 | S60: =P60-Q60 -> 0 | X60: =U60-V60 -> 0 | AD60: =AA60-AB60 -> 0 | AH60: =AE60-AF60 -> 0 | AN60: =AK60-AL60 -> 0 | AS60: =AP60-AQ60 -> 0 | AX60: =AU60-AV60 -> 0 | BC60: =AZ60-BA60 -> 0 | BI60: =BF60-BG60 -> 0 | BN60: =BK60-BL60 -> 0 | BS60: =BP60-BQ60 -> 0 | BX60: =BU60-BV60 -> 0 | CD60: =CA60-CB60 -> 0 | CI60: =CF60-CG60 -> 0 | CN60: =CK60-CL60 -> 0 | CS60: =CP60-CQ60 -> 0
A61: 52 | E61: 再生員給与 | J61: =SUM(P61,U61,Z61,AK61,AP61,AU61,BF61,BK61,BP61,CA61,CF61,CK61) -> 0 | K61: =SUM(Q61,V61,AA61,AL61,AQ61,AV61,BG61,BL61,BQ61,CB61,CG61,CL61) -> 0 | L61: =SUM(R61,W61,AB61,AM61,AR61,AW61,BH61,BM61,BR61,CC61,CH61,CM61) -> 0 | M61: =SUM(S61,X61,AC61,AN61,AS61,AX61,BI61,BN61,BS61,CD61,CI61,CN61) -> 0 | N61: =SUM(T61,Y61,AD61,AO61,AT61,AY61,BJ61,BO61,BT61,CE61,CJ61,CO61) -> 0 | S61: =P61-Q61 -> 0 | X61: =U61-V61 -> 0 | AD61: =AA61-AB61 -> 0 | AH61: =AE61-AF61 -> 0 | AN61: =AK61-AL61 -> 0 | AS61: =AP61-AQ61 -> 0 | AX61: =AU61-AV61 -> 0 | BC61: =AZ61-BA61 -> 0 | BI61: =BF61-BG61 -> 0 | BN61: =BK61-BL61 -> 0 | BS61: =BP61-BQ61 -> 0 | BX61: =BU61-BV61 -> 0 | CD61: =CA61-CB61 -> 0 | CI61: =CF61-CG61 -> 0 | CN61: =CK61-CL61 -> 0 | CS61: =CP61-CQ61 -> 0
A62: 53 | E62: 中古車粗利合計 | J62: =SUM(P62,U62,Z62,AK62,AP62,AU62,BF62,BK62,BP62,CA62,CF62,CK62) -> 0 | K62: =SUM(Q62,V62,AA62,AL62,AQ62,AV62,BG62,BL62,BQ62,CB62,CG62,CL62) -> 0 | L62: =SUM(R62,W62,AB62,AM62,AR62,AW62,BH62,BM62,BR62,CC62,CH62,CM62) -> 0 | M62: =SUM(S62,X62,AC62,AN62,AS62,AX62,BI62,BN62,BS62,CD62,CI62,CN62) -> 0 | N62: =SUM(T62,Y62,AD62,AO62,AT62,AY62,BJ62,BO62,BT62,CE62,CJ62,CO62) -> 0 | S62: =P62-Q62 -> 0 | X62: =U62-V62 -> 0 | AD62: =AA62-AB62 -> 0 | AH62: =AE62-AF62 -> 0 | AN62: =AK62-AL62 -> 0 | AS62: =AP62-AQ62 -> 0 | AX62: =AU62-AV62 -> 0 | BC62: =AZ62-BA62 -> 0 | BI62: =BF62-BG62 -> 0 | BN62: =BK62-BL62 -> 0 | BS62: =BP62-BQ62 -> 0 | BX62: =BU62-BV62 -> 0 | CD62: =CA62-CB62 -> 0 | CI62: =CF62-CG62 -> 0 | CN62: =CK62-CL62 -> 0 | CS62: =CP62-CQ62 -> 0
A63: 54 | E63: 販売費 | F63: 販手・サービス・雑費 | J63: =SUM(P63,U63,Z63,AK63,AP63,AU63,BF63,BK63,BP63,CA63,CF63,CK63) -> 0 | K63: =SUM(Q63,V63,AA63,AL63,AQ63,AV63,BG63,BL63,BQ63,CB63,CG63,CL63) -> 0 | L63: =SUM(R63,W63,AB63,AM63,AR63,AW63,BH63,BM63,BR63,CC63,CH63,CM63) -> 0 | M63: =SUM(S63,X63,AC63,AN63,AS63,AX63,BI63,BN63,BS63,CD63,CI63,CN63) -> 0 | N63: =SUM(T63,Y63,AD63,AO63,AT63,AY63,BJ63,BO63,BT63,CE63,CJ63,CO63) -> 0 | S63: =P63-Q63 -> 0 | X63: =U63-V63 -> 0 | AD63: =AA63-AB63 -> 0 | AH63: =AE63-AF63 -> 0 | AN63: =AK63-AL63 -> 0 | AS63: =AP63-AQ63 -> 0 | AX63: =AU63-AV63 -> 0 | BC63: =AZ63-BA63 -> 0 | BI63: =BF63-BG63 -> 0 | BN63: =BK63-BL63 -> 0 | BS63: =BP63-BQ63 -> 0 | BX63: =BU63-BV63 -> 0 | CD63: =CA63-CB63 -> 0 | CI63: =CF63-CG63 -> 0 | CN63: =CK63-CL63 -> 0 | CS63: =CP63-CQ63 -> 0
A64: 55 | F64: 納車費・運送保管費 | J64: =SUM(P64,U64,Z64,AK64,AP64,AU64,BF64,BK64,BP64,CA64,CF64,CK64) -> 0 | K64: =SUM(Q64,V64,AA64,AL64,AQ64,AV64,BG64,BL64,BQ64,CB64,CG64,CL64) -> 0 | L64: =SUM(R64,W64,AB64,AM64,AR64,AW64,BH64,BM64,BR64,CC64,CH64,CM64) -> 0 | M64: =SUM(S64,X64,AC64,AN64,AS64,AX64,BI64,BN64,BS64,CD64,CI64,CN64) -> 0 | N64: =SUM(T64,Y64,AD64,AO64,AT64,AY64,BJ64,BO64,BT64,CE64,CJ64,CO64) -> 0 | S64: =P64-Q64 -> 0 | X64: =U64-V64 -> 0 | AD64: =AA64-AB64 -> 0 | AH64: =AE64-AF64 -> 0 | AN64: =AK64-AL64 -> 0 | AS64: =AP64-AQ64 -> 0 | AX64: =AU64-AV64 -> 0 | BC64: =AZ64-BA64 -> 0 | BI64: =BF64-BG64 -> 0 | BN64: =BK64-BL64 -> 0 | BS64: =BP64-BQ64 -> 0 | BX64: =BU64-BV64 -> 0 | CD64: =CA64-CB64 -> 0 | CI64: =CF64-CG64 -> 0 | CN64: =CK64-CL64 -> 0 | CS64: =CP64-CQ64 -> 0
A65: 56 | F65: 広告宣伝費 | J65: =SUM(P65,U65,Z65,AK65,AP65,AU65,BF65,BK65,BP65,CA65,CF65,CK65) -> 0 | K65: =SUM(Q65,V65,AA65,AL65,AQ65,AV65,BG65,BL65,BQ65,CB65,CG65,CL65) -> 0 | L65: =SUM(R65,W65,AB65,AM65,AR65,AW65,BH65,BM65,BR65,CC65,CH65,CM65) -> 0 | M65: =SUM(S65,X65,AC65,AN65,AS65,AX65,BI65,BN65,BS65,CD65,CI65,CN65) -> 0 | N65: =SUM(T65,Y65,AD65,AO65,AT65,AY65,BJ65,BO65,BT65,CE65,CJ65,CO65) -> 0 | S65: =P65-Q65 -> 0 | X65: =U65-V65 -> 0 | AD65: =AA65-AB65 -> 0 | AH65: =AE65-AF65 -> 0 | AN65: =AK65-AL65 -> 0 | AS65: =AP65-AQ65 -> 0 | AX65: =AU65-AV65 -> 0 | BC65: =AZ65-BA65 -> 0 | BI65: =BF65-BG65 -> 0 | BN65: =BK65-BL65 -> 0 | BS65: =BP65-BQ65 -> 0 | BX65: =BU65-BV65 -> 0 | CD65: =CA65-CB65 -> 0 | CI65: =CF65-CG65 -> 0 | CN65: =CK65-CL65 -> 0 | CS65: =CP65-CQ65 -> 0
A66: 57 | F66: デモカー・代車費 | J66: =SUM(P66,U66,Z66,AK66,AP66,AU66,BF66,BK66,BP66,CA66,CF66,CK66) -> 0 | K66: =SUM(Q66,V66,AA66,AL66,AQ66,AV66,BG66,BL66,BQ66,CB66,CG66,CL66) -> 0 | L66: =SUM(R66,W66,AB66,AM66,AR66,AW66,BH66,BM66,BR66,CC66,CH66,CM66) -> 0 | M66: =SUM(S66,X66,AC66,AN66,AS66,AX66,BI66,BN66,BS66,CD66,CI66,CN66) -> 0 | N66: =SUM(T66,Y66,AD66,AO66,AT66,AY66,BJ66,BO66,BT66,CE66,CJ66,CO66) -> 0 | S66: =P66-Q66 -> 0 | X66: =U66-V66 -> 0 | AD66: =AA66-AB66 -> 0 | AH66: =AE66-AF66 -> 0 | AN66: =AK66-AL66 -> 0 | AS66: =AP66-AQ66 -> 0 | AX66: =AU66-AV66 -> 0 | BC66: =AZ66-BA66 -> 0 | BI66: =BF66-BG66 -> 0 | BN66: =BK66-BL66 -> 0 | BS66: =BP66-BQ66 -> 0 | BX66: =BU66-BV66 -> 0 | CD66: =CA66-CB66 -> 0 | CI66: =CF66-CG66 -> 0 | CN66: =CK66-CL66 -> 0 | CS66: =CP66-CQ66 -> 0
A67: 58 | F67: 本部負担金 | J67: =SUM(P67,U67,Z67,AK67,AP67,AU67,BF67,BK67,BP67,CA67,CF67,CK67) -> 0 | K67: =SUM(Q67,V67,AA67,AL67,AQ67,AV67,BG67,BL67,BQ67,CB67,CG67,CL67) -> 0 | L67: =SUM(R67,W67,AB67,AM67,AR67,AW67,BH67,BM67,BR67,CC67,CH67,CM67) -> 0 | M67: =SUM(S67,X67,AC67,AN67,AS67,AX67,BI67,BN67,BS67,CD67,CI67,CN67) -> 0 | N67: =SUM(T67,Y67,AD67,AO67,AT67,AY67,BJ67,BO67,BT67,CE67,CJ67,CO67) -> 0 | S67: =P67-Q67 -> 0 | X67: =U67-V67 -> 0 | AD67: =AA67-AB67 -> 0 | AH67: =AE67-AF67 -> 0 | AN67: =AK67-AL67 -> 0 | AS67: =AP67-AQ67 -> 0 | AX67: =AU67-AV67 -> 0 | BC67: =AZ67-BA67 -> 0 | BI67: =BF67-BG67 -> 0 | BN67: =BK67-BL67 -> 0 | BS67: =BP67-BQ67 -> 0 | BX67: =BU67-BV67 -> 0 | CD67: =CA67-CB67 -> 0 | CI67: =CF67-CG67 -> 0 | CN67: =CK67-CL67 -> 0 | CS67: =CP67-CQ67 -> 0
A68: 59 | F68: 小計 | J68: =SUM(P68,U68,Z68,AK68,AP68,AU68,BF68,BK68,BP68,CA68,CF68,CK68) -> 0 | K68: =SUM(Q68,V68,AA68,AL68,AQ68,AV68,BG68,BL68,BQ68,CB68,CG68,CL68) -> 0 | L68: =SUM(R68,W68,AB68,AM68,AR68,AW68,BH68,BM68,BR68,CC68,CH68,CM68) -> 0 | M68: =SUM(S68,X68,AC68,AN68,AS68,AX68,BI68,BN68,BS68,CD68,CI68,CN68) -> 0 | N68: =SUM(T68,Y68,AD68,AO68,AT68,AY68,BJ68,BO68,BT68,CE68,CJ68,CO68) -> 0 | S68: =P68-Q68 -> 0 | X68: =U68-V68 -> 0 | AD68: =AA68-AB68 -> 0 | AH68: =AE68-AF68 -> 0 | AN68: =AK68-AL68 -> 0 | AS68: =AP68-AQ68 -> 0 | AX68: =AU68-AV68 -> 0 | BC68: =AZ68-BA68 -> 0 | BI68: =BF68-BG68 -> 0 | BN68: =BK68-BL68 -> 0 | BS68: =BP68-BQ68 -> 0 | BX68: =BU68-BV68 -> 0 | CD68: =CA68-CB68 -> 0 | CI68: =CF68-CG68 -> 0 | CN68: =CK68-CL68 -> 0 | CS68: =CP68-CQ68 -> 0
A69: 60 | E69: 中古車限界利益 | J69: =SUM(P69,U69,Z69,AK69,AP69,AU69,BF69,BK69,BP69,CA69,CF69,CK69) -> 0 | K69: =SUM(Q69,V69,AA69,AL69,AQ69,AV69,BG69,BL69,BQ69,CB69,CG69,CL69) -> 0 | L69: =SUM(R69,W69,AB69,AM69,AR69,AW69,BH69,BM69,BR69,CC69,CH69,CM69) -> 0 | M69: =SUM(S69,X69,AC69,AN69,AS69,AX69,BI69,BN69,BS69,CD69,CI69,CN69) -> 0 | N69: =SUM(T69,Y69,AD69,AO69,AT69,AY69,BJ69,BO69,BT69,CE69,CJ69,CO69) -> 0 | S69: =P69-Q69 -> 0 | X69: =U69-V69 -> 0 | AD69: =AA69-AB69 -> 0 | AH69: =AE69-AF69 -> 0 | AN69: =AK69-AL69 -> 0 | AS69: =AP69-AQ69 -> 0 | AX69: =AU69-AV69 -> 0 | BC69: =AZ69-BA69 -> 0 | BI69: =BF69-BG69 -> 0 | BN69: =BK69-BL69 -> 0 | BS69: =BP69-BQ69 -> 0 | BX69: =BU69-BV69 -> 0 | CD69: =CA69-CB69 -> 0 | CI69: =CF69-CG69 -> 0 | CN69: =CK69-CL69 -> 0 | CS69: =CP69-CQ69 -> 0
A70: 61 | D70: 整備 | E70: 売上金額 | J70: =SUM(P70,U70,Z70,AK70,AP70,AU70,BF70,BK70,BP70,CA70,CF70,CK70) -> 0 | K70: =SUM(Q70,V70,AA70,AL70,AQ70,AV70,BG70,BL70,BQ70,CB70,CG70,CL70) -> 0 | L70: =SUM(R70,W70,AB70,AM70,AR70,AW70,BH70,BM70,BR70,CC70,CH70,CM70) -> 0 | M70: =SUM(S70,X70,AC70,AN70,AS70,AX70,BI70,BN70,BS70,CD70,CI70,CN70) -> 0 | N70: =SUM(T70,Y70,AD70,AO70,AT70,AY70,BJ70,BO70,BT70,CE70,CJ70,CO70) -> 0 | S70: =P70-Q70 -> 0 | X70: =U70-V70 -> 0 | AD70: =AA70-AB70 -> 0 | AH70: =AE70-AF70 -> 0 | AN70: =AK70-AL70 -> 0 | AS70: =AP70-AQ70 -> 0 | AX70: =AU70-AV70 -> 0 | BC70: =AZ70-BA70 -> 0 | BI70: =BF70-BG70 -> 0 | BN70: =BK70-BL70 -> 0 | BS70: =BP70-BQ70 -> 0 | BX70: =BU70-BV70 -> 0 | CD70: =CA70-CB70 -> 0 | CI70: =CF70-CG70 -> 0 | CN70: =CK70-CL70 -> 0 | CS70: =CP70-CQ70 -> 0
A71: 62 | F71: ＜内車両値引＞ | J71: =SUM(P71,U71,Z71,AK71,AP71,AU71,BF71,BK71,BP71,CA71,CF71,CK71) -> 0 | K71: =SUM(Q71,V71,AA71,AL71,AQ71,AV71,BG71,BL71,BQ71,CB71,CG71,CL71) -> 0 | L71: =SUM(R71,W71,AB71,AM71,AR71,AW71,BH71,BM71,BR71,CC71,CH71,CM71) -> 0 | M71: =SUM(S71,X71,AC71,AN71,AS71,AX71,BI71,BN71,BS71,CD71,CI71,CN71) -> 0 | N71: =SUM(T71,Y71,AD71,AO71,AT71,AY71,BJ71,BO71,BT71,CE71,CJ71,CO71) -> 0 | S71: =P71-Q71 -> 0 | X71: =U71-V71 -> 0 | AD71: =AA71-AB71 -> 0 | AH71: =AE71-AF71 -> 0 | AN71: =AK71-AL71 -> 0 | AS71: =AP71-AQ71 -> 0 | AX71: =AU71-AV71 -> 0 | BC71: =AZ71-BA71 -> 0 | BI71: =BF71-BG71 -> 0 | BN71: =BK71-BL71 -> 0 | BS71: =BP71-BQ71 -> 0 | BX71: =BU71-BV71 -> 0 | CD71: =CA71-CB71 -> 0 | CI71: =CF71-CG71 -> 0 | CN71: =CK71-CL71 -> 0 | CS71: =CP71-CQ71 -> 0
A72: 63 | E72: 車検 | F72: 台数 | J72: =SUM(P72,U72,Z72,AK72,AP72,AU72,BF72,BK72,BP72,CA72,CF72,CK72) -> 0 | K72: =SUM(Q72,V72,AA72,AL72,AQ72,AV72,BG72,BL72,BQ72,CB72,CG72,CL72) -> 0 | L72: =SUM(R72,W72,AB72,AM72,AR72,AW72,BH72,BM72,BR72,CC72,CH72,CM72) -> 0 | M72: =SUM(S72,X72,AC72,AN72,AS72,AX72,BI72,BN72,BS72,CD72,CI72,CN72) -> 0 | N72: =SUM(T72,Y72,AD72,AO72,AT72,AY72,BJ72,BO72,BT72,CE72,CJ72,CO72) -> 0 | S72: =P72-Q72 -> 0 | X72: =U72-V72 -> 0 | AD72: =AA72-AB72 -> 0 | AH72: =AE72-AF72 -> 0 | AN72: =AK72-AL72 -> 0 | AS72: =AP72-AQ72 -> 0 | AX72: =AU72-AV72 -> 0 | BC72: =AZ72-BA72 -> 0 | BI72: =BF72-BG72 -> 0 | BN72: =BK72-BL72 -> 0 | BS72: =BP72-BQ72 -> 0 | BX72: =BU72-BV72 -> 0 | CD72: =CA72-CB72 -> 0 | CI72: =CF72-CG72 -> 0 | CN72: =CK72-CL72 -> 0 | CS72: =CP72-CQ72 -> 0
A73: 64 | F73: 粗利益 | J73: =SUM(P73,U73,Z73,AK73,AP73,AU73,BF73,BK73,BP73,CA73,CF73,CK73) -> 0 | K73: =SUM(Q73,V73,AA73,AL73,AQ73,AV73,BG73,BL73,BQ73,CB73,CG73,CL73) -> 0 | L73: =SUM(R73,W73,AB73,AM73,AR73,AW73,BH73,BM73,BR73,CC73,CH73,CM73) -> 0 | M73: =SUM(S73,X73,AC73,AN73,AS73,AX73,BI73,BN73,BS73,CD73,CI73,CN73) -> 0 | N73: =SUM(T73,Y73,AD73,AO73,AT73,AY73,BJ73,BO73,BT73,CE73,CJ73,CO73) -> 0 | S73: =P73-Q73 -> 0 | X73: =U73-V73 -> 0 | AD73: =AA73-AB73 -> 0 | AH73: =AE73-AF73 -> 0 | AN73: =AK73-AL73 -> 0 | AS73: =AP73-AQ73 -> 0 | AX73: =AU73-AV73 -> 0 | BC73: =AZ73-BA73 -> 0 | BI73: =BF73-BG73 -> 0 | BN73: =BK73-BL73 -> 0 | BS73: =BP73-BQ73 -> 0 | BX73: =BU73-BV73 -> 0 | CD73: =CA73-CB73 -> 0 | CI73: =CF73-CG73 -> 0 | CN73: =CK73-CL73 -> 0 | CS73: =CP73-CQ73 -> 0
A74: 65 | E74: 点検 | F74: 台数 | J74: =SUM(P74,U74,Z74,AK74,AP74,AU74,BF74,BK74,BP74,CA74,CF74,CK74) -> 0 | K74: =SUM(Q74,V74,AA74,AL74,AQ74,AV74,BG74,BL74,BQ74,CB74,CG74,CL74) -> 0 | L74: =SUM(R74,W74,AB74,AM74,AR74,AW74,BH74,BM74,BR74,CC74,CH74,CM74) -> 0 | M74: =SUM(S74,X74,AC74,AN74,AS74,AX74,BI74,BN74,BS74,CD74,CI74,CN74) -> 0 | N74: =SUM(T74,Y74,AD74,AO74,AT74,AY74,BJ74,BO74,BT74,CE74,CJ74,CO74) -> 0 | S74: =P74-Q74 -> 0 | X74: =U74-V74 -> 0 | AD74: =AA74-AB74 -> 0 | AH74: =AE74-AF74 -> 0 | AN74: =AK74-AL74 -> 0 | AS74: =AP74-AQ74 -> 0 | AX74: =AU74-AV74 -> 0 | BC74: =AZ74-BA74 -> 0 | BI74: =BF74-BG74 -> 0 | BN74: =BK74-BL74 -> 0 | BS74: =BP74-BQ74 -> 0 | BX74: =BU74-BV74 -> 0 | CD74: =CA74-CB74 -> 0 | CI74: =CF74-CG74 -> 0 | CN74: =CK74-CL74 -> 0 | CS74: =CP74-CQ74 -> 0
A75: 66 | F75: 粗利益 | J75: =SUM(P75,U75,Z75,AK75,AP75,AU75,BF75,BK75,BP75,CA75,CF75,CK75) -> 0 | K75: =SUM(Q75,V75,AA75,AL75,AQ75,AV75,BG75,BL75,BQ75,CB75,CG75,CL75) -> 0 | L75: =SUM(R75,W75,AB75,AM75,AR75,AW75,BH75,BM75,BR75,CC75,CH75,CM75) -> 0 | M75: =SUM(S75,X75,AC75,AN75,AS75,AX75,BI75,BN75,BS75,CD75,CI75,CN75) -> 0 | N75: =SUM(T75,Y75,AD75,AO75,AT75,AY75,BJ75,BO75,BT75,CE75,CJ75,CO75) -> 0 | S75: =P75-Q75 -> 0 | X75: =U75-V75 -> 0 | AD75: =AA75-AB75 -> 0 | AH75: =AE75-AF75 -> 0 | AN75: =AK75-AL75 -> 0 | AS75: =AP75-AQ75 -> 0 | AX75: =AU75-AV75 -> 0 | BC75: =AZ75-BA75 -> 0 | BI75: =BF75-BG75 -> 0 | BN75: =BK75-BL75 -> 0 | BS75: =BP75-BQ75 -> 0 | BX75: =BU75-BV75 -> 0 | CD75: =CA75-CB75 -> 0 | CI75: =CF75-CG75 -> 0 | CN75: =CK75-CL75 -> 0 | CS75: =CP75-CQ75 -> 0
A76: 67 | E76: 一般 | F76: 台数 | J76: =SUM(P76,U76,Z76,AK76,AP76,AU76,BF76,BK76,BP76,CA76,CF76,CK76) -> 0 | K76: =SUM(Q76,V76,AA76,AL76,AQ76,AV76,BG76,BL76,BQ76,CB76,CG76,CL76) -> 0 | L76: =SUM(R76,W76,AB76,AM76,AR76,AW76,BH76,BM76,BR76,CC76,CH76,CM76) -> 0 | M76: =SUM(S76,X76,AC76,AN76,AS76,AX76,BI76,BN76,BS76,CD76,CI76,CN76) -> 0 | N76: =SUM(T76,Y76,AD76,AO76,AT76,AY76,BJ76,BO76,BT76,CE76,CJ76,CO76) -> 0 | S76: =P76-Q76 -> 0 | X76: =U76-V76 -> 0 | AD76: =AA76-AB76 -> 0 | AH76: =AE76-AF76 -> 0 | AN76: =AK76-AL76 -> 0 | AS76: =AP76-AQ76 -> 0 | AX76: =AU76-AV76 -> 0 | BC76: =AZ76-BA76 -> 0 | BI76: =BF76-BG76 -> 0 | BN76: =BK76-BL76 -> 0 | BS76: =BP76-BQ76 -> 0 | BX76: =BU76-BV76 -> 0 | CD76: =CA76-CB76 -> 0 | CI76: =CF76-CG76 -> 0 | CN76: =CK76-CL76 -> 0 | CS76: =CP76-CQ76 -> 0
A77: 68 | F77: 粗利益 | J77: =SUM(P77,U77,Z77,AK77,AP77,AU77,BF77,BK77,BP77,CA77,CF77,CK77) -> 0 | K77: =SUM(Q77,V77,AA77,AL77,AQ77,AV77,BG77,BL77,BQ77,CB77,CG77,CL77) -> 0 | L77: =SUM(R77,W77,AB77,AM77,AR77,AW77,BH77,BM77,BR77,CC77,CH77,CM77) -> 0 | M77: =SUM(S77,X77,AC77,AN77,AS77,AX77,BI77,BN77,BS77,CD77,CI77,CN77) -> 0 | N77: =SUM(T77,Y77,AD77,AO77,AT77,AY77,BJ77,BO77,BT77,CE77,CJ77,CO77) -> 0 | S77: =P77-Q77 -> 0 | X77: =U77-V77 -> 0 | AD77: =AA77-AB77 -> 0 | AH77: =AE77-AF77 -> 0 | AN77: =AK77-AL77 -> 0 | AS77: =AP77-AQ77 -> 0 | AX77: =AU77-AV77 -> 0 | BC77: =AZ77-BA77 -> 0 | BI77: =BF77-BG77 -> 0 | BN77: =BK77-BL77 -> 0 | BS77: =BP77-BQ77 -> 0 | BX77: =BU77-BV77 -> 0 | CD77: =CA77-CB77 -> 0 | CI77: =CF77-CG77 -> 0 | CN77: =CK77-CL77 -> 0 | CS77: =CP77-CQ77 -> 0
A78: 69 | E78: 外装 | F78: 台数 | J78: =SUM(P78,U78,Z78,AK78,AP78,AU78,BF78,BK78,BP78,CA78,CF78,CK78) -> 0 | K78: =SUM(Q78,V78,AA78,AL78,AQ78,AV78,BG78,BL78,BQ78,CB78,CG78,CL78) -> 0 | L78: =SUM(R78,W78,AB78,AM78,AR78,AW78,BH78,BM78,BR78,CC78,CH78,CM78) -> 0 | M78: =SUM(S78,X78,AC78,AN78,AS78,AX78,BI78,BN78,BS78,CD78,CI78,CN78) -> 0 | N78: =SUM(T78,Y78,AD78,AO78,AT78,AY78,BJ78,BO78,BT78,CE78,CJ78,CO78) -> 0 | S78: =P78-Q78 -> 0 | X78: =U78-V78 -> 0 | AD78: =AA78-AB78 -> 0 | AH78: =AE78-AF78 -> 0 | AN78: =AK78-AL78 -> 0 | AS78: =AP78-AQ78 -> 0 | AX78: =AU78-AV78 -> 0 | BC78: =AZ78-BA78 -> 0 | BI78: =BF78-BG78 -> 0 | BN78: =BK78-BL78 -> 0 | BS78: =BP78-BQ78 -> 0 | BX78: =BU78-BV78 -> 0 | CD78: =CA78-CB78 -> 0 | CI78: =CF78-CG78 -> 0 | CN78: =CK78-CL78 -> 0 | CS78: =CP78-CQ78 -> 0
A79: 70 | F79: 粗利益 | J79: =SUM(P79,U79,Z79,AK79,AP79,AU79,BF79,BK79,BP79,CA79,CF79,CK79) -> 0 | K79: =SUM(Q79,V79,AA79,AL79,AQ79,AV79,BG79,BL79,BQ79,CB79,CG79,CL79) -> 0 | L79: =SUM(R79,W79,AB79,AM79,AR79,AW79,BH79,BM79,BR79,CC79,CH79,CM79) -> 0 | M79: =SUM(S79,X79,AC79,AN79,AS79,AX79,BI79,BN79,BS79,CD79,CI79,CN79) -> 0 | N79: =SUM(T79,Y79,AD79,AO79,AT79,AY79,BJ79,BO79,BT79,CE79,CJ79,CO79) -> 0 | S79: =P79-Q79 -> 0 | X79: =U79-V79 -> 0 | AD79: =AA79-AB79 -> 0 | AH79: =AE79-AF79 -> 0 | AN79: =AK79-AL79 -> 0 | AS79: =AP79-AQ79 -> 0 | AX79: =AU79-AV79 -> 0 | BC79: =AZ79-BA79 -> 0 | BI79: =BF79-BG79 -> 0 | BN79: =BK79-BL79 -> 0 | BS79: =BP79-BQ79 -> 0 | BX79: =BU79-BV79 -> 0 | CD79: =CA79-CB79 -> 0 | CI79: =CF79-CG79 -> 0 | CN79: =CK79-CL79 -> 0 | CS79: =CP79-CQ79 -> 0
A80: 71 | E80: 部用品粗利 | J80: =SUM(P80,U80,Z80,AK80,AP80,AU80,BF80,BK80,BP80,CA80,CF80,CK80) -> 0 | K80: =SUM(Q80,V80,AA80,AL80,AQ80,AV80,BG80,BL80,BQ80,CB80,CG80,CL80) -> 0 | L80: =SUM(R80,W80,AB80,AM80,AR80,AW80,BH80,BM80,BR80,CC80,CH80,CM80) -> 0 | M80: =SUM(S80,X80,AC80,AN80,AS80,AX80,BI80,BN80,BS80,CD80,CI80,CN80) -> 0 | N80: =SUM(T80,Y80,AD80,AO80,AT80,AY80,BJ80,BO80,BT80,CE80,CJ80,CO80) -> 0 | S80: =P80-Q80 -> 0 | X80: =U80-V80 -> 0 | AD80: =AA80-AB80 -> 0 | AH80: =AE80-AF80 -> 0 | AN80: =AK80-AL80 -> 0 | AS80: =AP80-AQ80 -> 0 | AX80: =AU80-AV80 -> 0 | BC80: =AZ80-BA80 -> 0 | BI80: =BF80-BG80 -> 0 | BN80: =BK80-BL80 -> 0 | BS80: =BP80-BQ80 -> 0 | BX80: =BU80-BV80 -> 0 | CD80: =CA80-CB80 -> 0 | CI80: =CF80-CG80 -> 0 | CN80: =CK80-CL80 -> 0 | CS80: =CP80-CQ80 -> 0
A81: 72 | E81: 有償利益合計 | J81: =SUM(P81,U81,Z81,AK81,AP81,AU81,BF81,BK81,BP81,CA81,CF81,CK81) -> 0 | K81: =SUM(Q81,V81,AA81,AL81,AQ81,AV81,BG81,BL81,BQ81,CB81,CG81,CL81) -> 0 | L81: =SUM(R81,W81,AB81,AM81,AR81,AW81,BH81,BM81,BR81,CC81,CH81,CM81) -> 0 | M81: =SUM(S81,X81,AC81,AN81,AS81,AX81,BI81,BN81,BS81,CD81,CI81,CN81) -> 0 | N81: =SUM(T81,Y81,AD81,AO81,AT81,AY81,BJ81,BO81,BT81,CE81,CJ81,CO81) -> 0 | S81: =P81-Q81 -> 0 | X81: =U81-V81 -> 0 | AD81: =AA81-AB81 -> 0 | AH81: =AE81-AF81 -> 0 | AN81: =AK81-AL81 -> 0 | AS81: =AP81-AQ81 -> 0 | AX81: =AU81-AV81 -> 0 | BC81: =AZ81-BA81 -> 0 | BI81: =BF81-BG81 -> 0 | BN81: =BK81-BL81 -> 0 | BS81: =BP81-BQ81 -> 0 | BX81: =BU81-BV81 -> 0 | CD81: =CA81-CB81 -> 0 | CI81: =CF81-CG81 -> 0 | CN81: =CK81-CL81 -> 0 | CS81: =CP81-CQ81 -> 0
A82: 73 | E82: 材料消耗品費1+2 | J82: =SUM(P82,U82,Z82,AK82,AP82,AU82,BF82,BK82,BP82,CA82,CF82,CK82) -> 0 | K82: =SUM(Q82,V82,AA82,AL82,AQ82,AV82,BG82,BL82,BQ82,CB82,CG82,CL82) -> 0 | L82: =SUM(R82,W82,AB82,AM82,AR82,AW82,BH82,BM82,BR82,CC82,CH82,CM82) -> 0 | M82: =SUM(S82,X82,AC82,AN82,AS82,AX82,BI82,BN82,BS82,CD82,CI82,CN82) -> 0 | N82: =SUM(T82,Y82,AD82,AO82,AT82,AY82,BJ82,BO82,BT82,CE82,CJ82,CO82) -> 0 | S82: =P82-Q82 -> 0 | X82: =U82-V82 -> 0 | AD82: =AA82-AB82 -> 0 | AH82: =AE82-AF82 -> 0 | AN82: =AK82-AL82 -> 0 | AS82: =AP82-AQ82 -> 0 | AX82: =AU82-AV82 -> 0 | BC82: =AZ82-BA82 -> 0 | BI82: =BF82-BG82 -> 0 | BN82: =BK82-BL82 -> 0 | BS82: =BP82-BQ82 -> 0 | BX82: =BU82-BV82 -> 0 | CD82: =CA82-CB82 -> 0 | CI82: =CF82-CG82 -> 0 | CN82: =CK82-CL82 -> 0 | CS82: =CP82-CQ82 -> 0
A83: 74 | E83: 回送要員・代車費用 | J83: =SUM(P83,U83,Z83,AK83,AP83,AU83,BF83,BK83,BP83,CA83,CF83,CK83) -> 0 | K83: =SUM(Q83,V83,AA83,AL83,AQ83,AV83,BG83,BL83,BQ83,CB83,CG83,CL83) -> 0 | L83: =SUM(R83,W83,AB83,AM83,AR83,AW83,BH83,BM83,BR83,CC83,CH83,CM83) -> 0 | M83: =SUM(S83,X83,AC83,AN83,AS83,AX83,BI83,BN83,BS83,CD83,CI83,CN83) -> 0 | N83: =SUM(T83,Y83,AD83,AO83,AT83,AY83,BJ83,BO83,BT83,CE83,CJ83,CO83) -> 0 | S83: =P83-Q83 -> 0 | X83: =U83-V83 -> 0 | AD83: =AA83-AB83 -> 0 | AH83: =AE83-AF83 -> 0 | AN83: =AK83-AL83 -> 0 | AS83: =AP83-AQ83 -> 0 | AX83: =AU83-AV83 -> 0 | BC83: =AZ83-BA83 -> 0 | BI83: =BF83-BG83 -> 0 | BN83: =BK83-BL83 -> 0 | BS83: =BP83-BQ83 -> 0 | BX83: =BU83-BV83 -> 0 | CD83: =CA83-CB83 -> 0 | CI83: =CF83-CG83 -> 0 | CN83: =CK83-CL83 -> 0 | CS83: =CP83-CQ83 -> 0
A84: 75 | E84: 有償粗利合計 | J84: =SUM(P84,U84,Z84,AK84,AP84,AU84,BF84,BK84,BP84,CA84,CF84,CK84) -> 0 | K84: =SUM(Q84,V84,AA84,AL84,AQ84,AV84,BG84,BL84,BQ84,CB84,CG84,CL84) -> 0 | L84: =SUM(R84,W84,AB84,AM84,AR84,AW84,BH84,BM84,BR84,CC84,CH84,CM84) -> 0 | M84: =SUM(S84,X84,AC84,AN84,AS84,AX84,BI84,BN84,BS84,CD84,CI84,CN84) -> 0 | N84: =SUM(T84,Y84,AD84,AO84,AT84,AY84,BJ84,BO84,BT84,CE84,CJ84,CO84) -> 0 | S84: =P84-Q84 -> 0 | X84: =U84-V84 -> 0 | AD84: =AA84-AB84 -> 0 | AH84: =AE84-AF84 -> 0 | AN84: =AK84-AL84 -> 0 | AS84: =AP84-AQ84 -> 0 | AX84: =AU84-AV84 -> 0 | BC84: =AZ84-BA84 -> 0 | BI84: =BF84-BG84 -> 0 | BN84: =BK84-BL84 -> 0 | BS84: =BP84-BQ84 -> 0 | BX84: =BU84-BV84 -> 0 | CD84: =CA84-CB84 -> 0 | CI84: =CF84-CG84 -> 0 | CN84: =CK84-CL84 -> 0 | CS84: =CP84-CQ84 -> 0
A85: 76 | E85: 無償 | J85: =SUM(P85,U85,Z85,AK85,AP85,AU85,BF85,BK85,BP85,CA85,CF85,CK85) -> 0 | K85: =SUM(Q85,V85,AA85,AL85,AQ85,AV85,BG85,BL85,BQ85,CB85,CG85,CL85) -> 0 | L85: =SUM(R85,W85,AB85,AM85,AR85,AW85,BH85,BM85,BR85,CC85,CH85,CM85) -> 0 | M85: =SUM(S85,X85,AC85,AN85,AS85,AX85,BI85,BN85,BS85,CD85,CI85,CN85) -> 0 | N85: =SUM(T85,Y85,AD85,AO85,AT85,AY85,BJ85,BO85,BT85,CE85,CJ85,CO85) -> 0 | S85: =P85-Q85 -> 0 | X85: =U85-V85 -> 0 | AD85: =AA85-AB85 -> 0 | AH85: =AE85-AF85 -> 0 | AN85: =AK85-AL85 -> 0 | AS85: =AP85-AQ85 -> 0 | AX85: =AU85-AV85 -> 0 | BC85: =AZ85-BA85 -> 0 | BI85: =BF85-BG85 -> 0 | BN85: =BK85-BL85 -> 0 | BS85: =BP85-BQ85 -> 0 | BX85: =BU85-BV85 -> 0 | CD85: =CA85-CB85 -> 0 | CI85: =CF85-CG85 -> 0 | CN85: =CK85-CL85 -> 0 | CS85: =CP85-CQ85 -> 0
A86: 77 | E86: 整備収手 | J86: =SUM(P86,U86,Z86,AK86,AP86,AU86,BF86,BK86,BP86,CA86,CF86,CK86) -> 0 | K86: =SUM(Q86,V86,AA86,AL86,AQ86,AV86,BG86,BL86,BQ86,CB86,CG86,CL86) -> 0 | L86: =SUM(R86,W86,AB86,AM86,AR86,AW86,BH86,BM86,BR86,CC86,CH86,CM86) -> 0 | M86: =SUM(S86,X86,AC86,AN86,AS86,AX86,BI86,BN86,BS86,CD86,CI86,CN86) -> 0 | N86: =SUM(T86,Y86,AD86,AO86,AT86,AY86,BJ86,BO86,BT86,CE86,CJ86,CO86) -> 0 | S86: =P86-Q86 -> 0 | X86: =U86-V86 -> 0 | AD86: =AA86-AB86 -> 0 | AH86: =AE86-AF86 -> 0 | AN86: =AK86-AL86 -> 0 | AS86: =AP86-AQ86 -> 0 | AX86: =AU86-AV86 -> 0 | BC86: =AZ86-BA86 -> 0 | BI86: =BF86-BG86 -> 0 | BN86: =BK86-BL86 -> 0 | BS86: =BP86-BQ86 -> 0 | BX86: =BU86-BV86 -> 0 | CD86: =CA86-CB86 -> 0 | CI86: =CF86-CG86 -> 0 | CN86: =CK86-CL86 -> 0 | CS86: =CP86-CQ86 -> 0
A87: 78 | E87: サービス員給与 | J87: =SUM(P87,U87,Z87,AK87,AP87,AU87,BF87,BK87,BP87,CA87,CF87,CK87) -> 0 | K87: =SUM(Q87,V87,AA87,AL87,AQ87,AV87,BG87,BL87,BQ87,CB87,CG87,CL87) -> 0 | L87: =SUM(R87,W87,AB87,AM87,AR87,AW87,BH87,BM87,BR87,CC87,CH87,CM87) -> 0 | M87: =SUM(S87,X87,AC87,AN87,AS87,AX87,BI87,BN87,BS87,CD87,CI87,CN87) -> 0 | N87: =SUM(T87,Y87,AD87,AO87,AT87,AY87,BJ87,BO87,BT87,CE87,CJ87,CO87) -> 0 | S87: =P87-Q87 -> 0 | X87: =U87-V87 -> 0 | AD87: =AA87-AB87 -> 0 | AH87: =AE87-AF87 -> 0 | AN87: =AK87-AL87 -> 0 | AS87: =AP87-AQ87 -> 0 | AX87: =AU87-AV87 -> 0 | BC87: =AZ87-BA87 -> 0 | BI87: =BF87-BG87 -> 0 | BN87: =BK87-BL87 -> 0 | BS87: =BP87-BQ87 -> 0 | BX87: =BU87-BV87 -> 0 | CD87: =CA87-CB87 -> 0 | CI87: =CF87-CG87 -> 0 | CN87: =CK87-CL87 -> 0 | CS87: =CP87-CQ87 -> 0
A88: 79 | E88: 整備総粗利 | J88: =SUM(P88,U88,Z88,AK88,AP88,AU88,BF88,BK88,BP88,CA88,CF88,CK88) -> 0 | K88: =SUM(Q88,V88,AA88,AL88,AQ88,AV88,BG88,BL88,BQ88,CB88,CG88,CL88) -> 0 | L88: =SUM(R88,W88,AB88,AM88,AR88,AW88,BH88,BM88,BR88,CC88,CH88,CM88) -> 0 | M88: =SUM(S88,X88,AC88,AN88,AS88,AX88,BI88,BN88,BS88,CD88,CI88,CN88) -> 0 | N88: =SUM(T88,Y88,AD88,AO88,AT88,AY88,BJ88,BO88,BT88,CE88,CJ88,CO88) -> 0 | S88: =P88-Q88 -> 0 | X88: =U88-V88 -> 0 | AD88: =AA88-AB88 -> 0 | AH88: =AE88-AF88 -> 0 | AN88: =AK88-AL88 -> 0 | AS88: =AP88-AQ88 -> 0 | AX88: =AU88-AV88 -> 0 | BC88: =AZ88-BA88 -> 0 | BI88: =BF88-BG88 -> 0 | BN88: =BK88-BL88 -> 0 | BS88: =BP88-BQ88 -> 0 | BX88: =BU88-BV88 -> 0 | CD88: =CA88-CB88 -> 0 | CI88: =CF88-CG88 -> 0 | CN88: =CK88-CL88 -> 0 | CS88: =CP88-CQ88 -> 0
A89: 80 | E89: 販売費 | F89: 販手・サービス・雑費 | J89: =SUM(P89,U89,Z89,AK89,AP89,AU89,BF89,BK89,BP89,CA89,CF89,CK89) -> 0 | K89: =SUM(Q89,V89,AA89,AL89,AQ89,AV89,BG89,BL89,BQ89,CB89,CG89,CL89) -> 0 | L89: =SUM(R89,W89,AB89,AM89,AR89,AW89,BH89,BM89,BR89,CC89,CH89,CM89) -> 0 | M89: =SUM(S89,X89,AC89,AN89,AS89,AX89,BI89,BN89,BS89,CD89,CI89,CN89) -> 0 | N89: =SUM(T89,Y89,AD89,AO89,AT89,AY89,BJ89,BO89,BT89,CE89,CJ89,CO89) -> 0 | S89: =P89-Q89 -> 0 | X89: =U89-V89 -> 0 | AD89: =AA89-AB89 -> 0 | AH89: =AE89-AF89 -> 0 | AN89: =AK89-AL89 -> 0 | AS89: =AP89-AQ89 -> 0 | AX89: =AU89-AV89 -> 0 | BC89: =AZ89-BA89 -> 0 | BI89: =BF89-BG89 -> 0 | BN89: =BK89-BL89 -> 0 | BS89: =BP89-BQ89 -> 0 | BX89: =BU89-BV89 -> 0 | CD89: =CA89-CB89 -> 0 | CI89: =CF89-CG89 -> 0 | CN89: =CK89-CL89 -> 0 | CS89: =CP89-CQ89 -> 0
A90: 81 | F90: 納車費・運送保管費 | J90: =SUM(P90,U90,Z90,AK90,AP90,AU90,BF90,BK90,BP90,CA90,CF90,CK90) -> 0 | K90: =SUM(Q90,V90,AA90,AL90,AQ90,AV90,BG90,BL90,BQ90,CB90,CG90,CL90) -> 0 | L90: =SUM(R90,W90,AB90,AM90,AR90,AW90,BH90,BM90,BR90,CC90,CH90,CM90) -> 0 | M90: =SUM(S90,X90,AC90,AN90,AS90,AX90,BI90,BN90,BS90,CD90,CI90,CN90) -> 0 | N90: =SUM(T90,Y90,AD90,AO90,AT90,AY90,BJ90,BO90,BT90,CE90,CJ90,CO90) -> 0 | S90: =P90-Q90 -> 0 | X90: =U90-V90 -> 0 | AD90: =AA90-AB90 -> 0 | AH90: =AE90-AF90 -> 0 | AN90: =AK90-AL90 -> 0 | AS90: =AP90-AQ90 -> 0 | AX90: =AU90-AV90 -> 0 | BC90: =AZ90-BA90 -> 0 | BI90: =BF90-BG90 -> 0 | BN90: =BK90-BL90 -> 0 | BS90: =BP90-BQ90 -> 0 | BX90: =BU90-BV90 -> 0 | CD90: =CA90-CB90 -> 0 | CI90: =CF90-CG90 -> 0 | CN90: =CK90-CL90 -> 0 | CS90: =CP90-CQ90 -> 0
A91: 82 | F91: 広告宣伝費 | J91: =SUM(P91,U91,Z91,AK91,AP91,AU91,BF91,BK91,BP91,CA91,CF91,CK91) -> 0 | K91: =SUM(Q91,V91,AA91,AL91,AQ91,AV91,BG91,BL91,BQ91,CB91,CG91,CL91) -> 0 | L91: =SUM(R91,W91,AB91,AM91,AR91,AW91,BH91,BM91,BR91,CC91,CH91,CM91) -> 0 | M91: =SUM(S91,X91,AC91,AN91,AS91,AX91,BI91,BN91,BS91,CD91,CI91,CN91) -> 0 | N91: =SUM(T91,Y91,AD91,AO91,AT91,AY91,BJ91,BO91,BT91,CE91,CJ91,CO91) -> 0 | S91: =P91-Q91 -> 0 | X91: =U91-V91 -> 0 | AD91: =AA91-AB91 -> 0 | AH91: =AE91-AF91 -> 0 | AN91: =AK91-AL91 -> 0 | AS91: =AP91-AQ91 -> 0 | AX91: =AU91-AV91 -> 0 | BC91: =AZ91-BA91 -> 0 | BI91: =BF91-BG91 -> 0 | BN91: =BK91-BL91 -> 0 | BS91: =BP91-BQ91 -> 0 | BX91: =BU91-BV91 -> 0 | CD91: =CA91-CB91 -> 0 | CI91: =CF91-CG91 -> 0 | CN91: =CK91-CL91 -> 0 | CS91: =CP91-CQ91 -> 0
A92: 83 | F92: デモカー・代車費 | J92: =SUM(P92,U92,Z92,AK92,AP92,AU92,BF92,BK92,BP92,CA92,CF92,CK92) -> 0 | K92: =SUM(Q92,V92,AA92,AL92,AQ92,AV92,BG92,BL92,BQ92,CB92,CG92,CL92) -> 0 | L92: =SUM(R92,W92,AB92,AM92,AR92,AW92,BH92,BM92,BR92,CC92,CH92,CM92) -> 0 | M92: =SUM(S92,X92,AC92,AN92,AS92,AX92,BI92,BN92,BS92,CD92,CI92,CN92) -> 0 | N92: =SUM(T92,Y92,AD92,AO92,AT92,AY92,BJ92,BO92,BT92,CE92,CJ92,CO92) -> 0 | S92: =P92-Q92 -> 0 | X92: =U92-V92 -> 0 | AD92: =AA92-AB92 -> 0 | AH92: =AE92-AF92 -> 0 | AN92: =AK92-AL92 -> 0 | AS92: =AP92-AQ92 -> 0 | AX92: =AU92-AV92 -> 0 | BC92: =AZ92-BA92 -> 0 | BI92: =BF92-BG92 -> 0 | BN92: =BK92-BL92 -> 0 | BS92: =BP92-BQ92 -> 0 | BX92: =BU92-BV92 -> 0 | CD92: =CA92-CB92 -> 0 | CI92: =CF92-CG92 -> 0 | CN92: =CK92-CL92 -> 0 | CS92: =CP92-CQ92 -> 0
A93: 84 | F93: 本部負担金 | J93: =SUM(P93,U93,Z93,AK93,AP93,AU93,BF93,BK93,BP93,CA93,CF93,CK93) -> 0 | K93: =SUM(Q93,V93,AA93,AL93,AQ93,AV93,BG93,BL93,BQ93,CB93,CG93,CL93) -> 0 | L93: =SUM(R93,W93,AB93,AM93,AR93,AW93,BH93,BM93,BR93,CC93,CH93,CM93) -> 0 | M93: =SUM(S93,X93,AC93,AN93,AS93,AX93,BI93,BN93,BS93,CD93,CI93,CN93) -> 0 | N93: =SUM(T93,Y93,AD93,AO93,AT93,AY93,BJ93,BO93,BT93,CE93,CJ93,CO93) -> 0 | S93: =P93-Q93 -> 0 | X93: =U93-V93 -> 0 | AD93: =AA93-AB93 -> 0 | AH93: =AE93-AF93 -> 0 | AN93: =AK93-AL93 -> 0 | AS93: =AP93-AQ93 -> 0 | AX93: =AU93-AV93 -> 0 | BC93: =AZ93-BA93 -> 0 | BI93: =BF93-BG93 -> 0 | BN93: =BK93-BL93 -> 0 | BS93: =BP93-BQ93 -> 0 | BX93: =BU93-BV93 -> 0 | CD93: =CA93-CB93 -> 0 | CI93: =CF93-CG93 -> 0 | CN93: =CK93-CL93 -> 0 | CS93: =CP93-CQ93 -> 0
A94: 85 | F94: 小計 | J94: =SUM(P94,U94,Z94,AK94,AP94,AU94,BF94,BK94,BP94,CA94,CF94,CK94) -> 0 | K94: =SUM(Q94,V94,AA94,AL94,AQ94,AV94,BG94,BL94,BQ94,CB94,CG94,CL94) -> 0 | L94: =SUM(R94,W94,AB94,AM94,AR94,AW94,BH94,BM94,BR94,CC94,CH94,CM94) -> 0 | M94: =SUM(S94,X94,AC94,AN94,AS94,AX94,BI94,BN94,BS94,CD94,CI94,CN94) -> 0 | N94: =SUM(T94,Y94,AD94,AO94,AT94,AY94,BJ94,BO94,BT94,CE94,CJ94,CO94) -> 0 | S94: =P94-Q94 -> 0 | X94: =U94-V94 -> 0 | AD94: =AA94-AB94 -> 0 | AH94: =AE94-AF94 -> 0 | AN94: =AK94-AL94 -> 0 | AS94: =AP94-AQ94 -> 0 | AX94: =AU94-AV94 -> 0 | BC94: =AZ94-BA94 -> 0 | BI94: =BF94-BG94 -> 0 | BN94: =BK94-BL94 -> 0 | BS94: =BP94-BQ94 -> 0 | BX94: =BU94-BV94 -> 0 | CD94: =CA94-CB94 -> 0 | CI94: =CF94-CG94 -> 0 | CN94: =CK94-CL94 -> 0 | CS94: =CP94-CQ94 -> 0
A95: 86 | E95: 整備限界利益 | J95: =SUM(P95,U95,Z95,AK95,AP95,AU95,BF95,BK95,BP95,CA95,CF95,CK95) -> 0 | K95: =SUM(Q95,V95,AA95,AL95,AQ95,AV95,BG95,BL95,BQ95,CB95,CG95,CL95) -> 0 | L95: =SUM(R95,W95,AB95,AM95,AR95,AW95,BH95,BM95,BR95,CC95,CH95,CM95) -> 0 | M95: =SUM(S95,X95,AC95,AN95,AS95,AX95,BI95,BN95,BS95,CD95,CI95,CN95) -> 0 | N95: =SUM(T95,Y95,AD95,AO95,AT95,AY95,BJ95,BO95,BT95,CE95,CJ95,CO95) -> 0 | S95: =P95-Q95 -> 0 | X95: =U95-V95 -> 0 | AD95: =AA95-AB95 -> 0 | AH95: =AE95-AF95 -> 0 | AN95: =AK95-AL95 -> 0 | AS95: =AP95-AQ95 -> 0 | AX95: =AU95-AV95 -> 0 | BC95: =AZ95-BA95 -> 0 | BI95: =BF95-BG95 -> 0 | BN95: =BK95-BL95 -> 0 | BS95: =BP95-BQ95 -> 0 | BX95: =BU95-BV95 -> 0 | CD95: =CA95-CB95 -> 0 | CI95: =CF95-CG95 -> 0 | CN95: =CK95-CL95 -> 0 | CS95: =CP95-CQ95 -> 0
A96: 87 | D96: 保険収入手数料 | J96: =SUM(P96,U96,Z96,AK96,AP96,AU96,BF96,BK96,BP96,CA96,CF96,CK96) -> 0 | K96: =SUM(Q96,V96,AA96,AL96,AQ96,AV96,BG96,BL96,BQ96,CB96,CG96,CL96) -> 0 | L96: =SUM(R96,W96,AB96,AM96,AR96,AW96,BH96,BM96,BR96,CC96,CH96,CM96) -> 0 | M96: =SUM(S96,X96,AC96,AN96,AS96,AX96,BI96,BN96,BS96,CD96,CI96,CN96) -> 0 | N96: =SUM(T96,Y96,AD96,AO96,AT96,AY96,BJ96,BO96,BT96,CE96,CJ96,CO96) -> 0 | S96: =P96-Q96 -> 0 | X96: =U96-V96 -> 0 | AD96: =AA96-AB96 -> 0 | AH96: =AE96-AF96 -> 0 | AN96: =AK96-AL96 -> 0 | AS96: =AP96-AQ96 -> 0 | AX96: =AU96-AV96 -> 0 | BC96: =AZ96-BA96 -> 0 | BI96: =BF96-BG96 -> 0 | BN96: =BK96-BL96 -> 0 | BS96: =BP96-BQ96 -> 0 | BX96: =BU96-BV96 -> 0 | CD96: =CA96-CB96 -> 0 | CI96: =CF96-CG96 -> 0 | CN96: =CK96-CL96 -> 0 | CS96: =CP96-CQ96 -> 0
A97: 88 | D97: その他収手及び商品利益 | J97: =SUM(P97,U97,Z97,AK97,AP97,AU97,BF97,BK97,BP97,CA97,CF97,CK97) -> 0 | K97: =SUM(Q97,V97,AA97,AL97,AQ97,AV97,BG97,BL97,BQ97,CB97,CG97,CL97) -> 0 | L97: =SUM(R97,W97,AB97,AM97,AR97,AW97,BH97,BM97,BR97,CC97,CH97,CM97) -> 0 | M97: =SUM(S97,X97,AC97,AN97,AS97,AX97,BI97,BN97,BS97,CD97,CI97,CN97) -> 0 | N97: =SUM(T97,Y97,AD97,AO97,AT97,AY97,BJ97,BO97,BT97,CE97,CJ97,CO97) -> 0 | S97: =P97-Q97 -> 0 | X97: =U97-V97 -> 0 | AD97: =AA97-AB97 -> 0 | AH97: =AE97-AF97 -> 0 | AN97: =AK97-AL97 -> 0 | AS97: =AP97-AQ97 -> 0 | AX97: =AU97-AV97 -> 0 | BC97: =AZ97-BA97 -> 0 | BI97: =BF97-BG97 -> 0 | BN97: =BK97-BL97 -> 0 | BS97: =BP97-BQ97 -> 0 | BX97: =BU97-BV97 -> 0 | CD97: =CA97-CB97 -> 0 | CI97: =CF97-CG97 -> 0 | CN97: =CK97-CL97 -> 0 | CS97: =CP97-CQ97 -> 0
A98: 89 | D98: 総利益合計 | J98: =SUM(P98,U98,Z98,AK98,AP98,AU98,BF98,BK98,BP98,CA98,CF98,CK98) -> 0 | K98: =SUM(Q98,V98,AA98,AL98,AQ98,AV98,BG98,BL98,BQ98,CB98,CG98,CL98) -> 0 | L98: =SUM(R98,W98,AB98,AM98,AR98,AW98,BH98,BM98,BR98,CC98,CH98,CM98) -> 0 | M98: =SUM(S98,X98,AC98,AN98,AS98,AX98,BI98,BN98,BS98,CD98,CI98,CN98) -> 0 | N98: =SUM(T98,Y98,AD98,AO98,AT98,AY98,BJ98,BO98,BT98,CE98,CJ98,CO98) -> 0 | S98: =P98-Q98 -> 0 | X98: =U98-V98 -> 0 | AD98: =AA98-AB98 -> 0 | AH98: =AE98-AF98 -> 0 | AN98: =AK98-AL98 -> 0 | AS98: =AP98-AQ98 -> 0 | AX98: =AU98-AV98 -> 0 | BC98: =AZ98-BA98 -> 0 | BI98: =BF98-BG98 -> 0 | BN98: =BK98-BL98 -> 0 | BS98: =BP98-BQ98 -> 0 | BX98: =BU98-BV98 -> 0 | CD98: =CA98-CB98 -> 0 | CI98: =CF98-CG98 -> 0 | CN98: =CK98-CL98 -> 0 | CS98: =CP98-CQ98 -> 0
A99: 90 | C99: 総限界利益 | J99: =SUM(P99,U99,Z99,AK99,AP99,AU99,BF99,BK99,BP99,CA99,CF99,CK99) -> 0 | K99: =SUM(Q99,V99,AA99,AL99,AQ99,AV99,BG99,BL99,BQ99,CB99,CG99,CL99) -> 0 | L99: =SUM(R99,W99,AB99,AM99,AR99,AW99,BH99,BM99,BR99,CC99,CH99,CM99) -> 0 | M99: =SUM(S99,X99,AC99,AN99,AS99,AX99,BI99,BN99,BS99,CD99,CI99,CN99) -> 0 | N99: =SUM(T99,Y99,AD99,AO99,AT99,AY99,BJ99,BO99,BT99,CE99,CJ99,CO99) -> 0 | S99: =P99-Q99 -> 0 | X99: =U99-V99 -> 0 | AD99: =AA99-AB99 -> 0 | AH99: =AE99-AF99 -> 0 | AN99: =AK99-AL99 -> 0 | AS99: =AP99-AQ99 -> 0 | AX99: =AU99-AV99 -> 0 | BC99: =AZ99-BA99 -> 0 | BI99: =BF99-BG99 -> 0 | BN99: =BK99-BL99 -> 0 | BS99: =BP99-BQ99 -> 0 | BX99: =BU99-BV99 -> 0 | CD99: =CA99-CB99 -> 0 | CI99: =CF99-CG99 -> 0 | CN99: =CK99-CL99 -> 0 | CS99: =CP99-CQ99 -> 0
A100: 91 | B100: 一般管理費 | C100: 人件費 | E100: 給与手当 | J100: =SUM(P100,U100,Z100,AK100,AP100,AU100,BF100,BK100,BP100,CA100,CF100,CK100) -> 0 | K100: =SUM(Q100,V100,AA100,AL100,AQ100,AV100,BG100,BL100,BQ100,CB100,CG100,CL100) -> 0 | L100: =SUM(R100,W100,AB100,AM100,AR100,AW100,BH100,BM100,BR100,CC100,CH100,CM100) -> 0 | M100: =SUM(S100,X100,AC100,AN100,AS100,AX100,BI100,BN100,BS100,CD100,CI100,CN100) -> 0 | N100: =SUM(T100,Y100,AD100,AO100,AT100,AY100,BJ100,BO100,BT100,CE100,CJ100,CO100) -> 0 | S100: =P100-Q100 -> 0 | X100: =U100-V100 -> 0 | AD100: =AA100-AB100 -> 0 | AH100: =AE100-AF100 -> 0 | AN100: =AK100-AL100 -> 0 | AS100: =AP100-AQ100 -> 0 | AX100: =AU100-AV100 -> 0 | BC100: =AZ100-BA100 -> 0 | BI100: =BF100-BG100 -> 0 | BN100: =BK100-BL100 -> 0 | BS100: =BP100-BQ100 -> 0 | BX100: =BU100-BV100 -> 0 | CD100: =CA100-CB100 -> 0 | CI100: =CF100-CG100 -> 0 | CN100: =CK100-CL100 -> 0 | CS100: =CP100-CQ100 -> 0
A101: 92 | E101: ＜内残業・奨励金＞ | J101: =SUM(P101,U101,Z101,AK101,AP101,AU101,BF101,BK101,BP101,CA101,CF101,CK101) -> 0 | K101: =SUM(Q101,V101,AA101,AL101,AQ101,AV101,BG101,BL101,BQ101,CB101,CG101,CL101) -> 0 | L101: =SUM(R101,W101,AB101,AM101,AR101,AW101,BH101,BM101,BR101,CC101,CH101,CM101) -> 0 | M101: =SUM(S101,X101,AC101,AN101,AS101,AX101,BI101,BN101,BS101,CD101,CI101,CN101) -> 0 | N101: =SUM(T101,Y101,AD101,AO101,AT101,AY101,BJ101,BO101,BT101,CE101,CJ101,CO101) -> 0 | S101: =P101-Q101 -> 0 | X101: =U101-V101 -> 0 | AD101: =AA101-AB101 -> 0 | AH101: =AE101-AF101 -> 0 | AN101: =AK101-AL101 -> 0 | AS101: =AP101-AQ101 -> 0 | AX101: =AU101-AV101 -> 0 | BC101: =AZ101-BA101 -> 0 | BI101: =BF101-BG101 -> 0 | BN101: =BK101-BL101 -> 0 | BS101: =BP101-BQ101 -> 0 | BX101: =BU101-BV101 -> 0 | CD101: =CA101-CB101 -> 0 | CI101: =CF101-CG101 -> 0 | CN101: =CK101-CL101 -> 0 | CS101: =CP101-CQ101 -> 0
A102: 93 | E102: 賞与 | J102: =SUM(P102,U102,Z102,AK102,AP102,AU102,BF102,BK102,BP102,CA102,CF102,CK102) -> 0 | K102: =SUM(Q102,V102,AA102,AL102,AQ102,AV102,BG102,BL102,BQ102,CB102,CG102,CL102) -> 0 | L102: =SUM(R102,W102,AB102,AM102,AR102,AW102,BH102,BM102,BR102,CC102,CH102,CM102) -> 0 | M102: =SUM(S102,X102,AC102,AN102,AS102,AX102,BI102,BN102,BS102,CD102,CI102,CN102) -> 0 | N102: =SUM(T102,Y102,AD102,AO102,AT102,AY102,BJ102,BO102,BT102,CE102,CJ102,CO102) -> 0 | S102: =P102-Q102 -> 0 | X102: =U102-V102 -> 0 | AD102: =AA102-AB102 -> 0 | AH102: =AE102-AF102 -> 0 | AN102: =AK102-AL102 -> 0 | AS102: =AP102-AQ102 -> 0 | AX102: =AU102-AV102 -> 0 | BC102: =AZ102-BA102 -> 0 | BI102: =BF102-BG102 -> 0 | BN102: =BK102-BL102 -> 0 | BS102: =BP102-BQ102 -> 0 | BX102: =BU102-BV102 -> 0 | CD102: =CA102-CB102 -> 0 | CI102: =CF102-CG102 -> 0 | CN102: =CK102-CL102 -> 0 | CS102: =CP102-CQ102 -> 0
A103: 94 | E103: 退職・福利厚生費 | J103: =SUM(P103,U103,Z103,AK103,AP103,AU103,BF103,BK103,BP103,CA103,CF103,CK103) -> 0 | K103: =SUM(Q103,V103,AA103,AL103,AQ103,AV103,BG103,BL103,BQ103,CB103,CG103,CL103) -> 0 | L103: =SUM(R103,W103,AB103,AM103,AR103,AW103,BH103,BM103,BR103,CC103,CH103,CM103) -> 0 | M103: =SUM(S103,X103,AC103,AN103,AS103,AX103,BI103,BN103,BS103,CD103,CI103,CN103) -> 0 | N103: =SUM(T103,Y103,AD103,AO103,AT103,AY103,BJ103,BO103,BT103,CE103,CJ103,CO103) -> 0 | S103: =P103-Q103 -> 0 | X103: =U103-V103 -> 0 | AD103: =AA103-AB103 -> 0 | AH103: =AE103-AF103 -> 0 | AN103: =AK103-AL103 -> 0 | AS103: =AP103-AQ103 -> 0 | AX103: =AU103-AV103 -> 0 | BC103: =AZ103-BA103 -> 0 | BI103: =BF103-BG103 -> 0 | BN103: =BK103-BL103 -> 0 | BS103: =BP103-BQ103 -> 0 | BX103: =BU103-BV103 -> 0 | CD103: =CA103-CB103 -> 0 | CI103: =CF103-CG103 -> 0 | CN103: =CK103-CL103 -> 0 | CS103: =CP103-CQ103 -> 0
...

Sheet 販売２
B1: 予算表
B3: 期：
B5: 部署：
B7: 項目 | J7: 年間計 | P7: １０月 | U7: １１月 | Z7: １２月 | AE7: １０月～１２月合計 | AK7: １月 | AP7: ２月 | AU7: ３月 | AZ7: １月～３月合計 | BF7: ４月 | BK7: ５月 | BP7: ６月 | BU7: ４月～６月合計 | CA7: ７月 | CF7: ８月 | CK7: ９月 | CP7: ７月～９月合計
A8: LineNo
J9: 計画 | K9: 前年実績 | L9: 指標 | M9: 差 | N9: 前年比 | P9: 計画 | Q9: 前年実績 | R9: 指標 | S9: 差 | T9: 前年比 | U9: 計画 | V9: 前年実績 | W9: 指標 | X9: 差 | Y9: 前年比 | Z9: 計画 | AA9: 前年実績 | AB9: 指標 | AC9: 差 | AD9: 前年比 | AE9: 計画 | AF9: 前年実績 | AG9: 指標 | AH9: 差 | AI9: 前年比 | AK9: 計画 | AL9: 前年実績 | AM9: 指標 | AN9: 差 | AO9: 前年比 | AP9: 計画 | AQ9: 前年実績 | AR9: 指標 | AS9: 差 | AT9: 前年比 | AU9: 計画 | AV9: 前年実績 | AW9: 指標 | AX9: 差 | AY9: 前年比 | AZ9: 計画 | BA9: 前年実績 | BB9: 指標 | BC9: 差 | BD9: 前年比 | BF9: 計画 | BG9: 前年実績 | BH9: 指標 | BI9: 差 | BJ9: 前年比 | BK9: 計画 | BL9: 前年実績 | BM9: 指標 | BN9: 差 | BO9: 前年比 | BP9: 計画 | BQ9: 前年実績 | BR9: 指標 | BS9: 差 | BT9: 前年比 | BU9: 計画 | BV9: 前年実績 | BW9: 指標 | BX9: 差 | BY9: 前年比 | CA9: 計画 | CB9: 前年実績 | CC9: 指標 | CD9: 差 | CE9: 前年比 | CF9: 計画 | CG9: 前年実績 | CH9: 指標 | CI9: 差 | CJ9: 前年比 | CK9: 計画 | CL9: 前年実績 | CM9: 指標 | CN9: 差 | CO9: 前年比 | CP9: 計画 | CQ9: 前年実績 | CR9: 指標 | CS9: 差 | CT9: 前年比
A10: 1 | B10: 営業スタッフ数 | J10: =SUM(P10,U10,Z10,AK10,AP10,AU10,BF10,BK10,BP10,CA10,CF10,CK10) -> 0 | K10: =SUM(Q10,V10,AA10,AL10,AQ10,AV10,BG10,BL10,BQ10,CB10,CG10,CL10) -> 0 | L10: =SUM(R10,W10,AB10,AM10,AR10,AW10,BH10,BM10,BR10,CC10,CH10,CM10) -> 0 | M10: =SUM(S10,X10,AC10,AN10,AS10,AX10,BI10,BN10,BS10,CD10,CI10,CN10) -> 0 | N10: =SUM(T10,Y10,AD10,AO10,AT10,AY10,BJ10,BO10,BT10,CE10,CJ10,CO10) -> 0 | S10: =P10-Q10 -> 0 | X10: =U10-V10 -> 0 | AD10: =AA10-AB10 -> 0 | AH10: =AE10-AF10 -> 0 | AN10: =AK10-AL10 -> 0 | AS10: =AP10-AQ10 -> 0 | AX10: =AU10-AV10 -> 0 | BC10: =AZ10-BA10 -> 0 | BI10: =BF10-BG10 -> 0 | BN10: =BK10-BL10 -> 0 | BS10: =BP10-BQ10 -> 0 | BX10: =BU10-BV10 -> 0 | CD10: =CA10-CB10 -> 0 | CI10: =CF10-CG10 -> 0 | CN10: =CK10-CL10 -> 0 | CS10: =CP10-CQ10 -> 0
A11: 2 | B11: 自新直顧客数 | J11: =SUM(P11,U11,Z11,AK11,AP11,AU11,BF11,BK11,BP11,CA11,CF11,CK11) -> 0 | K11: =SUM(Q11,V11,AA11,AL11,AQ11,AV11,BG11,BL11,BQ11,CB11,CG11,CL11) -> 0 | L11: =SUM(R11,W11,AB11,AM11,AR11,AW11,BH11,BM11,BR11,CC11,CH11,CM11) -> 0 | M11: =SUM(S11,X11,AC11,AN11,AS11,AX11,BI11,BN11,BS11,CD11,CI11,CN11) -> 0 | N11: =SUM(T11,Y11,AD11,AO11,AT11,AY11,BJ11,BO11,BT11,CE11,CJ11,CO11) -> 0 | S11: =P11-Q11 -> 0 | X11: =U11-V11 -> 0 | AD11: =AA11-AB11 -> 0 | AH11: =AE11-AF11 -> 0 | AN11: =AK11-AL11 -> 0 | AS11: =AP11-AQ11 -> 0 | AX11: =AU11-AV11 -> 0 | BC11: =AZ11-BA11 -> 0 | BI11: =BF11-BG11 -> 0 | BN11: =BK11-BL11 -> 0 | BS11: =BP11-BQ11 -> 0 | BX11: =BU11-BV11 -> 0 | CD11: =CA11-CB11 -> 0 | CI11: =CF11-CG11 -> 0 | CN11: =CK11-CL11 -> 0 | CS11: =CP11-CQ11 -> 0
A12: 3 | B12: 顧客代替台数 | J12: =SUM(P12,U12,Z12,AK12,AP12,AU12,BF12,BK12,BP12,CA12,CF12,CK12) -> 0 | K12: =SUM(Q12,V12,AA12,AL12,AQ12,AV12,BG12,BL12,BQ12,CB12,CG12,CL12) -> 0 | L12: =SUM(R12,W12,AB12,AM12,AR12,AW12,BH12,BM12,BR12,CC12,CH12,CM12) -> 0 | M12: =SUM(S12,X12,AC12,AN12,AS12,AX12,BI12,BN12,BS12,CD12,CI12,CN12) -> 0 | N12: =SUM(T12,Y12,AD12,AO12,AT12,AY12,BJ12,BO12,BT12,CE12,CJ12,CO12) -> 0 | S12: =P12-Q12 -> 0 | X12: =U12-V12 -> 0 | AD12: =AA12-AB12 -> 0 | AH12: =AE12-AF12 -> 0 | AN12: =AK12-AL12 -> 0 | AS12: =AP12-AQ12 -> 0 | AX12: =AU12-AV12 -> 0 | BC12: =AZ12-BA12 -> 0 | BI12: =BF12-BG12 -> 0 | BN12: =BK12-BL12 -> 0 | BS12: =BP12-BQ12 -> 0 | BX12: =BU12-BV12 -> 0 | CD12: =CA12-CB12 -> 0 | CI12: =CF12-CG12 -> 0 | CN12: =CK12-CL12 -> 0 | CS12: =CP12-CQ12 -> 0
A13: 4 | B13: 自中直顧客数 | J13: =SUM(P13,U13,Z13,AK13,AP13,AU13,BF13,BK13,BP13,CA13,CF13,CK13) -> 0 | K13: =SUM(Q13,V13,AA13,AL13,AQ13,AV13,BG13,BL13,BQ13,CB13,CG13,CL13) -> 0 | L13: =SUM(R13,W13,AB13,AM13,AR13,AW13,BH13,BM13,BR13,CC13,CH13,CM13) -> 0 | M13: =SUM(S13,X13,AC13,AN13,AS13,AX13,BI13,BN13,BS13,CD13,CI13,CN13) -> 0 | N13: =SUM(T13,Y13,AD13,AO13,AT13,AY13,BJ13,BO13,BT13,CE13,CJ13,CO13) -> 0 | S13: =P13-Q13 -> 0 | X13: =U13-V13 -> 0 | AD13: =AA13-AB13 -> 0 | AH13: =AE13-AF13 -> 0 | AN13: =AK13-AL13 -> 0 | AS13: =AP13-AQ13 -> 0 | AX13: =AU13-AV13 -> 0 | BC13: =AZ13-BA13 -> 0 | BI13: =BF13-BG13 -> 0 | BN13: =BK13-BL13 -> 0 | BS13: =BP13-BQ13 -> 0 | BX13: =BU13-BV13 -> 0 | CD13: =CA13-CB13 -> 0 | CI13: =CF13-CG13 -> 0 | CN13: =CK13-CL13 -> 0 | CS13: =CP13-CQ13 -> 0
A14: 5 | B14: サービス直人員 | J14: =SUM(P14,U14,Z14,AK14,AP14,AU14,BF14,BK14,BP14,CA14,CF14,CK14) -> 0 | K14: =SUM(Q14,V14,AA14,AL14,AQ14,AV14,BG14,BL14,BQ14,CB14,CG14,CL14) -> 0 | L14: =SUM(R14,W14,AB14,AM14,AR14,AW14,BH14,BM14,BR14,CC14,CH14,CM14) -> 0 | M14: =SUM(S14,X14,AC14,AN14,AS14,AX14,BI14,BN14,BS14,CD14,CI14,CN14) -> 0 | N14: =SUM(T14,Y14,AD14,AO14,AT14,AY14,BJ14,BO14,BT14,CE14,CJ14,CO14) -> 0 | S14: =P14-Q14 -> 0 | X14: =U14-V14 -> 0 | AD14: =AA14-AB14 -> 0 | AH14: =AE14-AF14 -> 0 | AN14: =AK14-AL14 -> 0 | AS14: =AP14-AQ14 -> 0 | AX14: =AU14-AV14 -> 0 | BC14: =AZ14-BA14 -> 0 | BI14: =BF14-BG14 -> 0 | BN14: =BK14-BL14 -> 0 | BS14: =BP14-BQ14 -> 0 | BX14: =BU14-BV14 -> 0 | CD14: =CA14-CB14 -> 0 | CI14: =CF14-CG14 -> 0 | CN14: =CK14-CL14 -> 0 | CS14: =CP14-CQ14 -> 0
A15: 6 | B15: サービス管理顧客数 | J15: =SUM(P15,U15,Z15,AK15,AP15,AU15,BF15,BK15,BP15,CA15,CF15,CK15) -> 0 | K15: =SUM(Q15,V15,AA15,AL15,AQ15,AV15,BG15,BL15,BQ15,CB15,CG15,CL15) -> 0 | L15: =SUM(R15,W15,AB15,AM15,AR15,AW15,BH15,BM15,BR15,CC15,CH15,CM15) -> 0 | M15: =SUM(S15,X15,AC15,AN15,AS15,AX15,BI15,BN15,BS15,CD15,CI15,CN15) -> 0 | N15: =SUM(T15,Y15,AD15,AO15,AT15,AY15,BJ15,BO15,BT15,CE15,CJ15,CO15) -> 0 | S15: =P15-Q15 -> 0 | X15: =U15-V15 -> 0 | AD15: =AA15-AB15 -> 0 | AH15: =AE15-AF15 -> 0 | AN15: =AK15-AL15 -> 0 | AS15: =AP15-AQ15 -> 0 | AX15: =AU15-AV15 -> 0 | BC15: =AZ15-BA15 -> 0 | BI15: =BF15-BG15 -> 0 | BN15: =BK15-BL15 -> 0 | BS15: =BP15-BQ15 -> 0 | BX15: =BU15-BV15 -> 0 | CD15: =CA15-CB15 -> 0 | CI15: =CF15-CG15 -> 0 | CN15: =CK15-CL15 -> 0 | CS15: =CP15-CQ15 -> 0
A16: 7 | B16: 車検対象台数 | J16: =SUM(P16,U16,Z16,AK16,AP16,AU16,BF16,BK16,BP16,CA16,CF16,CK16) -> 0 | K16: =SUM(Q16,V16,AA16,AL16,AQ16,AV16,BG16,BL16,BQ16,CB16,CG16,CL16) -> 0 | L16: =SUM(R16,W16,AB16,AM16,AR16,AW16,BH16,BM16,BR16,CC16,CH16,CM16) -> 0 | M16: =SUM(S16,X16,AC16,AN16,AS16,AX16,BI16,BN16,BS16,CD16,CI16,CN16) -> 0 | N16: =SUM(T16,Y16,AD16,AO16,AT16,AY16,BJ16,BO16,BT16,CE16,CJ16,CO16) -> 0 | S16: =P16-Q16 -> 0 | X16: =U16-V16 -> 0 | AD16: =AA16-AB16 -> 0 | AH16: =AE16-AF16 -> 0 | AN16: =AK16-AL16 -> 0 | AS16: =AP16-AQ16 -> 0 | AX16: =AU16-AV16 -> 0 | BC16: =AZ16-BA16 -> 0 | BI16: =BF16-BG16 -> 0 | BN16: =BK16-BL16 -> 0 | BS16: =BP16-BQ16 -> 0 | BX16: =BU16-BV16 -> 0 | CD16: =CA16-CB16 -> 0 | CI16: =CF16-CG16 -> 0 | CN16: =CK16-CL16 -> 0 | CS16: =CP16-CQ16 -> 0
A17: 8 | C17: 内初回車検対象台数 | J17: =SUM(P17,U17,Z17,AK17,AP17,AU17,BF17,BK17,BP17,CA17,CF17,CK17) -> 0 | K17: =SUM(Q17,V17,AA17,AL17,AQ17,AV17,BG17,BL17,BQ17,CB17,CG17,CL17) -> 0 | L17: =SUM(R17,W17,AB17,AM17,AR17,AW17,BH17,BM17,BR17,CC17,CH17,CM17) -> 0 | M17: =SUM(S17,X17,AC17,AN17,AS17,AX17,BI17,BN17,BS17,CD17,CI17,CN17) -> 0 | N17: =SUM(T17,Y17,AD17,AO17,AT17,AY17,BJ17,BO17,BT17,CE17,CJ17,CO17) -> 0 | S17: =P17-Q17 -> 0 | X17: =U17-V17 -> 0 | AD17: =AA17-AB17 -> 0 | AH17: =AE17-AF17 -> 0 | AN17: =AK17-AL17 -> 0 | AS17: =AP17-AQ17 -> 0 | AX17: =AU17-AV17 -> 0 | BC17: =AZ17-BA17 -> 0 | BI17: =BF17-BG17 -> 0 | BN17: =BK17-BL17 -> 0 | BS17: =BP17-BQ17 -> 0 | BX17: =BU17-BV17 -> 0 | CD17: =CA17-CB17 -> 0 | CI17: =CF17-CG17 -> 0 | CN17: =CK17-CL17 -> 0 | CS17: =CP17-CQ17 -> 0
A18: 9 | B18: 初回車検入庫 | J18: =SUM(P18,U18,Z18,AK18,AP18,AU18,BF18,BK18,BP18,CA18,CF18,CK18) -> 0 | K18: =SUM(Q18,V18,AA18,AL18,AQ18,AV18,BG18,BL18,BQ18,CB18,CG18,CL18) -> 0 | L18: =SUM(R18,W18,AB18,AM18,AR18,AW18,BH18,BM18,BR18,CC18,CH18,CM18) -> 0 | M18: =SUM(S18,X18,AC18,AN18,AS18,AX18,BI18,BN18,BS18,CD18,CI18,CN18) -> 0 | N18: =SUM(T18,Y18,AD18,AO18,AT18,AY18,BJ18,BO18,BT18,CE18,CJ18,CO18) -> 0 | S18: =P18-Q18 -> 0 | X18: =U18-V18 -> 0 | AD18: =AA18-AB18 -> 0 | AH18: =AE18-AF18 -> 0 | AN18: =AK18-AL18 -> 0 | AS18: =AP18-AQ18 -> 0 | AX18: =AU18-AV18 -> 0 | BC18: =AZ18-BA18 -> 0 | BI18: =BF18-BG18 -> 0 | BN18: =BK18-BL18 -> 0 | BS18: =BP18-BQ18 -> 0 | BX18: =BU18-BV18 -> 0 | CD18: =CA18-CB18 -> 0 | CI18: =CF18-CG18 -> 0 | CN18: =CK18-CL18 -> 0 | CS18: =CP18-CQ18 -> 0
A19: 10 | B19: 有償入庫台数 | J19: =SUM(P19,U19,Z19,AK19,AP19,AU19,BF19,BK19,BP19,CA19,CF19,CK19) -> 0 | K19: =SUM(Q19,V19,AA19,AL19,AQ19,AV19,BG19,BL19,BQ19,CB19,CG19,CL19) -> 0 | L19: =SUM(R19,W19,AB19,AM19,AR19,AW19,BH19,BM19,BR19,CC19,CH19,CM19) -> 0 | M19: =SUM(S19,X19,AC19,AN19,AS19,AX19,BI19,BN19,BS19,CD19,CI19,CN19) -> 0 | N19: =SUM(T19,Y19,AD19,AO19,AT19,AY19,BJ19,BO19,BT19,CE19,CJ19,CO19) -> 0 | S19: =P19-Q19 -> 0 | X19: =U19-V19 -> 0 | AD19: =AA19-AB19 -> 0 | AH19: =AE19-AF19 -> 0 | AN19: =AK19-AL19 -> 0 | AS19: =AP19-AQ19 -> 0 | AX19: =AU19-AV19 -> 0 | BC19: =AZ19-BA19 -> 0 | BI19: =BF19-BG19 -> 0 | BN19: =BK19-BL19 -> 0 | BS19: =BP19-BQ19 -> 0 | BX19: =BU19-BV19 -> 0 | CD19: =CA19-CB19 -> 0 | CI19: =CF19-CG19 -> 0 | CN19: =CK19-CL19 -> 0 | CS19: =CP19-CQ19 -> 0
A20: 11 | B20: 新規獲得件数 | J20: =SUM(P20,U20,Z20,AK20,AP20,AU20,BF20,BK20,BP20,CA20,CF20,CK20) -> 0 | K20: =SUM(Q20,V20,AA20,AL20,AQ20,AV20,BG20,BL20,BQ20,CB20,CG20,CL20) -> 0 | L20: =SUM(R20,W20,AB20,AM20,AR20,AW20,BH20,BM20,BR20,CC20,CH20,CM20) -> 0 | M20: =SUM(S20,X20,AC20,AN20,AS20,AX20,BI20,BN20,BS20,CD20,CI20,CN20) -> 0 | N20: =SUM(T20,Y20,AD20,AO20,AT20,AY20,BJ20,BO20,BT20,CE20,CJ20,CO20) -> 0 | S20: =P20-Q20 -> 0 | X20: =U20-V20 -> 0 | AD20: =AA20-AB20 -> 0 | AH20: =AE20-AF20 -> 0 | AN20: =AK20-AL20 -> 0 | AS20: =AP20-AQ20 -> 0 | AX20: =AU20-AV20 -> 0 | BC20: =AZ20-BA20 -> 0 | BI20: =BF20-BG20 -> 0 | BN20: =BK20-BL20 -> 0 | BS20: =BP20-BQ20 -> 0 | BX20: =BU20-BV20 -> 0 | CD20: =CA20-CB20 -> 0 | CI20: =CF20-CG20 -> 0 | CN20: =CK20-CL20 -> 0 | CS20: =CP20-CQ20 -> 0
A21: 12 | B21: 継続対象件数 | J21: =SUM(P21,U21,Z21,AK21,AP21,AU21,BF21,BK21,BP21,CA21,CF21,CK21) -> 0 | K21: =SUM(Q21,V21,AA21,AL21,AQ21,AV21,BG21,BL21,BQ21,CB21,CG21,CL21) -> 0 | L21: =SUM(R21,W21,AB21,AM21,AR21,AW21,BH21,BM21,BR21,CC21,CH21,CM21) -> 0 | M21: =SUM(S21,X21,AC21,AN21,AS21,AX21,BI21,BN21,BS21,CD21,CI21,CN21) -> 0 | N21: =SUM(T21,Y21,AD21,AO21,AT21,AY21,BJ21,BO21,BT21,CE21,CJ21,CO21) -> 0 | S21: =P21-Q21 -> 0 | X21: =U21-V21 -> 0 | AD21: =AA21-AB21 -> 0 | AH21: =AE21-AF21 -> 0 | AN21: =AK21-AL21 -> 0 | AS21: =AP21-AQ21 -> 0 | AX21: =AU21-AV21 -> 0 | BC21: =AZ21-BA21 -> 0 | BI21: =BF21-BG21 -> 0 | BN21: =BK21-BL21 -> 0 | BS21: =BP21-BQ21 -> 0 | BX21: =BU21-BV21 -> 0 | CD21: =CA21-CB21 -> 0 | CI21: =CF21-CG21 -> 0 | CN21: =CK21-CL21 -> 0 | CS21: =CP21-CQ21 -> 0
A22: 13 | B22: 継続件数 | J22: =SUM(P22,U22,Z22,AK22,AP22,AU22,BF22,BK22,BP22,CA22,CF22,CK22) -> 0 | K22: =SUM(Q22,V22,AA22,AL22,AQ22,AV22,BG22,BL22,BQ22,CB22,CG22,CL22) -> 0 | L22: =SUM(R22,W22,AB22,AM22,AR22,AW22,BH22,BM22,BR22,CC22,CH22,CM22) -> 0 | M22: =SUM(S22,X22,AC22,AN22,AS22,AX22,BI22,BN22,BS22,CD22,CI22,CN22) -> 0 | N22: =SUM(T22,Y22,AD22,AO22,AT22,AY22,BJ22,BO22,BT22,CE22,CJ22,CO22) -> 0 | S22: =P22-Q22 -> 0 | X22: =U22-V22 -> 0 | AD22: =AA22-AB22 -> 0 | AH22: =AE22-AF22 -> 0 | AN22: =AK22-AL22 -> 0 | AS22: =AP22-AQ22 -> 0 | AX22: =AU22-AV22 -> 0 | BC22: =AZ22-BA22 -> 0 | BI22: =BF22-BG22 -> 0 | BN22: =BK22-BL22 -> 0 | BS22: =BP22-BQ22 -> 0 | BX22: =BU22-BV22 -> 0 | CD22: =CA22-CB22 -> 0 | CI22: =CF22-CG22 -> 0 | CN22: =CK22-CL22 -> 0 | CS22: =CP22-CQ22 -> 0
A23: 14 | B23: 車両保険件数 | J23: =SUM(P23,U23,Z23,AK23,AP23,AU23,BF23,BK23,BP23,CA23,CF23,CK23) -> 0 | K23: =SUM(Q23,V23,AA23,AL23,AQ23,AV23,BG23,BL23,BQ23,CB23,CG23,CL23) -> 0 | L23: =SUM(R23,W23,AB23,AM23,AR23,AW23,BH23,BM23,BR23,CC23,CH23,CM23) -> 0 | M23: =SUM(S23,X23,AC23,AN23,AS23,AX23,BI23,BN23,BS23,CD23,CI23,CN23) -> 0 | N23: =SUM(T23,Y23,AD23,AO23,AT23,AY23,BJ23,BO23,BT23,CE23,CJ23,CO23) -> 0 | S23: =P23-Q23 -> 0 | X23: =U23-V23 -> 0 | AD23: =AA23-AB23 -> 0 | AH23: =AE23-AF23 -> 0 | AN23: =AK23-AL23 -> 0 | AS23: =AP23-AQ23 -> 0 | AX23: =AU23-AV23 -> 0 | BC23: =AZ23-BA23 -> 0 | BI23: =BF23-BG23 -> 0 | BN23: =BK23-BL23 -> 0 | BS23: =BP23-BQ23 -> 0 | BX23: =BU23-BV23 -> 0 | CD23: =CA23-CB23 -> 0 | CI23: =CF23-CG23 -> 0 | CN23: =CK23-CL23 -> 0 | CS23: =CP23-CQ23 -> 0
A24: 15 | B24: 収保 | J24: =SUM(P24,U24,Z24,AK24,AP24,AU24,BF24,BK24,BP24,CA24,CF24,CK24) -> 0 | K24: =SUM(Q24,V24,AA24,AL24,AQ24,AV24,BG24,BL24,BQ24,CB24,CG24,CL24) -> 0 | L24: =SUM(R24,W24,AB24,AM24,AR24,AW24,BH24,BM24,BR24,CC24,CH24,CM24) -> 0 | M24: =SUM(S24,X24,AC24,AN24,AS24,AX24,BI24,BN24,BS24,CD24,CI24,CN24) -> 0 | N24: =SUM(T24,Y24,AD24,AO24,AT24,AY24,BJ24,BO24,BT24,CE24,CJ24,CO24) -> 0 | S24: =P24-Q24 -> 0 | X24: =U24-V24 -> 0 | AD24: =AA24-AB24 -> 0 | AH24: =AE24-AF24 -> 0 | AN24: =AK24-AL24 -> 0 | AS24: =AP24-AQ24 -> 0 | AX24: =AU24-AV24 -> 0 | BC24: =AZ24-BA24 -> 0 | BI24: =BF24-BG24 -> 0 | BN24: =BK24-BL24 -> 0 | BS24: =BP24-BQ24 -> 0 | BX24: =BU24-BV24 -> 0 | CD24: =CA24-CB24 -> 0 | CI24: =CF24-CG24 -> 0 | CN24: =CK24-CL24 -> 0 | CS24: =CP24-CQ24 -> 0
A25: 16 | B25: 総限界利益 | C25: 総利益合計 | D25: 新車 | E25: 新車台数 | J25: =SUM(P25,U25,Z25,AK25,AP25,AU25,BF25,BK25,BP25,CA25,CF25,CK25) -> 0 | K25: =SUM(Q25,V25,AA25,AL25,AQ25,AV25,BG25,BL25,BQ25,CB25,CG25,CL25) -> 0 | L25: =SUM(R25,W25,AB25,AM25,AR25,AW25,BH25,BM25,BR25,CC25,CH25,CM25) -> 0 | M25: =SUM(S25,X25,AC25,AN25,AS25,AX25,BI25,BN25,BS25,CD25,CI25,CN25) -> 0 | N25: =SUM(T25,Y25,AD25,AO25,AT25,AY25,BJ25,BO25,BT25,CE25,CJ25,CO25) -> 0 | S25: =P25-Q25 -> 0 | X25: =U25-V25 -> 0 | AD25: =AA25-AB25 -> 0 | AH25: =AE25-AF25 -> 0 | AN25: =AK25-AL25 -> 0 | AS25: =AP25-AQ25 -> 0 | AX25: =AU25-AV25 -> 0 | BC25: =AZ25-BA25 -> 0 | BI25: =BF25-BG25 -> 0 | BN25: =BK25-BL25 -> 0 | BS25: =BP25-BQ25 -> 0 | BX25: =BU25-BV25 -> 0 | CD25: =CA25-CB25 -> 0 | CI25: =CF25-CG25 -> 0 | CN25: =CK25-CL25 -> 0 | CS25: =CP25-CQ25 -> 0
A26: 17 | E26: 売上金額（架装売上含む） | J26: =SUM(P26,U26,Z26,AK26,AP26,AU26,BF26,BK26,BP26,CA26,CF26,CK26) -> 0 | K26: =SUM(Q26,V26,AA26,AL26,AQ26,AV26,BG26,BL26,BQ26,CB26,CG26,CL26) -> 0 | L26: =SUM(R26,W26,AB26,AM26,AR26,AW26,BH26,BM26,BR26,CC26,CH26,CM26) -> 0 | M26: =SUM(S26,X26,AC26,AN26,AS26,AX26,BI26,BN26,BS26,CD26,CI26,CN26) -> 0 | N26: =SUM(T26,Y26,AD26,AO26,AT26,AY26,BJ26,BO26,BT26,CE26,CJ26,CO26) -> 0 | S26: =P26-Q26 -> 0 | X26: =U26-V26 -> 0 | AD26: =AA26-AB26 -> 0 | AH26: =AE26-AF26 -> 0 | AN26: =AK26-AL26 -> 0 | AS26: =AP26-AQ26 -> 0 | AX26: =AU26-AV26 -> 0 | BC26: =AZ26-BA26 -> 0 | BI26: =BF26-BG26 -> 0 | BN26: =BK26-BL26 -> 0 | BS26: =BP26-BQ26 -> 0 | BX26: =BU26-BV26 -> 0 | CD26: =CA26-CB26 -> 0 | CI26: =CF26-CG26 -> 0 | CN26: =CK26-CL26 -> 0 | CS26: =CP26-CQ26 -> 0
A27: 18 | F27: ＜内車両値引＞ | J27: =SUM(P27,U27,Z27,AK27,AP27,AU27,BF27,BK27,BP27,CA27,CF27,CK27) -> 0 | K27: =SUM(Q27,V27,AA27,AL27,AQ27,AV27,BG27,BL27,BQ27,CB27,CG27,CL27) -> 0 | L27: =SUM(R27,W27,AB27,AM27,AR27,AW27,BH27,BM27,BR27,CC27,CH27,CM27) -> 0 | M27: =SUM(S27,X27,AC27,AN27,AS27,AX27,BI27,BN27,BS27,CD27,CI27,CN27) -> 0 | N27: =SUM(T27,Y27,AD27,AO27,AT27,AY27,BJ27,BO27,BT27,CE27,CJ27,CO27) -> 0 | S27: =P27-Q27 -> 0 | X27: =U27-V27 -> 0 | AD27: =AA27-AB27 -> 0 | AH27: =AE27-AF27 -> 0 | AN27: =AK27-AL27 -> 0 | AS27: =AP27-AQ27 -> 0 | AX27: =AU27-AV27 -> 0 | BC27: =AZ27-BA27 -> 0 | BI27: =BF27-BG27 -> 0 | BN27: =BK27-BL27 -> 0 | BS27: =BP27-BQ27 -> 0 | BX27: =BU27-BV27 -> 0 | CD27: =CA27-CB27 -> 0 | CI27: =CF27-CG27 -> 0 | CN27: =CK27-CL27 -> 0 | CS27: =CP27-CQ27 -> 0
A28: 19 | F28: 車両本体利益 | J28: =SUM(P28,U28,Z28,AK28,AP28,AU28,BF28,BK28,BP28,CA28,CF28,CK28) -> 0 | K28: =SUM(Q28,V28,AA28,AL28,AQ28,AV28,BG28,BL28,BQ28,CB28,CG28,CL28) -> 0 | L28: =SUM(R28,W28,AB28,AM28,AR28,AW28,BH28,BM28,BR28,CC28,CH28,CM28) -> 0 | M28: =SUM(S28,X28,AC28,AN28,AS28,AX28,BI28,BN28,BS28,CD28,CI28,CN28) -> 0 | N28: =SUM(T28,Y28,AD28,AO28,AT28,AY28,BJ28,BO28,BT28,CE28,CJ28,CO28) -> 0 | S28: =P28-Q28 -> 0 | X28: =U28-V28 -> 0 | AD28: =AA28-AB28 -> 0 | AH28: =AE28-AF28 -> 0 | AN28: =AK28-AL28 -> 0 | AS28: =AP28-AQ28 -> 0 | AX28: =AU28-AV28 -> 0 | BC28: =AZ28-BA28 -> 0 | BI28: =BF28-BG28 -> 0 | BN28: =BK28-BL28 -> 0 | BS28: =BP28-BQ28 -> 0 | BX28: =BU28-BV28 -> 0 | CD28: =CA28-CB28 -> 0 | CI28: =CF28-CG28 -> 0 | CN28: =CK28-CL28 -> 0 | CS28: =CP28-CQ28 -> 0
A29: 20 | F29: 架装付属品利益 | J29: =SUM(P29,U29,Z29,AK29,AP29,AU29,BF29,BK29,BP29,CA29,CF29,CK29) -> 0 | K29: =SUM(Q29,V29,AA29,AL29,AQ29,AV29,BG29,BL29,BQ29,CB29,CG29,CL29) -> 0 | L29: =SUM(R29,W29,AB29,AM29,AR29,AW29,BH29,BM29,BR29,CC29,CH29,CM29) -> 0 | M29: =SUM(S29,X29,AC29,AN29,AS29,AX29,BI29,BN29,BS29,CD29,CI29,CN29) -> 0 | N29: =SUM(T29,Y29,AD29,AO29,AT29,AY29,BJ29,BO29,BT29,CE29,CJ29,CO29) -> 0 | S29: =P29-Q29 -> 0 | X29: =U29-V29 -> 0 | AD29: =AA29-AB29 -> 0 | AH29: =AE29-AF29 -> 0 | AN29: =AK29-AL29 -> 0 | AS29: =AP29-AQ29 -> 0 | AX29: =AU29-AV29 -> 0 | BC29: =AZ29-BA29 -> 0 | BI29: =BF29-BG29 -> 0 | BN29: =BK29-BL29 -> 0 | BS29: =BP29-BQ29 -> 0 | BX29: =BU29-BV29 -> 0 | CD29: =CA29-CB29 -> 0 | CI29: =CF29-CG29 -> 0 | CN29: =CK29-CL29 -> 0 | CS29: =CP29-CQ29 -> 0
A30: 21 | F30: 車両収入手数料 | J30: =SUM(P30,U30,Z30,AK30,AP30,AU30,BF30,BK30,BP30,CA30,CF30,CK30) -> 0 | K30: =SUM(Q30,V30,AA30,AL30,AQ30,AV30,BG30,BL30,BQ30,CB30,CG30,CL30) -> 0 | L30: =SUM(R30,W30,AB30,AM30,AR30,AW30,BH30,BM30,BR30,CC30,CH30,CM30) -> 0 | M30: =SUM(S30,X30,AC30,AN30,AS30,AX30,BI30,BN30,BS30,CD30,CI30,CN30) -> 0 | N30: =SUM(T30,Y30,AD30,AO30,AT30,AY30,BJ30,BO30,BT30,CE30,CJ30,CO30) -> 0 | S30: =P30-Q30 -> 0 | X30: =U30-V30 -> 0 | AD30: =AA30-AB30 -> 0 | AH30: =AE30-AF30 -> 0 | AN30: =AK30-AL30 -> 0 | AS30: =AP30-AQ30 -> 0 | AX30: =AU30-AV30 -> 0 | BC30: =AZ30-BA30 -> 0 | BI30: =BF30-BG30 -> 0 | BN30: =BK30-BL30 -> 0 | BS30: =BP30-BQ30 -> 0 | BX30: =BU30-BV30 -> 0 | CD30: =CA30-CB30 -> 0 | CI30: =CF30-CG30 -> 0 | CN30: =CK30-CL30 -> 0 | CS30: =CP30-CQ30 -> 0
A31: 22 | F31: 登録収入手数料 | J31: =SUM(P31,U31,Z31,AK31,AP31,AU31,BF31,BK31,BP31,CA31,CF31,CK31) -> 0 | K31: =SUM(Q31,V31,AA31,AL31,AQ31,AV31,BG31,BL31,BQ31,CB31,CG31,CL31) -> 0 | L31: =SUM(R31,W31,AB31,AM31,AR31,AW31,BH31,BM31,BR31,CC31,CH31,CM31) -> 0 | M31: =SUM(S31,X31,AC31,AN31,AS31,AX31,BI31,BN31,BS31,CD31,CI31,CN31) -> 0 | N31: =SUM(T31,Y31,AD31,AO31,AT31,AY31,BJ31,BO31,BT31,CE31,CJ31,CO31) -> 0 | S31: =P31-Q31 -> 0 | X31: =U31-V31 -> 0 | AD31: =AA31-AB31 -> 0 | AH31: =AE31-AF31 -> 0 | AN31: =AK31-AL31 -> 0 | AS31: =AP31-AQ31 -> 0 | AX31: =AU31-AV31 -> 0 | BC31: =AZ31-BA31 -> 0 | BI31: =BF31-BG31 -> 0 | BN31: =BK31-BL31 -> 0 | BS31: =BP31-BQ31 -> 0 | BX31: =BU31-BV31 -> 0 | CD31: =CA31-CB31 -> 0 | CI31: =CF31-CG31 -> 0 | CN31: =CK31-CL31 -> 0 | CS31: =CP31-CQ31 -> 0
A32: 23 | F32: クレジット利益 | J32: =SUM(P32,U32,Z32,AK32,AP32,AU32,BF32,BK32,BP32,CA32,CF32,CK32) -> 0 | K32: =SUM(Q32,V32,AA32,AL32,AQ32,AV32,BG32,BL32,BQ32,CB32,CG32,CL32) -> 0 | L32: =SUM(R32,W32,AB32,AM32,AR32,AW32,BH32,BM32,BR32,CC32,CH32,CM32) -> 0 | M32: =SUM(S32,X32,AC32,AN32,AS32,AX32,BI32,BN32,BS32,CD32,CI32,CN32) -> 0 | N32: =SUM(T32,Y32,AD32,AO32,AT32,AY32,BJ32,BO32,BT32,CE32,CJ32,CO32) -> 0 | S32: =P32-Q32 -> 0 | X32: =U32-V32 -> 0 | AD32: =AA32-AB32 -> 0 | AH32: =AE32-AF32 -> 0 | AN32: =AK32-AL32 -> 0 | AS32: =AP32-AQ32 -> 0 | AX32: =AU32-AV32 -> 0 | BC32: =AZ32-BA32 -> 0 | BI32: =BF32-BG32 -> 0 | BN32: =BK32-BL32 -> 0 | BS32: =BP32-BQ32 -> 0 | BX32: =BU32-BV32 -> 0 | CD32: =CA32-CB32 -> 0 | CI32: =CF32-CG32 -> 0 | CN32: =CK32-CL32 -> 0 | CS32: =CP32-CQ32 -> 0
A33: 24 | F33: 販売手数料 | J33: =SUM(P33,U33,Z33,AK33,AP33,AU33,BF33,BK33,BP33,CA33,CF33,CK33) -> 0 | K33: =SUM(Q33,V33,AA33,AL33,AQ33,AV33,BG33,BL33,BQ33,CB33,CG33,CL33) -> 0 | L33: =SUM(R33,W33,AB33,AM33,AR33,AW33,BH33,BM33,BR33,CC33,CH33,CM33) -> 0 | M33: =SUM(S33,X33,AC33,AN33,AS33,AX33,BI33,BN33,BS33,CD33,CI33,CN33) -> 0 | N33: =SUM(T33,Y33,AD33,AO33,AT33,AY33,BJ33,BO33,BT33,CE33,CJ33,CO33) -> 0 | S33: =P33-Q33 -> 0 | X33: =U33-V33 -> 0 | AD33: =AA33-AB33 -> 0 | AH33: =AE33-AF33 -> 0 | AN33: =AK33-AL33 -> 0 | AS33: =AP33-AQ33 -> 0 | AX33: =AU33-AV33 -> 0 | BC33: =AZ33-BA33 -> 0 | BI33: =BF33-BG33 -> 0 | BN33: =BK33-BL33 -> 0 | BS33: =BP33-BQ33 -> 0 | BX33: =BU33-BV33 -> 0 | CD33: =CA33-CB33 -> 0 | CI33: =CF33-CG33 -> 0 | CN33: =CK33-CL33 -> 0 | CS33: =CP33-CQ33 -> 0
A34: 25 | E34: 新車総粗利 | J34: =SUM(P34,U34,Z34,AK34,AP34,AU34,BF34,BK34,BP34,CA34,CF34,CK34) -> 0 | K34: =SUM(Q34,V34,AA34,AL34,AQ34,AV34,BG34,BL34,BQ34,CB34,CG34,CL34) -> 0 | L34: =SUM(R34,W34,AB34,AM34,AR34,AW34,BH34,BM34,BR34,CC34,CH34,CM34) -> 0 | M34: =SUM(S34,X34,AC34,AN34,AS34,AX34,BI34,BN34,BS34,CD34,CI34,CN34) -> 0 | N34: =SUM(T34,Y34,AD34,AO34,AT34,AY34,BJ34,BO34,BT34,CE34,CJ34,CO34) -> 0 | S34: =P34-Q34 -> 0 | X34: =U34-V34 -> 0 | AD34: =AA34-AB34 -> 0 | AH34: =AE34-AF34 -> 0 | AN34: =AK34-AL34 -> 0 | AS34: =AP34-AQ34 -> 0 | AX34: =AU34-AV34 -> 0 | BC34: =AZ34-BA34 -> 0 | BI34: =BF34-BG34 -> 0 | BN34: =BK34-BL34 -> 0 | BS34: =BP34-BQ34 -> 0 | BX34: =BU34-BV34 -> 0 | CD34: =CA34-CB34 -> 0 | CI34: =CF34-CG34 -> 0 | CN34: =CK34-CL34 -> 0 | CS34: =CP34-CQ34 -> 0
A35: 26 | E35: 販売費 | F35: 販手・サービス・雑費 | J35: =SUM(P35,U35,Z35,AK35,AP35,AU35,BF35,BK35,BP35,CA35,CF35,CK35) -> 0 | K35: =SUM(Q35,V35,AA35,AL35,AQ35,AV35,BG35,BL35,BQ35,CB35,CG35,CL35) -> 0 | L35: =SUM(R35,W35,AB35,AM35,AR35,AW35,BH35,BM35,BR35,CC35,CH35,CM35) -> 0 | M35: =SUM(S35,X35,AC35,AN35,AS35,AX35,BI35,BN35,BS35,CD35,CI35,CN35) -> 0 | N35: =SUM(T35,Y35,AD35,AO35,AT35,AY35,BJ35,BO35,BT35,CE35,CJ35,CO35) -> 0 | S35: =P35-Q35 -> 0 | X35: =U35-V35 -> 0 | AD35: =AA35-AB35 -> 0 | AH35: =AE35-AF35 -> 0 | AN35: =AK35-AL35 -> 0 | AS35: =AP35-AQ35 -> 0 | AX35: =AU35-AV35 -> 0 | BC35: =AZ35-BA35 -> 0 | BI35: =BF35-BG35 -> 0 | BN35: =BK35-BL35 -> 0 | BS35: =BP35-BQ35 -> 0 | BX35: =BU35-BV35 -> 0 | CD35: =CA35-CB35 -> 0 | CI35: =CF35-CG35 -> 0 | CN35: =CK35-CL35 -> 0 | CS35: =CP35-CQ35 -> 0
A36: 27 | F36: 納車費・運送保管費 | J36: =SUM(P36,U36,Z36,AK36,AP36,AU36,BF36,BK36,BP36,CA36,CF36,CK36) -> 0 | K36: =SUM(Q36,V36,AA36,AL36,AQ36,AV36,BG36,BL36,BQ36,CB36,CG36,CL36) -> 0 | L36: =SUM(R36,W36,AB36,AM36,AR36,AW36,BH36,BM36,BR36,CC36,CH36,CM36) -> 0 | M36: =SUM(S36,X36,AC36,AN36,AS36,AX36,BI36,BN36,BS36,CD36,CI36,CN36) -> 0 | N36: =SUM(T36,Y36,AD36,AO36,AT36,AY36,BJ36,BO36,BT36,CE36,CJ36,CO36) -> 0 | S36: =P36-Q36 -> 0 | X36: =U36-V36 -> 0 | AD36: =AA36-AB36 -> 0 | AH36: =AE36-AF36 -> 0 | AN36: =AK36-AL36 -> 0 | AS36: =AP36-AQ36 -> 0 | AX36: =AU36-AV36 -> 0 | BC36: =AZ36-BA36 -> 0 | BI36: =BF36-BG36 -> 0 | BN36: =BK36-BL36 -> 0 | BS36: =BP36-BQ36 -> 0 | BX36: =BU36-BV36 -> 0 | CD36: =CA36-CB36 -> 0 | CI36: =CF36-CG36 -> 0 | CN36: =CK36-CL36 -> 0 | CS36: =CP36-CQ36 -> 0
A37: 28 | F37: 広告宣伝費 | J37: =SUM(P37,U37,Z37,AK37,AP37,AU37,BF37,BK37,BP37,CA37,CF37,CK37) -> 0 | K37: =SUM(Q37,V37,AA37,AL37,AQ37,AV37,BG37,BL37,BQ37,CB37,CG37,CL37) -> 0 | L37: =SUM(R37,W37,AB37,AM37,AR37,AW37,BH37,BM37,BR37,CC37,CH37,CM37) -> 0 | M37: =SUM(S37,X37,AC37,AN37,AS37,AX37,BI37,BN37,BS37,CD37,CI37,CN37) -> 0 | N37: =SUM(T37,Y37,AD37,AO37,AT37,AY37,BJ37,BO37,BT37,CE37,CJ37,CO37) -> 0 | S37: =P37-Q37 -> 0 | X37: =U37-V37 -> 0 | AD37: =AA37-AB37 -> 0 | AH37: =AE37-AF37 -> 0 | AN37: =AK37-AL37 -> 0 | AS37: =AP37-AQ37 -> 0 | AX37: =AU37-AV37 -> 0 | BC37: =AZ37-BA37 -> 0 | BI37: =BF37-BG37 -> 0 | BN37: =BK37-BL37 -> 0 | BS37: =BP37-BQ37 -> 0 | BX37: =BU37-BV37 -> 0 | CD37: =CA37-CB37 -> 0 | CI37: =CF37-CG37 -> 0 | CN37: =CK37-CL37 -> 0 | CS37: =CP37-CQ37 -> 0
A38: 29 | F38: デモカー・代車費 | J38: =SUM(P38,U38,Z38,AK38,AP38,AU38,BF38,BK38,BP38,CA38,CF38,CK38) -> 0 | K38: =SUM(Q38,V38,AA38,AL38,AQ38,AV38,BG38,BL38,BQ38,CB38,CG38,CL38) -> 0 | L38: =SUM(R38,W38,AB38,AM38,AR38,AW38,BH38,BM38,BR38,CC38,CH38,CM38) -> 0 | M38: =SUM(S38,X38,AC38,AN38,AS38,AX38,BI38,BN38,BS38,CD38,CI38,CN38) -> 0 | N38: =SUM(T38,Y38,AD38,AO38,AT38,AY38,BJ38,BO38,BT38,CE38,CJ38,CO38) -> 0 | S38: =P38-Q38 -> 0 | X38: =U38-V38 -> 0 | AD38: =AA38-AB38 -> 0 | AH38: =AE38-AF38 -> 0 | AN38: =AK38-AL38 -> 0 | AS38: =AP38-AQ38 -> 0 | AX38: =AU38-AV38 -> 0 | BC38: =AZ38-BA38 -> 0 | BI38: =BF38-BG38 -> 0 | BN38: =BK38-BL38 -> 0 | BS38: =BP38-BQ38 -> 0 | BX38: =BU38-BV38 -> 0 | CD38: =CA38-CB38 -> 0 | CI38: =CF38-CG38 -> 0 | CN38: =CK38-CL38 -> 0 | CS38: =CP38-CQ38 -> 0
A39: 30 | F39: 本部負担金 | J39: =SUM(P39,U39,Z39,AK39,AP39,AU39,BF39,BK39,BP39,CA39,CF39,CK39) -> 0 | K39: =SUM(Q39,V39,AA39,AL39,AQ39,AV39,BG39,BL39,BQ39,CB39,CG39,CL39) -> 0 | L39: =SUM(R39,W39,AB39,AM39,AR39,AW39,BH39,BM39,BR39,CC39,CH39,CM39) -> 0 | M39: =SUM(S39,X39,AC39,AN39,AS39,AX39,BI39,BN39,BS39,CD39,CI39,CN39) -> 0 | N39: =SUM(T39,Y39,AD39,AO39,AT39,AY39,BJ39,BO39,BT39,CE39,CJ39,CO39) -> 0 | S39: =P39-Q39 -> 0 | X39: =U39-V39 -> 0 | AD39: =AA39-AB39 -> 0 | AH39: =AE39-AF39 -> 0 | AN39: =AK39-AL39 -> 0 | AS39: =AP39-AQ39 -> 0 | AX39: =AU39-AV39 -> 0 | BC39: =AZ39-BA39 -> 0 | BI39: =BF39-BG39 -> 0 | BN39: =BK39-BL39 -> 0 | BS39: =BP39-BQ39 -> 0 | BX39: =BU39-BV39 -> 0 | CD39: =CA39-CB39 -> 0 | CI39: =CF39-CG39 -> 0 | CN39: =CK39-CL39 -> 0 | CS39: =CP39-CQ39 -> 0
A40: 31 | F40: 小計 | J40: =SUM(P40,U40,Z40,AK40,AP40,AU40,BF40,BK40,BP40,CA40,CF40,CK40) -> 0 | K40: =SUM(Q40,V40,AA40,AL40,AQ40,AV40,BG40,BL40,BQ40,CB40,CG40,CL40) -> 0 | L40: =SUM(R40,W40,AB40,AM40,AR40,AW40,BH40,BM40,BR40,CC40,CH40,CM40) -> 0 | M40: =SUM(S40,X40,AC40,AN40,AS40,AX40,BI40,BN40,BS40,CD40,CI40,CN40) -> 0 | N40: =SUM(T40,Y40,AD40,AO40,AT40,AY40,BJ40,BO40,BT40,CE40,CJ40,CO40) -> 0 | S40: =P40-Q40 -> 0 | X40: =U40-V40 -> 0 | AD40: =AA40-AB40 -> 0 | AH40: =AE40-AF40 -> 0 | AN40: =AK40-AL40 -> 0 | AS40: =AP40-AQ40 -> 0 | AX40: =AU40-AV40 -> 0 | BC40: =AZ40-BA40 -> 0 | BI40: =BF40-BG40 -> 0 | BN40: =BK40-BL40 -> 0 | BS40: =BP40-BQ40 -> 0 | BX40: =BU40-BV40 -> 0 | CD40: =CA40-CB40 -> 0 | CI40: =CF40-CG40 -> 0 | CN40: =CK40-CL40 -> 0 | CS40: =CP40-CQ40 -> 0
A41: 32 | E41: 新車限界利益 | J41: =SUM(P41,U41,Z41,AK41,AP41,AU41,BF41,BK41,BP41,CA41,CF41,CK41) -> 0 | K41: =SUM(Q41,V41,AA41,AL41,AQ41,AV41,BG41,BL41,BQ41,CB41,CG41,CL41) -> 0 | L41: =SUM(R41,W41,AB41,AM41,AR41,AW41,BH41,BM41,BR41,CC41,CH41,CM41) -> 0 | M41: =SUM(S41,X41,AC41,AN41,AS41,AX41,BI41,BN41,BS41,CD41,CI41,CN41) -> 0 | N41: =SUM(T41,Y41,AD41,AO41,AT41,AY41,BJ41,BO41,BT41,CE41,CJ41,CO41) -> 0 | S41: =P41-Q41 -> 0 | X41: =U41-V41 -> 0 | AD41: =AA41-AB41 -> 0 | AH41: =AE41-AF41 -> 0 | AN41: =AK41-AL41 -> 0 | AS41: =AP41-AQ41 -> 0 | AX41: =AU41-AV41 -> 0 | BC41: =AZ41-BA41 -> 0 | BI41: =BF41-BG41 -> 0 | BN41: =BK41-BL41 -> 0 | BS41: =BP41-BQ41 -> 0 | BX41: =BU41-BV41 -> 0 | CD41: =CA41-CB41 -> 0 | CI41: =CF41-CG41 -> 0 | CN41: =CK41-CL41 -> 0 | CS41: =CP41-CQ41 -> 0
A42: 33 | D42: 中古車 | E42: 直売 | F42: 直売台数 | J42: =SUM(P42,U42,Z42,AK42,AP42,AU42,BF42,BK42,BP42,CA42,CF42,CK42) -> 0 | K42: =SUM(Q42,V42,AA42,AL42,AQ42,AV42,BG42,BL42,BQ42,CB42,CG42,CL42) -> 0 | L42: =SUM(R42,W42,AB42,AM42,AR42,AW42,BH42,BM42,BR42,CC42,CH42,CM42) -> 0 | M42: =SUM(S42,X42,AC42,AN42,AS42,AX42,BI42,BN42,BS42,CD42,CI42,CN42) -> 0 | N42: =SUM(T42,Y42,AD42,AO42,AT42,AY42,BJ42,BO42,BT42,CE42,CJ42,CO42) -> 0 | S42: =P42-Q42 -> 0 | X42: =U42-V42 -> 0 | AD42: =AA42-AB42 -> 0 | AH42: =AE42-AF42 -> 0 | AN42: =AK42-AL42 -> 0 | AS42: =AP42-AQ42 -> 0 | AX42: =AU42-AV42 -> 0 | BC42: =AZ42-BA42 -> 0 | BI42: =BF42-BG42 -> 0 | BN42: =BK42-BL42 -> 0 | BS42: =BP42-BQ42 -> 0 | BX42: =BU42-BV42 -> 0 | CD42: =CA42-CB42 -> 0 | CI42: =CF42-CG42 -> 0 | CN42: =CK42-CL42 -> 0 | CS42: =CP42-CQ42 -> 0
A43: 34 | F43: 売上金額 | J43: =SUM(P43,U43,Z43,AK43,AP43,AU43,BF43,BK43,BP43,CA43,CF43,CK43) -> 0 | K43: =SUM(Q43,V43,AA43,AL43,AQ43,AV43,BG43,BL43,BQ43,CB43,CG43,CL43) -> 0 | L43: =SUM(R43,W43,AB43,AM43,AR43,AW43,BH43,BM43,BR43,CC43,CH43,CM43) -> 0 | M43: =SUM(S43,X43,AC43,AN43,AS43,AX43,BI43,BN43,BS43,CD43,CI43,CN43) -> 0 | N43: =SUM(T43,Y43,AD43,AO43,AT43,AY43,BJ43,BO43,BT43,CE43,CJ43,CO43) -> 0 | S43: =P43-Q43 -> 0 | X43: =U43-V43 -> 0 | AD43: =AA43-AB43 -> 0 | AH43: =AE43-AF43 -> 0 | AN43: =AK43-AL43 -> 0 | AS43: =AP43-AQ43 -> 0 | AX43: =AU43-AV43 -> 0 | BC43: =AZ43-BA43 -> 0 | BI43: =BF43-BG43 -> 0 | BN43: =BK43-BL43 -> 0 | BS43: =BP43-BQ43 -> 0 | BX43: =BU43-BV43 -> 0 | CD43: =CA43-CB43 -> 0 | CI43: =CF43-CG43 -> 0 | CN43: =CK43-CL43 -> 0 | CS43: =CP43-CQ43 -> 0
A44: 35 | F44: 車両本体利益 | J44: =SUM(P44,U44,Z44,AK44,AP44,AU44,BF44,BK44,BP44,CA44,CF44,CK44) -> 0 | K44: =SUM(Q44,V44,AA44,AL44,AQ44,AV44,BG44,BL44,BQ44,CB44,CG44,CL44) -> 0 | L44: =SUM(R44,W44,AB44,AM44,AR44,AW44,BH44,BM44,BR44,CC44,CH44,CM44) -> 0 | M44: =SUM(S44,X44,AC44,AN44,AS44,AX44,BI44,BN44,BS44,CD44,CI44,CN44) -> 0 | N44: =SUM(T44,Y44,AD44,AO44,AT44,AY44,BJ44,BO44,BT44,CE44,CJ44,CO44) -> 0 | S44: =P44-Q44 -> 0 | X44: =U44-V44 -> 0 | AD44: =AA44-AB44 -> 0 | AH44: =AE44-AF44 -> 0 | AN44: =AK44-AL44 -> 0 | AS44: =AP44-AQ44 -> 0 | AX44: =AU44-AV44 -> 0 | BC44: =AZ44-BA44 -> 0 | BI44: =BF44-BG44 -> 0 | BN44: =BK44-BL44 -> 0 | BS44: =BP44-BQ44 -> 0 | BX44: =BU44-BV44 -> 0 | CD44: =CA44-CB44 -> 0 | CI44: =CF44-CG44 -> 0 | CN44: =CK44-CL44 -> 0 | CS44: =CP44-CQ44 -> 0
A45: 36 | F45: 車両収入手数料 | J45: =SUM(P45,U45,Z45,AK45,AP45,AU45,BF45,BK45,BP45,CA45,CF45,CK45) -> 0 | K45: =SUM(Q45,V45,AA45,AL45,AQ45,AV45,BG45,BL45,BQ45,CB45,CG45,CL45) -> 0 | L45: =SUM(R45,W45,AB45,AM45,AR45,AW45,BH45,BM45,BR45,CC45,CH45,CM45) -> 0 | M45: =SUM(S45,X45,AC45,AN45,AS45,AX45,BI45,BN45,BS45,CD45,CI45,CN45) -> 0 | N45: =SUM(T45,Y45,AD45,AO45,AT45,AY45,BJ45,BO45,BT45,CE45,CJ45,CO45) -> 0 | S45: =P45-Q45 -> 0 | X45: =U45-V45 -> 0 | AD45: =AA45-AB45 -> 0 | AH45: =AE45-AF45 -> 0 | AN45: =AK45-AL45 -> 0 | AS45: =AP45-AQ45 -> 0 | AX45: =AU45-AV45 -> 0 | BC45: =AZ45-BA45 -> 0 | BI45: =BF45-BG45 -> 0 | BN45: =BK45-BL45 -> 0 | BS45: =BP45-BQ45 -> 0 | BX45: =BU45-BV45 -> 0 | CD45: =CA45-CB45 -> 0 | CI45: =CF45-CG45 -> 0 | CN45: =CK45-CL45 -> 0 | CS45: =CP45-CQ45 -> 0
A46: 37 | F46: 登録収入手数料 | J46: =SUM(P46,U46,Z46,AK46,AP46,AU46,BF46,BK46,BP46,CA46,CF46,CK46) -> 0 | K46: =SUM(Q46,V46,AA46,AL46,AQ46,AV46,BG46,BL46,BQ46,CB46,CG46,CL46) -> 0 | L46: =SUM(R46,W46,AB46,AM46,AR46,AW46,BH46,BM46,BR46,CC46,CH46,CM46) -> 0 | M46: =SUM(S46,X46,AC46,AN46,AS46,AX46,BI46,BN46,BS46,CD46,CI46,CN46) -> 0 | N46: =SUM(T46,Y46,AD46,AO46,AT46,AY46,BJ46,BO46,BT46,CE46,CJ46,CO46) -> 0 | S46: =P46-Q46 -> 0 | X46: =U46-V46 -> 0 | AD46: =AA46-AB46 -> 0 | AH46: =AE46-AF46 -> 0 | AN46: =AK46-AL46 -> 0 | AS46: =AP46-AQ46 -> 0 | AX46: =AU46-AV46 -> 0 | BC46: =AZ46-BA46 -> 0 | BI46: =BF46-BG46 -> 0 | BN46: =BK46-BL46 -> 0 | BS46: =BP46-BQ46 -> 0 | BX46: =BU46-BV46 -> 0 | CD46: =CA46-CB46 -> 0 | CI46: =CF46-CG46 -> 0 | CN46: =CK46-CL46 -> 0 | CS46: =CP46-CQ46 -> 0
A47: 38 | F47: クレジット利益 | J47: =SUM(P47,U47,Z47,AK47,AP47,AU47,BF47,BK47,BP47,CA47,CF47,CK47) -> 0 | K47: =SUM(Q47,V47,AA47,AL47,AQ47,AV47,BG47,BL47,BQ47,CB47,CG47,CL47) -> 0 | L47: =SUM(R47,W47,AB47,AM47,AR47,AW47,BH47,BM47,BR47,CC47,CH47,CM47) -> 0 | M47: =SUM(S47,X47,AC47,AN47,AS47,AX47,BI47,BN47,BS47,CD47,CI47,CN47) -> 0 | N47: =SUM(T47,Y47,AD47,AO47,AT47,AY47,BJ47,BO47,BT47,CE47,CJ47,CO47) -> 0 | S47: =P47-Q47 -> 0 | X47: =U47-V47 -> 0 | AD47: =AA47-AB47 -> 0 | AH47: =AE47-AF47 -> 0 | AN47: =AK47-AL47 -> 0 | AS47: =AP47-AQ47 -> 0 | AX47: =AU47-AV47 -> 0 | BC47: =AZ47-BA47 -> 0 | BI47: =BF47-BG47 -> 0 | BN47: =BK47-BL47 -> 0 | BS47: =BP47-BQ47 -> 0 | BX47: =BU47-BV47 -> 0 | CD47: =CA47-CB47 -> 0 | CI47: =CF47-CG47 -> 0 | CN47: =CK47-CL47 -> 0 | CS47: =CP47-CQ47 -> 0
A48: 39 | F48: 直売総粗利 | J48: =SUM(P48,U48,Z48,AK48,AP48,AU48,BF48,BK48,BP48,CA48,CF48,CK48) -> 0 | K48: =SUM(Q48,V48,AA48,AL48,AQ48,AV48,BG48,BL48,BQ48,CB48,CG48,CL48) -> 0 | L48: =SUM(R48,W48,AB48,AM48,AR48,AW48,BH48,BM48,BR48,CC48,CH48,CM48) -> 0 | M48: =SUM(S48,X48,AC48,AN48,AS48,AX48,BI48,BN48,BS48,CD48,CI48,CN48) -> 0 | N48: =SUM(T48,Y48,AD48,AO48,AT48,AY48,BJ48,BO48,BT48,CE48,CJ48,CO48) -> 0 | S48: =P48-Q48 -> 0 | X48: =U48-V48 -> 0 | AD48: =AA48-AB48 -> 0 | AH48: =AE48-AF48 -> 0 | AN48: =AK48-AL48 -> 0 | AS48: =AP48-AQ48 -> 0 | AX48: =AU48-AV48 -> 0 | BC48: =AZ48-BA48 -> 0 | BI48: =BF48-BG48 -> 0 | BN48: =BK48-BL48 -> 0 | BS48: =BP48-BQ48 -> 0 | BX48: =BU48-BV48 -> 0 | CD48: =CA48-CB48 -> 0 | CI48: =CF48-CG48 -> 0 | CN48: =CK48-CL48 -> 0 | CS48: =CP48-CQ48 -> 0
A49: 40 | E49: 業売 | F49: 業売台数 | J49: =SUM(P49,U49,Z49,AK49,AP49,AU49,BF49,BK49,BP49,CA49,CF49,CK49) -> 0 | K49: =SUM(Q49,V49,AA49,AL49,AQ49,AV49,BG49,BL49,BQ49,CB49,CG49,CL49) -> 0 | L49: =SUM(R49,W49,AB49,AM49,AR49,AW49,BH49,BM49,BR49,CC49,CH49,CM49) -> 0 | M49: =SUM(S49,X49,AC49,AN49,AS49,AX49,BI49,BN49,BS49,CD49,CI49,CN49) -> 0 | N49: =SUM(T49,Y49,AD49,AO49,AT49,AY49,BJ49,BO49,BT49,CE49,CJ49,CO49) -> 0 | S49: =P49-Q49 -> 0 | X49: =U49-V49 -> 0 | AD49: =AA49-AB49 -> 0 | AH49: =AE49-AF49 -> 0 | AN49: =AK49-AL49 -> 0 | AS49: =AP49-AQ49 -> 0 | AX49: =AU49-AV49 -> 0 | BC49: =AZ49-BA49 -> 0 | BI49: =BF49-BG49 -> 0 | BN49: =BK49-BL49 -> 0 | BS49: =BP49-BQ49 -> 0 | BX49: =BU49-BV49 -> 0 | CD49: =CA49-CB49 -> 0 | CI49: =CF49-CG49 -> 0 | CN49: =CK49-CL49 -> 0 | CS49: =CP49-CQ49 -> 0
A50: 41 | F50: 業売売上 | J50: =SUM(P50,U50,Z50,AK50,AP50,AU50,BF50,BK50,BP50,CA50,CF50,CK50) -> 0 | K50: =SUM(Q50,V50,AA50,AL50,AQ50,AV50,BG50,BL50,BQ50,CB50,CG50,CL50) -> 0 | L50: =SUM(R50,W50,AB50,AM50,AR50,AW50,BH50,BM50,BR50,CC50,CH50,CM50) -> 0 | M50: =SUM(S50,X50,AC50,AN50,AS50,AX50,BI50,BN50,BS50,CD50,CI50,CN50) -> 0 | N50: =SUM(T50,Y50,AD50,AO50,AT50,AY50,BJ50,BO50,BT50,CE50,CJ50,CO50) -> 0 | S50: =P50-Q50 -> 0 | X50: =U50-V50 -> 0 | AD50: =AA50-AB50 -> 0 | AH50: =AE50-AF50 -> 0 | AN50: =AK50-AL50 -> 0 | AS50: =AP50-AQ50 -> 0 | AX50: =AU50-AV50 -> 0 | BC50: =AZ50-BA50 -> 0 | BI50: =BF50-BG50 -> 0 | BN50: =BK50-BL50 -> 0 | BS50: =BP50-BQ50 -> 0 | BX50: =BU50-BV50 -> 0 | CD50: =CA50-CB50 -> 0 | CI50: =CF50-CG50 -> 0 | CN50: =CK50-CL50 -> 0 | CS50: =CP50-CQ50 -> 0
A51: 42 | F51: 業売放出台数 | J51: =SUM(P51,U51,Z51,AK51,AP51,AU51,BF51,BK51,BP51,CA51,CF51,CK51) -> 0 | K51: =SUM(Q51,V51,AA51,AL51,AQ51,AV51,BG51,BL51,BQ51,CB51,CG51,CL51) -> 0 | L51: =SUM(R51,W51,AB51,AM51,AR51,AW51,BH51,BM51,BR51,CC51,CH51,CM51) -> 0 | M51: =SUM(S51,X51,AC51,AN51,AS51,AX51,BI51,BN51,BS51,CD51,CI51,CN51) -> 0 | N51: =SUM(T51,Y51,AD51,AO51,AT51,AY51,BJ51,BO51,BT51,CE51,CJ51,CO51) -> 0 | S51: =P51-Q51 -> 0 | X51: =U51-V51 -> 0 | AD51: =AA51-AB51 -> 0 | AH51: =AE51-AF51 -> 0 | AN51: =AK51-AL51 -> 0 | AS51: =AP51-AQ51 -> 0 | AX51: =AU51-AV51 -> 0 | BC51: =AZ51-BA51 -> 0 | BI51: =BF51-BG51 -> 0 | BN51: =BK51-BL51 -> 0 | BS51: =BP51-BQ51 -> 0 | BX51: =BU51-BV51 -> 0 | CD51: =CA51-CB51 -> 0 | CI51: =CF51-CG51 -> 0 | CN51: =CK51-CL51 -> 0 | CS51: =CP51-CQ51 -> 0
A52: 43 | F52: 業売放出売上 | J52: =SUM(P52,U52,Z52,AK52,AP52,AU52,BF52,BK52,BP52,CA52,CF52,CK52) -> 0 | K52: =SUM(Q52,V52,AA52,AL52,AQ52,AV52,BG52,BL52,BQ52,CB52,CG52,CL52) -> 0 | L52: =SUM(R52,W52,AB52,AM52,AR52,AW52,BH52,BM52,BR52,CC52,CH52,CM52) -> 0 | M52: =SUM(S52,X52,AC52,AN52,AS52,AX52,BI52,BN52,BS52,CD52,CI52,CN52) -> 0 | N52: =SUM(T52,Y52,AD52,AO52,AT52,AY52,BJ52,BO52,BT52,CE52,CJ52,CO52) -> 0 | S52: =P52-Q52 -> 0 | X52: =U52-V52 -> 0 | AD52: =AA52-AB52 -> 0 | AH52: =AE52-AF52 -> 0 | AN52: =AK52-AL52 -> 0 | AS52: =AP52-AQ52 -> 0 | AX52: =AU52-AV52 -> 0 | BC52: =AZ52-BA52 -> 0 | BI52: =BF52-BG52 -> 0 | BN52: =BK52-BL52 -> 0 | BS52: =BP52-BQ52 -> 0 | BX52: =BU52-BV52 -> 0 | CD52: =CA52-CB52 -> 0 | CI52: =CF52-CG52 -> 0 | CN52: =CK52-CL52 -> 0 | CS52: =CP52-CQ52 -> 0
A53: 44 | F53: 業売スクラップ台数 | J53: =SUM(P53,U53,Z53,AK53,AP53,AU53,BF53,BK53,BP53,CA53,CF53,CK53) -> 0 | K53: =SUM(Q53,V53,AA53,AL53,AQ53,AV53,BG53,BL53,BQ53,CB53,CG53,CL53) -> 0 | L53: =SUM(R53,W53,AB53,AM53,AR53,AW53,BH53,BM53,BR53,CC53,CH53,CM53) -> 0 | M53: =SUM(S53,X53,AC53,AN53,AS53,AX53,BI53,BN53,BS53,CD53,CI53,CN53) -> 0 | N53: =SUM(T53,Y53,AD53,AO53,AT53,AY53,BJ53,BO53,BT53,CE53,CJ53,CO53) -> 0 | S53: =P53-Q53 -> 0 | X53: =U53-V53 -> 0 | AD53: =AA53-AB53 -> 0 | AH53: =AE53-AF53 -> 0 | AN53: =AK53-AL53 -> 0 | AS53: =AP53-AQ53 -> 0 | AX53: =AU53-AV53 -> 0 | BC53: =AZ53-BA53 -> 0 | BI53: =BF53-BG53 -> 0 | BN53: =BK53-BL53 -> 0 | BS53: =BP53-BQ53 -> 0 | BX53: =BU53-BV53 -> 0 | CD53: =CA53-CB53 -> 0 | CI53: =CF53-CG53 -> 0 | CN53: =CK53-CL53 -> 0 | CS53: =CP53-CQ53 -> 0
A54: 45 | F54: 業売スクラップ売上 | J54: =SUM(P54,U54,Z54,AK54,AP54,AU54,BF54,BK54,BP54,CA54,CF54,CK54) -> 0 | K54: =SUM(Q54,V54,AA54,AL54,AQ54,AV54,BG54,BL54,BQ54,CB54,CG54,CL54) -> 0 | L54: =SUM(R54,W54,AB54,AM54,AR54,AW54,BH54,BM54,BR54,CC54,CH54,CM54) -> 0 | M54: =SUM(S54,X54,AC54,AN54,AS54,AX54,BI54,BN54,BS54,CD54,CI54,CN54) -> 0 | N54: =SUM(T54,Y54,AD54,AO54,AT54,AY54,BJ54,BO54,BT54,CE54,CJ54,CO54) -> 0 | S54: =P54-Q54 -> 0 | X54: =U54-V54 -> 0 | AD54: =AA54-AB54 -> 0 | AH54: =AE54-AF54 -> 0 | AN54: =AK54-AL54 -> 0 | AS54: =AP54-AQ54 -> 0 | AX54: =AU54-AV54 -> 0 | BC54: =AZ54-BA54 -> 0 | BI54: =BF54-BG54 -> 0 | BN54: =BK54-BL54 -> 0 | BS54: =BP54-BQ54 -> 0 | BX54: =BU54-BV54 -> 0 | CD54: =CA54-CB54 -> 0 | CI54: =CF54-CG54 -> 0 | CN54: =CK54-CL54 -> 0 | CS54: =CP54-CQ54 -> 0
A55: 46 | F55: 業販粗利益 | J55: =SUM(P55,U55,Z55,AK55,AP55,AU55,BF55,BK55,BP55,CA55,CF55,CK55) -> 0 | K55: =SUM(Q55,V55,AA55,AL55,AQ55,AV55,BG55,BL55,BQ55,CB55,CG55,CL55) -> 0 | L55: =SUM(R55,W55,AB55,AM55,AR55,AW55,BH55,BM55,BR55,CC55,CH55,CM55) -> 0 | M55: =SUM(S55,X55,AC55,AN55,AS55,AX55,BI55,BN55,BS55,CD55,CI55,CN55) -> 0 | N55: =SUM(T55,Y55,AD55,AO55,AT55,AY55,BJ55,BO55,BT55,CE55,CJ55,CO55) -> 0 | S55: =P55-Q55 -> 0 | X55: =U55-V55 -> 0 | AD55: =AA55-AB55 -> 0 | AH55: =AE55-AF55 -> 0 | AN55: =AK55-AL55 -> 0 | AS55: =AP55-AQ55 -> 0 | AX55: =AU55-AV55 -> 0 | BC55: =AZ55-BA55 -> 0 | BI55: =BF55-BG55 -> 0 | BN55: =BK55-BL55 -> 0 | BS55: =BP55-BQ55 -> 0 | BX55: =BU55-BV55 -> 0 | CD55: =CA55-CB55 -> 0 | CI55: =CF55-CG55 -> 0 | CN55: =CK55-CL55 -> 0 | CS55: =CP55-CQ55 -> 0
A56: 47 | E56: 台数合計 | J56: =SUM(P56,U56,Z56,AK56,AP56,AU56,BF56,BK56,BP56,CA56,CF56,CK56) -> 0 | K56: =SUM(Q56,V56,AA56,AL56,AQ56,AV56,BG56,BL56,BQ56,CB56,CG56,CL56) -> 0 | L56: =SUM(R56,W56,AB56,AM56,AR56,AW56,BH56,BM56,BR56,CC56,CH56,CM56) -> 0 | M56: =SUM(S56,X56,AC56,AN56,AS56,AX56,BI56,BN56,BS56,CD56,CI56,CN56) -> 0 | N56: =SUM(T56,Y56,AD56,AO56,AT56,AY56,BJ56,BO56,BT56,CE56,CJ56,CO56) -> 0 | S56: =P56-Q56 -> 0 | X56: =U56-V56 -> 0 | AD56: =AA56-AB56 -> 0 | AH56: =AE56-AF56 -> 0 | AN56: =AK56-AL56 -> 0 | AS56: =AP56-AQ56 -> 0 | AX56: =AU56-AV56 -> 0 | BC56: =AZ56-BA56 -> 0 | BI56: =BF56-BG56 -> 0 | BN56: =BK56-BL56 -> 0 | BS56: =BP56-BQ56 -> 0 | BX56: =BU56-BV56 -> 0 | CD56: =CA56-CB56 -> 0 | CI56: =CF56-CG56 -> 0 | CN56: =CK56-CL56 -> 0 | CS56: =CP56-CQ56 -> 0
A57: 48 | E57: 粗利益計 | J57: =SUM(P57,U57,Z57,AK57,AP57,AU57,BF57,BK57,BP57,CA57,CF57,CK57) -> 0 | K57: =SUM(Q57,V57,AA57,AL57,AQ57,AV57,BG57,BL57,BQ57,CB57,CG57,CL57) -> 0 | L57: =SUM(R57,W57,AB57,AM57,AR57,AW57,BH57,BM57,BR57,CC57,CH57,CM57) -> 0 | M57: =SUM(S57,X57,AC57,AN57,AS57,AX57,BI57,BN57,BS57,CD57,CI57,CN57) -> 0 | N57: =SUM(T57,Y57,AD57,AO57,AT57,AY57,BJ57,BO57,BT57,CE57,CJ57,CO57) -> 0 | S57: =P57-Q57 -> 0 | X57: =U57-V57 -> 0 | AD57: =AA57-AB57 -> 0 | AH57: =AE57-AF57 -> 0 | AN57: =AK57-AL57 -> 0 | AS57: =AP57-AQ57 -> 0 | AX57: =AU57-AV57 -> 0 | BC57: =AZ57-BA57 -> 0 | BI57: =BF57-BG57 -> 0 | BN57: =BK57-BL57 -> 0 | BS57: =BP57-BQ57 -> 0 | BX57: =BU57-BV57 -> 0 | CD57: =CA57-CB57 -> 0 | CI57: =CF57-CG57 -> 0 | CN57: =CK57-CL57 -> 0 | CS57: =CP57-CQ57 -> 0
A58: 49 | E58: 車両収入手数料計 | J58: =SUM(P58,U58,Z58,AK58,AP58,AU58,BF58,BK58,BP58,CA58,CF58,CK58) -> 0 | K58: =SUM(Q58,V58,AA58,AL58,AQ58,AV58,BG58,BL58,BQ58,CB58,CG58,CL58) -> 0 | L58: =SUM(R58,W58,AB58,AM58,AR58,AW58,BH58,BM58,BR58,CC58,CH58,CM58) -> 0 | M58: =SUM(S58,X58,AC58,AN58,AS58,AX58,BI58,BN58,BS58,CD58,CI58,CN58) -> 0 | N58: =SUM(T58,Y58,AD58,AO58,AT58,AY58,BJ58,BO58,BT58,CE58,CJ58,CO58) -> 0 | S58: =P58-Q58 -> 0 | X58: =U58-V58 -> 0 | AD58: =AA58-AB58 -> 0 | AH58: =AE58-AF58 -> 0 | AN58: =AK58-AL58 -> 0 | AS58: =AP58-AQ58 -> 0 | AX58: =AU58-AV58 -> 0 | BC58: =AZ58-BA58 -> 0 | BI58: =BF58-BG58 -> 0 | BN58: =BK58-BL58 -> 0 | BS58: =BP58-BQ58 -> 0 | BX58: =BU58-BV58 -> 0 | CD58: =CA58-CB58 -> 0 | CI58: =CF58-CG58 -> 0 | CN58: =CK58-CL58 -> 0 | CS58: =CP58-CQ58 -> 0
A59: 50 | E59: 登録収入手数料計 | J59: =SUM(P59,U59,Z59,AK59,AP59,AU59,BF59,BK59,BP59,CA59,CF59,CK59) -> 0 | K59: =SUM(Q59,V59,AA59,AL59,AQ59,AV59,BG59,BL59,BQ59,CB59,CG59,CL59) -> 0 | L59: =SUM(R59,W59,AB59,AM59,AR59,AW59,BH59,BM59,BR59,CC59,CH59,CM59) -> 0 | M59: =SUM(S59,X59,AC59,AN59,AS59,AX59,BI59,BN59,BS59,CD59,CI59,CN59) -> 0 | N59: =SUM(T59,Y59,AD59,AO59,AT59,AY59,BJ59,BO59,BT59,CE59,CJ59,CO59) -> 0 | S59: =P59-Q59 -> 0 | X59: =U59-V59 -> 0 | AD59: =AA59-AB59 -> 0 | AH59: =AE59-AF59 -> 0 | AN59: =AK59-AL59 -> 0 | AS59: =AP59-AQ59 -> 0 | AX59: =AU59-AV59 -> 0 | BC59: =AZ59-BA59 -> 0 | BI59: =BF59-BG59 -> 0 | BN59: =BK59-BL59 -> 0 | BS59: =BP59-BQ59 -> 0 | BX59: =BU59-BV59 -> 0 | CD59: =CA59-CB59 -> 0 | CI59: =CF59-CG59 -> 0 | CN59: =CK59-CL59 -> 0 | CS59: =CP59-CQ59 -> 0
A60: 51 | E60: クレジット利益計 | J60: =SUM(P60,U60,Z60,AK60,AP60,AU60,BF60,BK60,BP60,CA60,CF60,CK60) -> 0 | K60: =SUM(Q60,V60,AA60,AL60,AQ60,AV60,BG60,BL60,BQ60,CB60,CG60,CL60) -> 0 | L60: =SUM(R60,W60,AB60,AM60,AR60,AW60,BH60,BM60,BR60,CC60,CH60,CM60) -> 0 | M60: =SUM(S60,X60,AC60,AN60,AS60,AX60,BI60,BN60,BS60,CD60,CI60,CN60) -> 0 | N60: =SUM(T60,Y60,AD60,AO60,AT60,AY60,BJ60,BO60,BT60,CE60,CJ60,CO60) -> 0 | S60: =P60-Q60 -> 0 | X60: =U60-V60 -> 0 | AD60: =AA60-AB60 -> 0 | AH60: =AE60-AF60 -> 0 | AN60: =AK60-AL60 -> 0 | AS60: =AP60-AQ60 -> 0 | AX60: =AU60-AV60 -> 0 | BC60: =AZ60-BA60 -> 0 | BI60: =BF60-BG60 -> 0 | BN60: =BK60-BL60 -> 0 | BS60: =BP60-BQ60 -> 0 | BX60: =BU60-BV60 -> 0 | CD60: =CA60-CB60 -> 0 | CI60: =CF60-CG60 -> 0 | CN60: =CK60-CL60 -> 0 | CS60: =CP60-CQ60 -> 0
A61: 52 | E61: 再生員給与 | J61: =SUM(P61,U61,Z61,AK61,AP61,AU61,BF61,BK61,BP61,CA61,CF61,CK61) -> 0 | K61: =SUM(Q61,V61,AA61,AL61,AQ61,AV61,BG61,BL61,BQ61,CB61,CG61,CL61) -> 0 | L61: =SUM(R61,W61,AB61,AM61,AR61,AW61,BH61,BM61,BR61,CC61,CH61,CM61) -> 0 | M61: =SUM(S61,X61,AC61,AN61,AS61,AX61,BI61,BN61,BS61,CD61,CI61,CN61) -> 0 | N61: =SUM(T61,Y61,AD61,AO61,AT61,AY61,BJ61,BO61,BT61,CE61,CJ61,CO61) -> 0 | S61: =P61-Q61 -> 0 | X61: =U61-V61 -> 0 | AD61: =AA61-AB61 -> 0 | AH61: =AE61-AF61 -> 0 | AN61: =AK61-AL61 -> 0 | AS61: =AP61-AQ61 -> 0 | AX61: =AU61-AV61 -> 0 | BC61: =AZ61-BA61 -> 0 | BI61: =BF61-BG61 -> 0 | BN61: =BK61-BL61 -> 0 | BS61: =BP61-BQ61 -> 0 | BX61: =BU61-BV61 -> 0 | CD61: =CA61-CB61 -> 0 | CI61: =CF61-CG61 -> 0 | CN61: =CK61-CL61 -> 0 | CS61: =CP61-CQ61 -> 0
A62: 53 | E62: 中古車粗利合計 | J62: =SUM(P62,U62,Z62,AK62,AP62,AU62,BF62,BK62,BP62,CA62,CF62,CK62) -> 0 | K62: =SUM(Q62,V62,AA62,AL62,AQ62,AV62,BG62,BL62,BQ62,CB62,CG62,CL62) -> 0 | L62: =SUM(R62,W62,AB62,AM62,AR62,AW62,BH62,BM62,BR62,CC62,CH62,CM62) -> 0 | M62: =SUM(S62,X62,AC62,AN62,AS62,AX62,BI62,BN62,BS62,CD62,CI62,CN62) -> 0 | N62: =SUM(T62,Y62,AD62,AO62,AT62,AY62,BJ62,BO62,BT62,CE62,CJ62,CO62) -> 0 | S62: =P62-Q62 -> 0 | X62: =U62-V62 -> 0 | AD62: =AA62-AB62 -> 0 | AH62: =AE62-AF62 -> 0 | AN62: =AK62-AL62 -> 0 | AS62: =AP62-AQ62 -> 0 | AX62: =AU62-AV62 -> 0 | BC62: =AZ62-BA62 -> 0 | BI62: =BF62-BG62 -> 0 | BN62: =BK62-BL62 -> 0 | BS62: =BP62-BQ62 -> 0 | BX62: =BU62-BV62 -> 0 | CD62: =CA62-CB62 -> 0 | CI62: =CF62-CG62 -> 0 | CN62: =CK62-CL62 -> 0 | CS62: =CP62-CQ62 -> 0
A63: 54 | E63: 販売費 | F63: 販手・サービス・雑費 | J63: =SUM(P63,U63,Z63,AK63,AP63,AU63,BF63,BK63,BP63,CA63,CF63,CK63) -> 0 | K63: =SUM(Q63,V63,AA63,AL63,AQ63,AV63,BG63,BL63,BQ63,CB63,CG63,CL63) -> 0 | L63: =SUM(R63,W63,AB63,AM63,AR63,AW63,BH63,BM63,BR63,CC63,CH63,CM63) -> 0 | M63: =SUM(S63,X63,AC63,AN63,AS63,AX63,BI63,BN63,BS63,CD63,CI63,CN63) -> 0 | N63: =SUM(T63,Y63,AD63,AO63,AT63,AY63,BJ63,BO63,BT63,CE63,CJ63,CO63) -> 0 | S63: =P63-Q63 -> 0 | X63: =U63-V63 -> 0 | AD63: =AA63-AB63 -> 0 | AH63: =AE63-AF63 -> 0 | AN63: =AK63-AL63 -> 0 | AS63: =AP63-AQ63 -> 0 | AX63: =AU63-AV63 -> 0 | BC63: =AZ63-BA63 -> 0 | BI63: =BF63-BG63 -> 0 | BN63: =BK63-BL63 -> 0 | BS63: =BP63-BQ63 -> 0 | BX63: =BU63-BV63 -> 0 | CD63: =CA63-CB63 -> 0 | CI63: =CF63-CG63 -> 0 | CN63: =CK63-CL63 -> 0 | CS63: =CP63-CQ63 -> 0
A64: 55 | F64: 納車費・運送保管費 | J64: =SUM(P64,U64,Z64,AK64,AP64,AU64,BF64,BK64,BP64,CA64,CF64,CK64) -> 0 | K64: =SUM(Q64,V64,AA64,AL64,AQ64,AV64,BG64,BL64,BQ64,CB64,CG64,CL64) -> 0 | L64: =SUM(R64,W64,AB64,AM64,AR64,AW64,BH64,BM64,BR64,CC64,CH64,CM64) -> 0 | M64: =SUM(S64,X64,AC64,AN64,AS64,AX64,BI64,BN64,BS64,CD64,CI64,CN64) -> 0 | N64: =SUM(T64,Y64,AD64,AO64,AT64,AY64,BJ64,BO64,BT64,CE64,CJ64,CO64) -> 0 | S64: =P64-Q64 -> 0 | X64: =U64-V64 -> 0 | AD64: =AA64-AB64 -> 0 | AH64: =AE64-AF64 -> 0 | AN64: =AK64-AL64 -> 0 | AS64: =AP64-AQ64 -> 0 | AX64: =AU64-AV64 -> 0 | BC64: =AZ64-BA64 -> 0 | BI64: =BF64-BG64 -> 0 | BN64: =BK64-BL64 -> 0 | BS64: =BP64-BQ64 -> 0 | BX64: =BU64-BV64 -> 0 | CD64: =CA64-CB64 -> 0 | CI64: =CF64-CG64 -> 0 | CN64: =CK64-CL64 -> 0 | CS64: =CP64-CQ64 -> 0
A65: 56 | F65: 広告宣伝費 | J65: =SUM(P65,U65,Z65,AK65,AP65,AU65,BF65,BK65,BP65,CA65,CF65,CK65) -> 0 | K65: =SUM(Q65,V65,AA65,AL65,AQ65,AV65,BG65,BL65,BQ65,CB65,CG65,CL65) -> 0 | L65: =SUM(R65,W65,AB65,AM65,AR65,AW65,BH65,BM65,BR65,CC65,CH65,CM65) -> 0 | M65: =SUM(S65,X65,AC65,AN65,AS65,AX65,BI65,BN65,BS65,CD65,CI65,CN65) -> 0 | N65: =SUM(T65,Y65,AD65,AO65,AT65,AY65,BJ65,BO65,BT65,CE65,CJ65,CO65) -> 0 | S65: =P65-Q65 -> 0 | X65: =U65-V65 -> 0 | AD65: =AA65-AB65 -> 0 | AH65: =AE65-AF65 -> 0 | AN65: =AK65-AL65 -> 0 | AS65: =AP65-AQ65 -> 0 | AX65: =AU65-AV65 -> 0 | BC65: =AZ65-BA65 -> 0 | BI65: =BF65-BG65 -> 0 | BN65: =BK65-BL65 -> 0 | BS65: =BP65-BQ65 -> 0 | BX65: =BU65-BV65 -> 0 | CD65: =CA65-CB65 -> 0 | CI65: =CF65-CG65 -> 0 | CN65: =CK65-CL65 -> 0 | CS65: =CP65-CQ65 -> 0
A66: 57 | F66: デモカー・代車費 | J66: =SUM(P66,U66,Z66,AK66,AP66,AU66,BF66,BK66,BP66,CA66,CF66,CK66) -> 0 | K66: =SUM(Q66,V66,AA66,AL66,AQ66,AV66,BG66,BL66,BQ66,CB66,CG66,CL66) -> 0 | L66: =SUM(R66,W66,AB66,AM66,AR66,AW66,BH66,BM66,BR66,CC66,CH66,CM66) -> 0 | M66: =SUM(S66,X66,AC66,AN66,AS66,AX66,BI66,BN66,BS66,CD66,CI66,CN66) -> 0 | N66: =SUM(T66,Y66,AD66,AO66,AT66,AY66,BJ66,BO66,BT66,CE66,CJ66,CO66) -> 0 | S66: =P66-Q66 -> 0 | X66: =U66-V66 -> 0 | AD66: =AA66-AB66 -> 0 | AH66: =AE66-AF66 -> 0 | AN66: =AK66-AL66 -> 0 | AS66: =AP66-AQ66 -> 0 | AX66: =AU66-AV66 -> 0 | BC66: =AZ66-BA66 -> 0 | BI66: =BF66-BG66 -> 0 | BN66: =BK66-BL66 -> 0 | BS66: =BP66-BQ66 -> 0 | BX66: =BU66-BV66 -> 0 | CD66: =CA66-CB66 -> 0 | CI66: =CF66-CG66 -> 0 | CN66: =CK66-CL66 -> 0 | CS66: =CP66-CQ66 -> 0
A67: 58 | F67: 本部負担金 | J67: =SUM(P67,U67,Z67,AK67,AP67,AU67,BF67,BK67,BP67,CA67,CF67,CK67) -> 0 | K67: =SUM(Q67,V67,AA67,AL67,AQ67,AV67,BG67,BL67,BQ67,CB67,CG67,CL67) -> 0 | L67: =SUM(R67,W67,AB67,AM67,AR67,AW67,BH67,BM67,BR67,CC67,CH67,CM67) -> 0 | M67: =SUM(S67,X67,AC67,AN67,AS67,AX67,BI67,BN67,BS67,CD67,CI67,CN67) -> 0 | N67: =SUM(T67,Y67,AD67,AO67,AT67,AY67,BJ67,BO67,BT67,CE67,CJ67,CO67) -> 0 | S67: =P67-Q67 -> 0 | X67: =U67-V67 -> 0 | AD67: =AA67-AB67 -> 0 | AH67: =AE67-AF67 -> 0 | AN67: =AK67-AL67 -> 0 | AS67: =AP67-AQ67 -> 0 | AX67: =AU67-AV67 -> 0 | BC67: =AZ67-BA67 -> 0 | BI67: =BF67-BG67 -> 0 | BN67: =BK67-BL67 -> 0 | BS67: =BP67-BQ67 -> 0 | BX67: =BU67-BV67 -> 0 | CD67: =CA67-CB67 -> 0 | CI67: =CF67-CG67 -> 0 | CN67: =CK67-CL67 -> 0 | CS67: =CP67-CQ67 -> 0
A68: 59 | F68: 小計 | J68: =SUM(P68,U68,Z68,AK68,AP68,AU68,BF68,BK68,BP68,CA68,CF68,CK68) -> 0 | K68: =SUM(Q68,V68,AA68,AL68,AQ68,AV68,BG68,BL68,BQ68,CB68,CG68,CL68) -> 0 | L68: =SUM(R68,W68,AB68,AM68,AR68,AW68,BH68,BM68,BR68,CC68,CH68,CM68) -> 0 | M68: =SUM(S68,X68,AC68,AN68,AS68,AX68,BI68,BN68,BS68,CD68,CI68,CN68) -> 0 | N68: =SUM(T68,Y68,AD68,AO68,AT68,AY68,BJ68,BO68,BT68,CE68,CJ68,CO68) -> 0 | S68: =P68-Q68 -> 0 | X68: =U68-V68 -> 0 | AD68: =AA68-AB68 -> 0 | AH68: =AE68-AF68 -> 0 | AN68: =AK68-AL68 -> 0 | AS68: =AP68-AQ68 -> 0 | AX68: =AU68-AV68 -> 0 | BC68: =AZ68-BA68 -> 0 | BI68: =BF68-BG68 -> 0 | BN68: =BK68-BL68 -> 0 | BS68: =BP68-BQ68 -> 0 | BX68: =BU68-BV68 -> 0 | CD68: =CA68-CB68 -> 0 | CI68: =CF68-CG68 -> 0 | CN68: =CK68-CL68 -> 0 | CS68: =CP68-CQ68 -> 0
A69: 60 | E69: 中古車限界利益 | J69: =SUM(P69,U69,Z69,AK69,AP69,AU69,BF69,BK69,BP69,CA69,CF69,CK69) -> 0 | K69: =SUM(Q69,V69,AA69,AL69,AQ69,AV69,BG69,BL69,BQ69,CB69,CG69,CL69) -> 0 | L69: =SUM(R69,W69,AB69,AM69,AR69,AW69,BH69,BM69,BR69,CC69,CH69,CM69) -> 0 | M69: =SUM(S69,X69,AC69,AN69,AS69,AX69,BI69,BN69,BS69,CD69,CI69,CN69) -> 0 | N69: =SUM(T69,Y69,AD69,AO69,AT69,AY69,BJ69,BO69,BT69,CE69,CJ69,CO69) -> 0 | S69: =P69-Q69 -> 0 | X69: =U69-V69 -> 0 | AD69: =AA69-AB69 -> 0 | AH69: =AE69-AF69 -> 0 | AN69: =AK69-AL69 -> 0 | AS69: =AP69-AQ69 -> 0 | AX69: =AU69-AV69 -> 0 | BC69: =AZ69-BA69 -> 0 | BI69: =BF69-BG69 -> 0 | BN69: =BK69-BL69 -> 0 | BS69: =BP69-BQ69 -> 0 | BX69: =BU69-BV69 -> 0 | CD69: =CA69-CB69 -> 0 | CI69: =CF69-CG69 -> 0 | CN69: =CK69-CL69 -> 0 | CS69: =CP69-CQ69 -> 0
A70: 61 | D70: 整備 | E70: 売上金額 | J70: =SUM(P70,U70,Z70,AK70,AP70,AU70,BF70,BK70,BP70,CA70,CF70,CK70) -> 0 | K70: =SUM(Q70,V70,AA70,AL70,AQ70,AV70,BG70,BL70,BQ70,CB70,CG70,CL70) -> 0 | L70: =SUM(R70,W70,AB70,AM70,AR70,AW70,BH70,BM70,BR70,CC70,CH70,CM70) -> 0 | M70: =SUM(S70,X70,AC70,AN70,AS70,AX70,BI70,BN70,BS70,CD70,CI70,CN70) -> 0 | N70: =SUM(T70,Y70,AD70,AO70,AT70,AY70,BJ70,BO70,BT70,CE70,CJ70,CO70) -> 0 | S70: =P70-Q70 -> 0 | X70: =U70-V70 -> 0 | AD70: =AA70-AB70 -> 0 | AH70: =AE70-AF70 -> 0 | AN70: =AK70-AL70 -> 0 | AS70: =AP70-AQ70 -> 0 | AX70: =AU70-AV70 -> 0 | BC70: =AZ70-BA70 -> 0 | BI70: =BF70-BG70 -> 0 | BN70: =BK70-BL70 -> 0 | BS70: =BP70-BQ70 -> 0 | BX70: =BU70-BV70 -> 0 | CD70: =CA70-CB70 -> 0 | CI70: =CF70-CG70 -> 0 | CN70: =CK70-CL70 -> 0 | CS70: =CP70-CQ70 -> 0
A71: 62 | F71: ＜内車両値引＞ | J71: =SUM(P71,U71,Z71,AK71,AP71,AU71,BF71,BK71,BP71,CA71,CF71,CK71) -> 0 | K71: =SUM(Q71,V71,AA71,AL71,AQ71,AV71,BG71,BL71,BQ71,CB71,CG71,CL71) -> 0 | L71: =SUM(R71,W71,AB71,AM71,AR71,AW71,BH71,BM71,BR71,CC71,CH71,CM71) -> 0 | M71: =SUM(S71,X71,AC71,AN71,AS71,AX71,BI71,BN71,BS71,CD71,CI71,CN71) -> 0 | N71: =SUM(T71,Y71,AD71,AO71,AT71,AY71,BJ71,BO71,BT71,CE71,CJ71,CO71) -> 0 | S71: =P71-Q71 -> 0 | X71: =U71-V71 -> 0 | AD71: =AA71-AB71 -> 0 | AH71: =AE71-AF71 -> 0 | AN71: =AK71-AL71 -> 0 | AS71: =AP71-AQ71 -> 0 | AX71: =AU71-AV71 -> 0 | BC71: =AZ71-BA71 -> 0 | BI71: =BF71-BG71 -> 0 | BN71: =BK71-BL71 -> 0 | BS71: =BP71-BQ71 -> 0 | BX71: =BU71-BV71 -> 0 | CD71: =CA71-CB71 -> 0 | CI71: =CF71-CG71 -> 0 | CN71: =CK71-CL71 -> 0 | CS71: =CP71-CQ71 -> 0
A72: 63 | E72: 車検 | F72: 台数 | J72: =SUM(P72,U72,Z72,AK72,AP72,AU72,BF72,BK72,BP72,CA72,CF72,CK72) -> 0 | K72: =SUM(Q72,V72,AA72,AL72,AQ72,AV72,BG72,BL72,BQ72,CB72,CG72,CL72) -> 0 | L72: =SUM(R72,W72,AB72,AM72,AR72,AW72,BH72,BM72,BR72,CC72,CH72,CM72) -> 0 | M72: =SUM(S72,X72,AC72,AN72,AS72,AX72,BI72,BN72,BS72,CD72,CI72,CN72) -> 0 | N72: =SUM(T72,Y72,AD72,AO72,AT72,AY72,BJ72,BO72,BT72,CE72,CJ72,CO72) -> 0 | S72: =P72-Q72 -> 0 | X72: =U72-V72 -> 0 | AD72: =AA72-AB72 -> 0 | AH72: =AE72-AF72 -> 0 | AN72: =AK72-AL72 -> 0 | AS72: =AP72-AQ72 -> 0 | AX72: =AU72-AV72 -> 0 | BC72: =AZ72-BA72 -> 0 | BI72: =BF72-BG72 -> 0 | BN72: =BK72-BL72 -> 0 | BS72: =BP72-BQ72 -> 0 | BX72: =BU72-BV72 -> 0 | CD72: =CA72-CB72 -> 0 | CI72: =CF72-CG72 -> 0 | CN72: =CK72-CL72 -> 0 | CS72: =CP72-CQ72 -> 0
A73: 64 | F73: 粗利益 | J73: =SUM(P73,U73,Z73,AK73,AP73,AU73,BF73,BK73,BP73,CA73,CF73,CK73) -> 0 | K73: =SUM(Q73,V73,AA73,AL73,AQ73,AV73,BG73,BL73,BQ73,CB73,CG73,CL73) -> 0 | L73: =SUM(R73,W73,AB73,AM73,AR73,AW73,BH73,BM73,BR73,CC73,CH73,CM73) -> 0 | M73: =SUM(S73,X73,AC73,AN73,AS73,AX73,BI73,BN73,BS73,CD73,CI73,CN73) -> 0 | N73: =SUM(T73,Y73,AD73,AO73,AT73,AY73,BJ73,BO73,BT73,CE73,CJ73,CO73) -> 0 | S73: =P73-Q73 -> 0 | X73: =U73-V73 -> 0 | AD73: =AA73-AB73 -> 0 | AH73: =AE73-AF73 -> 0 | AN73: =AK73-AL73 -> 0 | AS73: =AP73-AQ73 -> 0 | AX73: =AU73-AV73 -> 0 | BC73: =AZ73-BA73 -> 0 | BI73: =BF73-BG73 -> 0 | BN73: =BK73-BL73 -> 0 | BS73: =BP73-BQ73 -> 0 | BX73: =BU73-BV73 -> 0 | CD73: =CA73-CB73 -> 0 | CI73: =CF73-CG73 -> 0 | CN73: =CK73-CL73 -> 0 | CS73: =CP73-CQ73 -> 0
A74: 65 | E74: 点検 | F74: 台数 | J74: =SUM(P74,U74,Z74,AK74,AP74,AU74,BF74,BK74,BP74,CA74,CF74,CK74) -> 0 | K74: =SUM(Q74,V74,AA74,AL74,AQ74,AV74,BG74,BL74,BQ74,CB74,CG74,CL74) -> 0 | L74: =SUM(R74,W74,AB74,AM74,AR74,AW74,BH74,BM74,BR74,CC74,CH74,CM74) -> 0 | M74: =SUM(S74,X74,AC74,AN74,AS74,AX74,BI74,BN74,BS74,CD74,CI74,CN74) -> 0 | N74: =SUM(T74,Y74,AD74,AO74,AT74,AY74,BJ74,BO74,BT74,CE74,CJ74,CO74) -> 0 | S74: =P74-Q74 -> 0 | X74: =U74-V74 -> 0 | AD74: =AA74-AB74 -> 0 | AH74: =AE74-AF74 -> 0 | AN74: =AK74-AL74 -> 0 | AS74: =AP74-AQ74 -> 0 | AX74: =AU74-AV74 -> 0 | BC74: =AZ74-BA74 -> 0 | BI74: =BF74-BG74 -> 0 | BN74: =BK74-BL74 -> 0 | BS74: =BP74-BQ74 -> 0 | BX74: =BU74-BV74 -> 0 | CD74: =CA74-CB74 -> 0 | CI74: =CF74-CG74 -> 0 | CN74: =CK74-CL74 -> 0 | CS74: =CP74-CQ74 -> 0
A75: 66 | F75: 粗利益 | J75: =SUM(P75,U75,Z75,AK75,AP75,AU75,BF75,BK75,BP75,CA75,CF75,CK75) -> 0 | K75: =SUM(Q75,V75,AA75,AL75,AQ75,AV75,BG75,BL75,BQ75,CB75,CG75,CL75) -> 0 | L75: =SUM(R75,W75,AB75,AM75,AR75,AW75,BH75,BM75,BR75,CC75,CH75,CM75) -> 0 | M75: =SUM(S75,X75,AC75,AN75,AS75,AX75,BI75,BN75,BS75,CD75,CI75,CN75) -> 0 | N75: =SUM(T75,Y75,AD75,AO75,AT75,AY75,BJ75,BO75,BT75,CE75,CJ75,CO75) -> 0 | S75: =P75-Q75 -> 0 | X75: =U75-V75 -> 0 | AD75: =AA75-AB75 -> 0 | AH75: =AE75-AF75 -> 0 | AN75: =AK75-AL75 -> 0 | AS75: =AP75-AQ75 -> 0 | AX75: =AU75-AV75 -> 0 | BC75: =AZ75-BA75 -> 0 | BI75: =BF75-BG75 -> 0 | BN75: =BK75-BL75 -> 0 | BS75: =BP75-BQ75 -> 0 | BX75: =BU75-BV75 -> 0 | CD75: =CA75-CB75 -> 0 | CI75: =CF75-CG75 -> 0 | CN75: =CK75-CL75 -> 0 | CS75: =CP75-CQ75 -> 0
A76: 67 | E76: 一般 | F76: 台数 | J76: =SUM(P76,U76,Z76,AK76,AP76,AU76,BF76,BK76,BP76,CA76,CF76,CK76) -> 0 | K76: =SUM(Q76,V76,AA76,AL76,AQ76,AV76,BG76,BL76,BQ76,CB76,CG76,CL76) -> 0 | L76: =SUM(R76,W76,AB76,AM76,AR76,AW76,BH76,BM76,BR76,CC76,CH76,CM76) -> 0 | M76: =SUM(S76,X76,AC76,AN76,AS76,AX76,BI76,BN76,BS76,CD76,CI76,CN76) -> 0 | N76: =SUM(T76,Y76,AD76,AO76,AT76,AY76,BJ76,BO76,BT76,CE76,CJ76,CO76) -> 0 | S76: =P76-Q76 -> 0 | X76: =U76-V76 -> 0 | AD76: =AA76-AB76 -> 0 | AH76: =AE76-AF76 -> 0 | AN76: =AK76-AL76 -> 0 | AS76: =AP76-AQ76 -> 0 | AX76: =AU76-AV76 -> 0 | BC76: =AZ76-BA76 -> 0 | BI76: =BF76-BG76 -> 0 | BN76: =BK76-BL76 -> 0 | BS76: =BP76-BQ76 -> 0 | BX76: =BU76-BV76 -> 0 | CD76: =CA76-CB76 -> 0 | CI76: =CF76-CG76 -> 0 | CN76: =CK76-CL76 -> 0 | CS76: =CP76-CQ76 -> 0
A77: 68 | F77: 粗利益 | J77: =SUM(P77,U77,Z77,AK77,AP77,AU77,BF77,BK77,BP77,CA77,CF77,CK77) -> 0 | K77: =SUM(Q77,V77,AA77,AL77,AQ77,AV77,BG77,BL77,BQ77,CB77,CG77,CL77) -> 0 | L77: =SUM(R77,W77,AB77,AM77,AR77,AW77,BH77,BM77,BR77,CC77,CH77,CM77) -> 0 | M77: =SUM(S77,X77,AC77,AN77,AS77,AX77,BI77,BN77,BS77,CD77,CI77,CN77) -> 0 | N77: =SUM(T77,Y77,AD77,AO77,AT77,AY77,BJ77,BO77,BT77,CE77,CJ77,CO77) -> 0 | S77: =P77-Q77 -> 0 | X77: =U77-V77 -> 0 | AD77: =AA77-AB77 -> 0 | AH77: =AE77-AF77 -> 0 | AN77: =AK77-AL77 -> 0 | AS77: =AP77-AQ77 -> 0 | AX77: =AU77-AV77 -> 0 | BC77: =AZ77-BA77 -> 0 | BI77: =BF77-BG77 -> 0 | BN77: =BK77-BL77 -> 0 | BS77: =BP77-BQ77 -> 0 | BX77: =BU77-BV77 -> 0 | CD77: =CA77-CB77 -> 0 | CI77: =CF77-CG77 -> 0 | CN77: =CK77-CL77 -> 0 | CS77: =CP77-CQ77 -> 0
A78: 69 | E78: 外装 | F78: 台数 | J78: =SUM(P78,U78,Z78,AK78,AP78,AU78,BF78,BK78,BP78,CA78,CF78,CK78) -> 0 | K78: =SUM(Q78,V78,AA78,AL78,AQ78,AV78,BG78,BL78,BQ78,CB78,CG78,CL78) -> 0 | L78: =SUM(R78,W78,AB78,AM78,AR78,AW78,BH78,BM78,BR78,CC78,CH78,CM78) -> 0 | M78: =SUM(S78,X78,AC78,AN78,AS78,AX78,BI78,BN78,BS78,CD78,CI78,CN78) -> 0 | N78: =SUM(T78,Y78,AD78,AO78,AT78,AY78,BJ78,BO78,BT78,CE78,CJ78,CO78) -> 0 | S78: =P78-Q78 -> 0 | X78: =U78-V78 -> 0 | AD78: =AA78-AB78 -> 0 | AH78: =AE78-AF78 -> 0 | AN78: =AK78-AL78 -> 0 | AS78: =AP78-AQ78 -> 0 | AX78: =AU78-AV78 -> 0 | BC78: =AZ78-BA78 -> 0 | BI78: =BF78-BG78 -> 0 | BN78: =BK78-BL78 -> 0 | BS78: =BP78-BQ78 -> 0 | BX78: =BU78-BV78 -> 0 | CD78: =CA78-CB78 -> 0 | CI78: =CF78-CG78 -> 0 | CN78: =CK78-CL78 -> 0 | CS78: =CP78-CQ78 -> 0
A79: 70 | F79: 粗利益 | J79: =SUM(P79,U79,Z79,AK79,AP79,AU79,BF79,BK79,BP79,CA79,CF79,CK79) -> 0 | K79: =SUM(Q79,V79,AA79,AL79,AQ79,AV79,BG79,BL79,BQ79,CB79,CG79,CL79) -> 0 | L79: =SUM(R79,W79,AB79,AM79,AR79,AW79,BH79,BM79,BR79,CC79,CH79,CM79) -> 0 | M79: =SUM(S79,X79,AC79,AN79,AS79,AX79,BI79,BN79,BS79,CD79,CI79,CN79) -> 0 | N79: =SUM(T79,Y79,AD79,AO79,AT79,AY79,BJ79,BO79,BT79,CE79,CJ79,CO79) -> 0 | S79: =P79-Q79 -> 0 | X79: =U79-V79 -> 0 | AD79: =AA79-AB79 -> 0 | AH79: =AE79-AF79 -> 0 | AN79: =AK79-AL79 -> 0 | AS79: =AP79-AQ79 -> 0 | AX79: =AU79-AV79 -> 0 | BC79: =AZ79-BA79 -> 0 | BI79: =BF79-BG79 -> 0 | BN79: =BK79-BL79 -> 0 | BS79: =BP79-BQ79 -> 0 | BX79: =BU79-BV79 -> 0 | CD79: =CA79-CB79 -> 0 | CI79: =CF79-CG79 -> 0 | CN79: =CK79-CL79 -> 0 | CS79: =CP79-CQ79 -> 0
A80: 71 | E80: 部用品粗利 | J80: =SUM(P80,U80,Z80,AK80,AP80,AU80,BF80,BK80,BP80,CA80,CF80,CK80) -> 0 | K80: =SUM(Q80,V80,AA80,AL80,AQ80,AV80,BG80,BL80,BQ80,CB80,CG80,CL80) -> 0 | L80: =SUM(R80,W80,AB80,AM80,AR80,AW80,BH80,BM80,BR80,CC80,CH80,CM80) -> 0 | M80: =SUM(S80,X80,AC80,AN80,AS80,AX80,BI80,BN80,BS80,CD80,CI80,CN80) -> 0 | N80: =SUM(T80,Y80,AD80,AO80,AT80,AY80,BJ80,BO80,BT80,CE80,CJ80,CO80) -> 0 | S80: =P80-Q80 -> 0 | X80: =U80-V80 -> 0 | AD80: =AA80-AB80 -> 0 | AH80: =AE80-AF80 -> 0 | AN80: =AK80-AL80 -> 0 | AS80: =AP80-AQ80 -> 0 | AX80: =AU80-AV80 -> 0 | BC80: =AZ80-BA80 -> 0 | BI80: =BF80-BG80 -> 0 | BN80: =BK80-BL80 -> 0 | BS80: =BP80-BQ80 -> 0 | BX80: =BU80-BV80 -> 0 | CD80: =CA80-CB80 -> 0 | CI80: =CF80-CG80 -> 0 | CN80: =CK80-CL80 -> 0 | CS80: =CP80-CQ80 -> 0
A81: 72 | E81: 有償利益合計 | J81: =SUM(P81,U81,Z81,AK81,AP81,AU81,BF81,BK81,BP81,CA81,CF81,CK81) -> 0 | K81: =SUM(Q81,V81,AA81,AL81,AQ81,AV81,BG81,BL81,BQ81,CB81,CG81,CL81) -> 0 | L81: =SUM(R81,W81,AB81,AM81,AR81,AW81,BH81,BM81,BR81,CC81,CH81,CM81) -> 0 | M81: =SUM(S81,X81,AC81,AN81,AS81,AX81,BI81,BN81,BS81,CD81,CI81,CN81) -> 0 | N81: =SUM(T81,Y81,AD81,AO81,AT81,AY81,BJ81,BO81,BT81,CE81,CJ81,CO81) -> 0 | S81: =P81-Q81 -> 0 | X81: =U81-V81 -> 0 | AD81: =AA81-AB81 -> 0 | AH81: =AE81-AF81 -> 0 | AN81: =AK81-AL81 -> 0 | AS81: =AP81-AQ81 -> 0 | AX81: =AU81-AV81 -> 0 | BC81: =AZ81-BA81 -> 0 | BI81: =BF81-BG81 -> 0 | BN81: =BK81-BL81 -> 0 | BS81: =BP81-BQ81 -> 0 | BX81: =BU81-BV81 -> 0 | CD81: =CA81-CB81 -> 0 | CI81: =CF81-CG81 -> 0 | CN81: =CK81-CL81 -> 0 | CS81: =CP81-CQ81 -> 0
A82: 73 | E82: 材料消耗品費1+2 | J82: =SUM(P82,U82,Z82,AK82,AP82,AU82,BF82,BK82,BP82,CA82,CF82,CK82) -> 0 | K82: =SUM(Q82,V82,AA82,AL82,AQ82,AV82,BG82,BL82,BQ82,CB82,CG82,CL82) -> 0 | L82: =SUM(R82,W82,AB82,AM82,AR82,AW82,BH82,BM82,BR82,CC82,CH82,CM82) -> 0 | M82: =SUM(S82,X82,AC82,AN82,AS82,AX82,BI82,BN82,BS82,CD82,CI82,CN82) -> 0 | N82: =SUM(T82,Y82,AD82,AO82,AT82,AY82,BJ82,BO82,BT82,CE82,CJ82,CO82) -> 0 | S82: =P82-Q82 -> 0 | X82: =U82-V82 -> 0 | AD82: =AA82-AB82 -> 0 | AH82: =AE82-AF82 -> 0 | AN82: =AK82-AL82 -> 0 | AS82: =AP82-AQ82 -> 0 | AX82: =AU82-AV82 -> 0 | BC82: =AZ82-BA82 -> 0 | BI82: =BF82-BG82 -> 0 | BN82: =BK82-BL82 -> 0 | BS82: =BP82-BQ82 -> 0 | BX82: =BU82-BV82 -> 0 | CD82: =CA82-CB82 -> 0 | CI82: =CF82-CG82 -> 0 | CN82: =CK82-CL82 -> 0 | CS82: =CP82-CQ82 -> 0
A83: 74 | E83: 回送要員・代車費用 | J83: =SUM(P83,U83,Z83,AK83,AP83,AU83,BF83,BK83,BP83,CA83,CF83,CK83) -> 0 | K83: =SUM(Q83,V83,AA83,AL83,AQ83,AV83,BG83,BL83,BQ83,CB83,CG83,CL83) -> 0 | L83: =SUM(R83,W83,AB83,AM83,AR83,AW83,BH83,BM83,BR83,CC83,CH83,CM83) -> 0 | M83: =SUM(S83,X83,AC83,AN83,AS83,AX83,BI83,BN83,BS83,CD83,CI83,CN83) -> 0 | N83: =SUM(T83,Y83,AD83,AO83,AT83,AY83,BJ83,BO83,BT83,CE83,CJ83,CO83) -> 0 | S83: =P83-Q83 -> 0 | X83: =U83-V83 -> 0 | AD83: =AA83-AB83 -> 0 | AH83: =AE83-AF83 -> 0 | AN83: =AK83-AL83 -> 0 | AS83: =AP83-AQ83 -> 0 | AX83: =AU83-AV83 -> 0 | BC83: =AZ83-BA83 -> 0 | BI83: =BF83-BG83 -> 0 | BN83: =BK83-BL83 -> 0 | BS83: =BP83-BQ83 -> 0 | BX83: =BU83-BV83 -> 0 | CD83: =CA83-CB83 -> 0 | CI83: =CF83-CG83 -> 0 | CN83: =CK83-CL83 -> 0 | CS83: =CP83-CQ83 -> 0
A84: 75 | E84: 有償粗利合計 | J84: =SUM(P84,U84,Z84,AK84,AP84,AU84,BF84,BK84,BP84,CA84,CF84,CK84) -> 0 | K84: =SUM(Q84,V84,AA84,AL84,AQ84,AV84,BG84,BL84,BQ84,CB84,CG84,CL84) -> 0 | L84: =SUM(R84,W84,AB84,AM84,AR84,AW84,BH84,BM84,BR84,CC84,CH84,CM84) -> 0 | M84: =SUM(S84,X84,AC84,AN84,AS84,AX84,BI84,BN84,BS84,CD84,CI84,CN84) -> 0 | N84: =SUM(T84,Y84,AD84,AO84,AT84,AY84,BJ84,BO84,BT84,CE84,CJ84,CO84) -> 0 | S84: =P84-Q84 -> 0 | X84: =U84-V84 -> 0 | AD84: =AA84-AB84 -> 0 | AH84: =AE84-AF84 -> 0 | AN84: =AK84-AL84 -> 0 | AS84: =AP84-AQ84 -> 0 | AX84: =AU84-AV84 -> 0 | BC84: =AZ84-BA84 -> 0 | BI84: =BF84-BG84 -> 0 | BN84: =BK84-BL84 -> 0 | BS84: =BP84-BQ84 -> 0 | BX84: =BU84-BV84 -> 0 | CD84: =CA84-CB84 -> 0 | CI84: =CF84-CG84 -> 0 | CN84: =CK84-CL84 -> 0 | CS84: =CP84-CQ84 -> 0
A85: 76 | E85: 無償 | J85: =SUM(P85,U85,Z85,AK85,AP85,AU85,BF85,BK85,BP85,CA85,CF85,CK85) -> 0 | K85: =SUM(Q85,V85,AA85,AL85,AQ85,AV85,BG85,BL85,BQ85,CB85,CG85,CL85) -> 0 | L85: =SUM(R85,W85,AB85,AM85,AR85,AW85,BH85,BM85,BR85,CC85,CH85,CM85) -> 0 | M85: =SUM(S85,X85,AC85,AN85,AS85,AX85,BI85,BN85,BS85,CD85,CI85,CN85) -> 0 | N85: =SUM(T85,Y85,AD85,AO85,AT85,AY85,BJ85,BO85,BT85,CE85,CJ85,CO85) -> 0 | S85: =P85-Q85 -> 0 | X85: =U85-V85 -> 0 | AD85: =AA85-AB85 -> 0 | AH85: =AE85-AF85 -> 0 | AN85: =AK85-AL85 -> 0 | AS85: =AP85-AQ85 -> 0 | AX85: =AU85-AV85 -> 0 | BC85: =AZ85-BA85 -> 0 | BI85: =BF85-BG85 -> 0 | BN85: =BK85-BL85 -> 0 | BS85: =BP85-BQ85 -> 0 | BX85: =BU85-BV85 -> 0 | CD85: =CA85-CB85 -> 0 | CI85: =CF85-CG85 -> 0 | CN85: =CK85-CL85 -> 0 | CS85: =CP85-CQ85 -> 0
A86: 77 | E86: 整備収手 | J86: =SUM(P86,U86,Z86,AK86,AP86,AU86,BF86,BK86,BP86,CA86,CF86,CK86) -> 0 | K86: =SUM(Q86,V86,AA86,AL86,AQ86,AV86,BG86,BL86,BQ86,CB86,CG86,CL86) -> 0 | L86: =SUM(R86,W86,AB86,AM86,AR86,AW86,BH86,BM86,BR86,CC86,CH86,CM86) -> 0 | M86: =SUM(S86,X86,AC86,AN86,AS86,AX86,BI86,BN86,BS86,CD86,CI86,CN86) -> 0 | N86: =SUM(T86,Y86,AD86,AO86,AT86,AY86,BJ86,BO86,BT86,CE86,CJ86,CO86) -> 0 | S86: =P86-Q86 -> 0 | X86: =U86-V86 -> 0 | AD86: =AA86-AB86 -> 0 | AH86: =AE86-AF86 -> 0 | AN86: =AK86-AL86 -> 0 | AS86: =AP86-AQ86 -> 0 | AX86: =AU86-AV86 -> 0 | BC86: =AZ86-BA86 -> 0 | BI86: =BF86-BG86 -> 0 | BN86: =BK86-BL86 -> 0 | BS86: =BP86-BQ86 -> 0 | BX86: =BU86-BV86 -> 0 | CD86: =CA86-CB86 -> 0 | CI86: =CF86-CG86 -> 0 | CN86: =CK86-CL86 -> 0 | CS86: =CP86-CQ86 -> 0
A87: 78 | E87: サービス員給与 | J87: =SUM(P87,U87,Z87,AK87,AP87,AU87,BF87,BK87,BP87,CA87,CF87,CK87) -> 0 | K87: =SUM(Q87,V87,AA87,AL87,AQ87,AV87,BG87,BL87,BQ87,CB87,CG87,CL87) -> 0 | L87: =SUM(R87,W87,AB87,AM87,AR87,AW87,BH87,BM87,BR87,CC87,CH87,CM87) -> 0 | M87: =SUM(S87,X87,AC87,AN87,AS87,AX87,BI87,BN87,BS87,CD87,CI87,CN87) -> 0 | N87: =SUM(T87,Y87,AD87,AO87,AT87,AY87,BJ87,BO87,BT87,CE87,CJ87,CO87) -> 0 | S87: =P87-Q87 -> 0 | X87: =U87-V87 -> 0 | AD87: =AA87-AB87 -> 0 | AH87: =AE87-AF87 -> 0 | AN87: =AK87-AL87 -> 0 | AS87: =AP87-AQ87 -> 0 | AX87: =AU87-AV87 -> 0 | BC87: =AZ87-BA87 -> 0 | BI87: =BF87-BG87 -> 0 | BN87: =BK87-BL87 -> 0 | BS87: =BP87-BQ87 -> 0 | BX87: =BU87-BV87 -> 0 | CD87: =CA87-CB87 -> 0 | CI87: =CF87-CG87 -> 0 | CN87: =CK87-CL87 -> 0 | CS87: =CP87-CQ87 -> 0
A88: 79 | E88: 整備総粗利 | J88: =SUM(P88,U88,Z88,AK88,AP88,AU88,BF88,BK88,BP88,CA88,CF88,CK88) -> 0 | K88: =SUM(Q88,V88,AA88,AL88,AQ88,AV88,BG88,BL88,BQ88,CB88,CG88,CL88) -> 0 | L88: =SUM(R88,W88,AB88,AM88,AR88,AW88,BH88,BM88,BR88,CC88,CH88,CM88) -> 0 | M88: =SUM(S88,X88,AC88,AN88,AS88,AX88,BI88,BN88,BS88,CD88,CI88,CN88) -> 0 | N88: =SUM(T88,Y88,AD88,AO88,AT88,AY88,BJ88,BO88,BT88,CE88,CJ88,CO88) -> 0 | S88: =P88-Q88 -> 0 | X88: =U88-V88 -> 0 | AD88: =AA88-AB88 -> 0 | AH88: =AE88-AF88 -> 0 | AN88: =AK88-AL88 -> 0 | AS88: =AP88-AQ88 -> 0 | AX88: =AU88-AV88 -> 0 | BC88: =AZ88-BA88 -> 0 | BI88: =BF88-BG88 -> 0 | BN88: =BK88-BL88 -> 0 | BS88: =BP88-BQ88 -> 0 | BX88: =BU88-BV88 -> 0 | CD88: =CA88-CB88 -> 0 | CI88: =CF88-CG88 -> 0 | CN88: =CK88-CL88 -> 0 | CS88: =CP88-CQ88 -> 0
A89: 80 | E89: 販売費 | F89: 販手・サービス・雑費 | J89: =SUM(P89,U89,Z89,AK89,AP89,AU89,BF89,BK89,BP89,CA89,CF89,CK89) -> 0 | K89: =SUM(Q89,V89,AA89,AL89,AQ89,AV89,BG89,BL89,BQ89,CB89,CG89,CL89) -> 0 | L89: =SUM(R89,W89,AB89,AM89,AR89,AW89,BH89,BM89,BR89,CC89,CH89,CM89) -> 0 | M89: =SUM(S89,X89,AC89,AN89,AS89,AX89,BI89,BN89,BS89,CD89,CI89,CN89) -> 0 | N89: =SUM(T89,Y89,AD89,AO89,AT89,AY89,BJ89,BO89,BT89,CE89,CJ89,CO89) -> 0 | S89: =P89-Q89 -> 0 | X89: =U89-V89 -> 0 | AD89: =AA89-AB89 -> 0 | AH89: =AE89-AF89 -> 0 | AN89: =AK89-AL89 -> 0 | AS89: =AP89-AQ89 -> 0 | AX89: =AU89-AV89 -> 0 | BC89: =AZ89-BA89 -> 0 | BI89: =BF89-BG89 -> 0 | BN89: =BK89-BL89 -> 0 | BS89: =BP89-BQ89 -> 0 | BX89: =BU89-BV89 -> 0 | CD89: =CA89-CB89 -> 0 | CI89: =CF89-CG89 -> 0 | CN89: =CK89-CL89 -> 0 | CS89: =CP89-CQ89 -> 0
A90: 81 | F90: 納車費・運送保管費 | J90: =SUM(P90,U90,Z90,AK90,AP90,AU90,BF90,BK90,BP90,CA90,CF90,CK90) -> 0 | K90: =SUM(Q90,V90,AA90,AL90,AQ90,AV90,BG90,BL90,BQ90,CB90,CG90,CL90) -> 0 | L90: =SUM(R90,W90,AB90,AM90,AR90,AW90,BH90,BM90,BR90,CC90,CH90,CM90) -> 0 | M90: =SUM(S90,X90,AC90,AN90,AS90,AX90,BI90,BN90,BS90,CD90,CI90,CN90) -> 0 | N90: =SUM(T90,Y90,AD90,AO90,AT90,AY90,BJ90,BO90,BT90,CE90,CJ90,CO90) -> 0 | S90: =P90-Q90 -> 0 | X90: =U90-V90 -> 0 | AD90: =AA90-AB90 -> 0 | AH90: =AE90-AF90 -> 0 | AN90: =AK90-AL90 -> 0 | AS90: =AP90-AQ90 -> 0 | AX90: =AU90-AV90 -> 0 | BC90: =AZ90-BA90 -> 0 | BI90: =BF90-BG90 -> 0 | BN90: =BK90-BL90 -> 0 | BS90: =BP90-BQ90 -> 0 | BX90: =BU90-BV90 -> 0 | CD90: =CA90-CB90 -> 0 | CI90: =CF90-CG90 -> 0 | CN90: =CK90-CL90 -> 0 | CS90: =CP90-CQ90 -> 0
A91: 82 | F91: 広告宣伝費 | J91: =SUM(P91,U91,Z91,AK91,AP91,AU91,BF91,BK91,BP91,CA91,CF91,CK91) -> 0 | K91: =SUM(Q91,V91,AA91,AL91,AQ91,AV91,BG91,BL91,BQ91,CB91,CG91,CL91) -> 0 | L91: =SUM(R91,W91,AB91,AM91,AR91,AW91,BH91,BM91,BR91,CC91,CH91,CM91) -> 0 | M91: =SUM(S91,X91,AC91,AN91,AS91,AX91,BI91,BN91,BS91,CD91,CI91,CN91) -> 0 | N91: =SUM(T91,Y91,AD91,AO91,AT91,AY91,BJ91,BO91,BT91,CE91,CJ91,CO91) -> 0 | S91: =P91-Q91 -> 0 | X91: =U91-V91 -> 0 | AD91: =AA91-AB91 -> 0 | AH91: =AE91-AF91 -> 0 | AN91: =AK91-AL91 -> 0 | AS91: =AP91-AQ91 -> 0 | AX91: =AU91-AV91 -> 0 | BC91: =AZ91-BA91 -> 0 | BI91: =BF91-BG91 -> 0 | BN91: =BK91-BL91 -> 0 | BS91: =BP91-BQ91 -> 0 | BX91: =BU91-BV91 -> 0 | CD91: =CA91-CB91 -> 0 | CI91: =CF91-CG91 -> 0 | CN91: =CK91-CL91 -> 0 | CS91: =CP91-CQ91 -> 0
A92: 83 | F92: デモカー・代車費 | J92: =SUM(P92,U92,Z92,AK92,AP92,AU92,BF92,BK92,BP92,CA92,CF92,CK92) -> 0 | K92: =SUM(Q92,V92,AA92,AL92,AQ92,AV92,BG92,BL92,BQ92,CB92,CG92,CL92) -> 0 | L92: =SUM(R92,W92,AB92,AM92,AR92,AW92,BH92,BM92,BR92,CC92,CH92,CM92) -> 0 | M92: =SUM(S92,X92,AC92,AN92,AS92,AX92,BI92,BN92,BS92,CD92,CI92,CN92) -> 0 | N92: =SUM(T92,Y92,AD92,AO92,AT92,AY92,BJ92,BO92,BT92,CE92,CJ92,CO92) -> 0 | S92: =P92-Q92 -> 0 | X92: =U92-V92 -> 0 | AD92: =AA92-AB92 -> 0 | AH92: =AE92-AF92 -> 0 | AN92: =AK92-AL92 -> 0 | AS92: =AP92-AQ92 -> 0 | AX92: =AU92-AV92 -> 0 | BC92: =AZ92-BA92 -> 0 | BI92: =BF92-BG92 -> 0 | BN92: =BK92-BL92 -> 0 | BS92: =BP92-BQ92 -> 0 | BX92: =BU92-BV92 -> 0 | CD92: =CA92-CB92 -> 0 | CI92: =CF92-CG92 -> 0 | CN92: =CK92-CL92 -> 0 | CS92: =CP92-CQ92 -> 0
A93: 84 | F93: 本部負担金 | J93: =SUM(P93,U93,Z93,AK93,AP93,AU93,BF93,BK93,BP93,CA93,CF93,CK93) -> 0 | K93: =SUM(Q93,V93,AA93,AL93,AQ93,AV93,BG93,BL93,BQ93,CB93,CG93,CL93) -> 0 | L93: =SUM(R93,W93,AB93,AM93,AR93,AW93,BH93,BM93,BR93,CC93,CH93,CM93) -> 0 | M93: =SUM(S93,X93,AC93,AN93,AS93,AX93,BI93,BN93,BS93,CD93,CI93,CN93) -> 0 | N93: =SUM(T93,Y93,AD93,AO93,AT93,AY93,BJ93,BO93,BT93,CE93,CJ93,CO93) -> 0 | S93: =P93-Q93 -> 0 | X93: =U93-V93 -> 0 | AD93: =AA93-AB93 -> 0 | AH93: =AE93-AF93 -> 0 | AN93: =AK93-AL93 -> 0 | AS93: =AP93-AQ93 -> 0 | AX93: =AU93-AV93 -> 0 | BC93: =AZ93-BA93 -> 0 | BI93: =BF93-BG93 -> 0 | BN93: =BK93-BL93 -> 0 | BS93: =BP93-BQ93 -> 0 | BX93: =BU93-BV93 -> 0 | CD93: =CA93-CB93 -> 0 | CI93: =CF93-CG93 -> 0 | CN93: =CK93-CL93 -> 0 | CS93: =CP93-CQ93 -> 0
A94: 85 | F94: 小計 | J94: =SUM(P94,U94,Z94,AK94,AP94,AU94,BF94,BK94,BP94,CA94,CF94,CK94) -> 0 | K94: =SUM(Q94,V94,AA94,AL94,AQ94,AV94,BG94,BL94,BQ94,CB94,CG94,CL94) -> 0 | L94: =SUM(R94,W94,AB94,AM94,AR94,AW94,BH94,BM94,BR94,CC94,CH94,CM94) -> 0 | M94: =SUM(S94,X94,AC94,AN94,AS94,AX94,BI94,BN94,BS94,CD94,CI94,CN94) -> 0 | N94: =SUM(T94,Y94,AD94,AO94,AT94,AY94,BJ94,BO94,BT94,CE94,CJ94,CO94) -> 0 | S94: =P94-Q94 -> 0 | X94: =U94-V94 -> 0 | AD94: =AA94-AB94 -> 0 | AH94: =AE94-AF94 -> 0 | AN94: =AK94-AL94 -> 0 | AS94: =AP94-AQ94 -> 0 | AX94: =AU94-AV94 -> 0 | BC94: =AZ94-BA94 -> 0 | BI94: =BF94-BG94 -> 0 | BN94: =BK94-BL94 -> 0 | BS94: =BP94-BQ94 -> 0 | BX94: =BU94-BV94 -> 0 | CD94: =CA94-CB94 -> 0 | CI94: =CF94-CG94 -> 0 | CN94: =CK94-CL94 -> 0 | CS94: =CP94-CQ94 -> 0
A95: 86 | E95: 整備限界利益 | J95: =SUM(P95,U95,Z95,AK95,AP95,AU95,BF95,BK95,BP95,CA95,CF95,CK95) -> 0 | K95: =SUM(Q95,V95,AA95,AL95,AQ95,AV95,BG95,BL95,BQ95,CB95,CG95,CL95) -> 0 | L95: =SUM(R95,W95,AB95,AM95,AR95,AW95,BH95,BM95,BR95,CC95,CH95,CM95) -> 0 | M95: =SUM(S95,X95,AC95,AN95,AS95,AX95,BI95,BN95,BS95,CD95,CI95,CN95) -> 0 | N95: =SUM(T95,Y95,AD95,AO95,AT95,AY95,BJ95,BO95,BT95,CE95,CJ95,CO95) -> 0 | S95: =P95-Q95 -> 0 | X95: =U95-V95 -> 0 | AD95: =AA95-AB95 -> 0 | AH95: =AE95-AF95 -> 0 | AN95: =AK95-AL95 -> 0 | AS95: =AP95-AQ95 -> 0 | AX95: =AU95-AV95 -> 0 | BC95: =AZ95-BA95 -> 0 | BI95: =BF95-BG95 -> 0 | BN95: =BK95-BL95 -> 0 | BS95: =BP95-BQ95 -> 0 | BX95: =BU95-BV95 -> 0 | CD95: =CA95-CB95 -> 0 | CI95: =CF95-CG95 -> 0 | CN95: =CK95-CL95 -> 0 | CS95: =CP95-CQ95 -> 0
A96: 87 | D96: 保険収入手数料 | J96: =SUM(P96,U96,Z96,AK96,AP96,AU96,BF96,BK96,BP96,CA96,CF96,CK96) -> 0 | K96: =SUM(Q96,V96,AA96,AL96,AQ96,AV96,BG96,BL96,BQ96,CB96,CG96,CL96) -> 0 | L96: =SUM(R96,W96,AB96,AM96,AR96,AW96,BH96,BM96,BR96,CC96,CH96,CM96) -> 0 | M96: =SUM(S96,X96,AC96,AN96,AS96,AX96,BI96,BN96,BS96,CD96,CI96,CN96) -> 0 | N96: =SUM(T96,Y96,AD96,AO96,AT96,AY96,BJ96,BO96,BT96,CE96,CJ96,CO96) -> 0 | S96: =P96-Q96 -> 0 | X96: =U96-V96 -> 0 | AD96: =AA96-AB96 -> 0 | AH96: =AE96-AF96 -> 0 | AN96: =AK96-AL96 -> 0 | AS96: =AP96-AQ96 -> 0 | AX96: =AU96-AV96 -> 0 | BC96: =AZ96-BA96 -> 0 | BI96: =BF96-BG96 -> 0 | BN96: =BK96-BL96 -> 0 | BS96: =BP96-BQ96 -> 0 | BX96: =BU96-BV96 -> 0 | CD96: =CA96-CB96 -> 0 | CI96: =CF96-CG96 -> 0 | CN96: =CK96-CL96 -> 0 | CS96: =CP96-CQ96 -> 0
A97: 88 | D97: その他収手及び商品利益 | J97: =SUM(P97,U97,Z97,AK97,AP97,AU97,BF97,BK97,BP97,CA97,CF97,CK97) -> 0 | K97: =SUM(Q97,V97,AA97,AL97,AQ97,AV97,BG97,BL97,BQ97,CB97,CG97,CL97) -> 0 | L97: =SUM(R97,W97,AB97,AM97,AR97,AW97,BH97,BM97,BR97,CC97,CH97,CM97) -> 0 | M97: =SUM(S97,X97,AC97,AN97,AS97,AX97,BI97,BN97,BS97,CD97,CI97,CN97) -> 0 | N97: =SUM(T97,Y97,AD97,AO97,AT97,AY97,BJ97,BO97,BT97,CE97,CJ97,CO97) -> 0 | S97: =P97-Q97 -> 0 | X97: =U97-V97 -> 0 | AD97: =AA97-AB97 -> 0 | AH97: =AE97-AF97 -> 0 | AN97: =AK97-AL97 -> 0 | AS97: =AP97-AQ97 -> 0 | AX97: =AU97-AV97 -> 0 | BC97: =AZ97-BA97 -> 0 | BI97: =BF97-BG97 -> 0 | BN97: =BK97-BL97 -> 0 | BS97: =BP97-BQ97 -> 0 | BX97: =BU97-BV97 -> 0 | CD97: =CA97-CB97 -> 0 | CI97: =CF97-CG97 -> 0 | CN97: =CK97-CL97 -> 0 | CS97: =CP97-CQ97 -> 0
A98: 89 | D98: 総利益合計 | J98: =SUM(P98,U98,Z98,AK98,AP98,AU98,BF98,BK98,BP98,CA98,CF98,CK98) -> 0 | K98: =SUM(Q98,V98,AA98,AL98,AQ98,AV98,BG98,BL98,BQ98,CB98,CG98,CL98) -> 0 | L98: =SUM(R98,W98,AB98,AM98,AR98,AW98,BH98,BM98,BR98,CC98,CH98,CM98) -> 0 | M98: =SUM(S98,X98,AC98,AN98,AS98,AX98,BI98,BN98,BS98,CD98,CI98,CN98) -> 0 | N98: =SUM(T98,Y98,AD98,AO98,AT98,AY98,BJ98,BO98,BT98,CE98,CJ98,CO98) -> 0 | S98: =P98-Q98 -> 0 | X98: =U98-V98 -> 0 | AD98: =AA98-AB98 -> 0 | AH98: =AE98-AF98 -> 0 | AN98: =AK98-AL98 -> 0 | AS98: =AP98-AQ98 -> 0 | AX98: =AU98-AV98 -> 0 | BC98: =AZ98-BA98 -> 0 | BI98: =BF98-BG98 -> 0 | BN98: =BK98-BL98 -> 0 | BS98: =BP98-BQ98 -> 0 | BX98: =BU98-BV98 -> 0 | CD98: =CA98-CB98 -> 0 | CI98: =CF98-CG98 -> 0 | CN98: =CK98-CL98 -> 0 | CS98: =CP98-CQ98 -> 0
A99: 90 | C99: 総限界利益 | J99: =SUM(P99,U99,Z99,AK99,AP99,AU99,BF99,BK99,BP99,CA99,CF99,CK99) -> 0 | K99: =SUM(Q99,V99,AA99,AL99,AQ99,AV99,BG99,BL99,BQ99,CB99,CG99,CL99) -> 0 | L99: =SUM(R99,W99,AB99,AM99,AR99,AW99,BH99,BM99,BR99,CC99,CH99,CM99) -> 0 | M99: =SUM(S99,X99,AC99,AN99,AS99,AX99,BI99,BN99,BS99,CD99,CI99,CN99) -> 0 | N99: =SUM(T99,Y99,AD99,AO99,AT99,AY99,BJ99,BO99,BT99,CE99,CJ99,CO99) -> 0 | S99: =P99-Q99 -> 0 | X99: =U99-V99 -> 0 | AD99: =AA99-AB99 -> 0 | AH99: =AE99-AF99 -> 0 | AN99: =AK99-AL99 -> 0 | AS99: =AP99-AQ99 -> 0 | AX99: =AU99-AV99 -> 0 | BC99: =AZ99-BA99 -> 0 | BI99: =BF99-BG99 -> 0 | BN99: =BK99-BL99 -> 0 | BS99: =BP99-BQ99 -> 0 | BX99: =BU99-BV99 -> 0 | CD99: =CA99-CB99 -> 0 | CI99: =CF99-CG99 -> 0 | CN99: =CK99-CL99 -> 0 | CS99: =CP99-CQ99 -> 0
A100: 91 | B100: 一般管理費 | C100: 人件費 | E100: 給与手当 | J100: =SUM(P100,U100,Z100,AK100,AP100,AU100,BF100,BK100,BP100,CA100,CF100,CK100) -> 0 | K100: =SUM(Q100,V100,AA100,AL100,AQ100,AV100,BG100,BL100,BQ100,CB100,CG100,CL100) -> 0 | L100: =SUM(R100,W100,AB100,AM100,AR100,AW100,BH100,BM100,BR100,CC100,CH100,CM100) -> 0 | M100: =SUM(S100,X100,AC100,AN100,AS100,AX100,BI100,BN100,BS100,CD100,CI100,CN100) -> 0 | N100: =SUM(T100,Y100,AD100,AO100,AT100,AY100,BJ100,BO100,BT100,CE100,CJ100,CO100) -> 0 | S100: =P100-Q100 -> 0 | X100: =U100-V100 -> 0 | AD100: =AA100-AB100 -> 0 | AH100: =AE100-AF100 -> 0 | AN100: =AK100-AL100 -> 0 | AS100: =AP100-AQ100 -> 0 | AX100: =AU100-AV100 -> 0 | BC100: =AZ100-BA100 -> 0 | BI100: =BF100-BG100 -> 0 | BN100: =BK100-BL100 -> 0 | BS100: =BP100-BQ100 -> 0 | BX100: =BU100-BV100 -> 0 | CD100: =CA100-CB100 -> 0 | CI100: =CF100-CG100 -> 0 | CN100: =CK100-CL100 -> 0 | CS100: =CP100-CQ100 -> 0
A101: 92 | E101: ＜内残業・奨励金＞ | J101: =SUM(P101,U101,Z101,AK101,AP101,AU101,BF101,BK101,BP101,CA101,CF101,CK101) -> 0 | K101: =SUM(Q101,V101,AA101,AL101,AQ101,AV101,BG101,BL101,BQ101,CB101,CG101,CL101) -> 0 | L101: =SUM(R101,W101,AB101,AM101,AR101,AW101,BH101,BM101,BR101,CC101,CH101,CM101) -> 0 | M101: =SUM(S101,X101,AC101,AN101,AS101,AX101,BI101,BN101,BS101,CD101,CI101,CN101) -> 0 | N101: =SUM(T101,Y101,AD101,AO101,AT101,AY101,BJ101,BO101,BT101,CE101,CJ101,CO101) -> 0 | S101: =P101-Q101 -> 0 | X101: =U101-V101 -> 0 | AD101: =AA101-AB101 -> 0 | AH101: =AE101-AF101 -> 0 | AN101: =AK101-AL101 -> 0 | AS101: =AP101-AQ101 -> 0 | AX101: =AU101-AV101 -> 0 | BC101: =AZ101-BA101 -> 0 | BI101: =BF101-BG101 -> 0 | BN101: =BK101-BL101 -> 0 | BS101: =BP101-BQ101 -> 0 | BX101: =BU101-BV101 -> 0 | CD101: =CA101-CB101 -> 0 | CI101: =CF101-CG101 -> 0 | CN101: =CK101-CL101 -> 0 | CS101: =CP101-CQ101 -> 0
A102: 93 | E102: 賞与 | J102: =SUM(P102,U102,Z102,AK102,AP102,AU102,BF102,BK102,BP102,CA102,CF102,CK102) -> 0 | K102: =SUM(Q102,V102,AA102,AL102,AQ102,AV102,BG102,BL102,BQ102,CB102,CG102,CL102) -> 0 | L102: =SUM(R102,W102,AB102,AM102,AR102,AW102,BH102,BM102,BR102,CC102,CH102,CM102) -> 0 | M102: =SUM(S102,X102,AC102,AN102,AS102,AX102,BI102,BN102,BS102,CD102,CI102,CN102) -> 0 | N102: =SUM(T102,Y102,AD102,AO102,AT102,AY102,BJ102,BO102,BT102,CE102,CJ102,CO102) -> 0 | S102: =P102-Q102 -> 0 | X102: =U102-V102 -> 0 | AD102: =AA102-AB102 -> 0 | AH102: =AE102-AF102 -> 0 | AN102: =AK102-AL102 -> 0 | AS102: =AP102-AQ102 -> 0 | AX102: =AU102-AV102 -> 0 | BC102: =AZ102-BA102 -> 0 | BI102: =BF102-BG102 -> 0 | BN102: =BK102-BL102 -> 0 | BS102: =BP102-BQ102 -> 0 | BX102: =BU102-BV102 -> 0 | CD102: =CA102-CB102 -> 0 | CI102: =CF102-CG102 -> 0 | CN102: =CK102-CL102 -> 0 | CS102: =CP102-CQ102 -> 0
A103: 94 | E103: 退職・福利厚生費 | J103: =SUM(P103,U103,Z103,AK103,AP103,AU103,BF103,BK103,BP103,CA103,CF103,CK103) -> 0 | K103: =SUM(Q103,V103,AA103,AL103,AQ103,AV103,BG103,BL103,BQ103,CB103,CG103,CL103) -> 0 | L103: =SUM(R103,W103,AB103,AM103,AR103,AW103,BH103,BM103,BR103,CC103,CH103,CM103) -> 0 | M103: =SUM(S103,X103,AC103,AN103,AS103,AX103,BI103,BN103,BS103,CD103,CI103,CN103) -> 0 | N103: =SUM(T103,Y103,AD103,AO103,AT103,AY103,BJ103,BO103,BT103,CE103,CJ103,CO103) -> 0 | S103: =P103-Q103 -> 0 | X103: =U103-V103 -> 0 | AD103: =AA103-AB103 -> 0 | AH103: =AE103-AF103 -> 0 | AN103: =AK103-AL103 -> 0 | AS103: =AP103-AQ103 -> 0 | AX103: =AU103-AV103 -> 0 | BC103: =AZ103-BA103 -> 0 | BI103: =BF103-BG103 -> 0 | BN103: =BK103-BL103 -> 0 | BS103: =BP103-BQ103 -> 0 | BX103: =BU103-BV103 -> 0 | CD103: =CA103-CB103 -> 0 | CI103: =CF103-CG103 -> 0 | CN103: =CK103-CL103 -> 0 | CS103: =CP103-CQ103 -> 0
...

Sheet サービス
B1: 予算表
B3: 期：
B5: 部署：
B7: 項目 | J7: 年間計 | P7: １０月 | U7: １１月 | Z7: １２月 | AE7: １０月～１２月合計 | AK7: １月 | AP7: ２月 | AU7: ３月 | AZ7: １月～３月合計 | BF7: ４月 | BK7: ５月 | BP7: ６月 | BU7: ４月～６月合計 | CA7: ７月 | CF7: ８月 | CK7: ９月 | CP7: ７月～９月合計
A8: LineNo
J9: 計画 | K9: 前年実績 | L9: 指標 | M9: 計画差 | N9: 前年比 | P9: 計画 | Q9: 前年実績 | R9: 指標 | S9: 計画差 | T9: 前年比 | U9: 計画 | V9: 前年実績 | W9: 指標 | X9: 計画差 | Y9: 前年比 | Z9: 計画 | AA9: 前年実績 | AB9: 指標 | AC9: 計画差 | AD9: 前年比 | AE9: 計画 | AF9: 前年実績 | AG9: 指標 | AH9: 計画差 | AI9: 前年比 | AK9: 計画 | AL9: 前年実績 | AM9: 指標 | AN9: 計画差 | AO9: 前年比 | AP9: 計画 | AQ9: 前年実績 | AR9: 指標 | AS9: 計画差 | AT9: 前年比 | AU9: 計画 | AV9: 前年実績 | AW9: 指標 | AX9: 計画差 | AY9: 前年比 | AZ9: 計画 | BA9: 前年実績 | BB9: 指標 | BC9: 計画差 | BD9: 前年比 | BF9: 計画 | BG9: 前年実績 | BH9: 指標 | BI9: 計画差 | BJ9: 前年比 | BK9: 計画 | BL9: 前年実績 | BM9: 指標 | BN9: 計画差 | BO9: 前年比 | BP9: 計画 | BQ9: 前年実績 | BR9: 指標 | BS9: 計画差 | BT9: 前年比 | BU9: 計画 | BV9: 前年実績 | BW9: 指標 | BX9: 計画差 | BY9: 前年比 | CA9: 計画 | CB9: 前年実績 | CC9: 指標 | CD9: 計画差 | CE9: 前年比 | CF9: 計画 | CG9: 前年実績 | CH9: 指標 | CI9: 計画差 | CJ9: 前年比 | CK9: 計画 | CL9: 前年実績 | CM9: 指標 | CN9: 計画差 | CO9: 前年比 | CP9: 計画 | CQ9: 前年実績 | CR9: 指標 | CS9: 計画差 | CT9: 前年比
A10: 1 | B10: 営業スタッフ数 | J10: =SUM(P10,U10,Z10,AK10,AP10,AU10,BF10,BK10,BP10,CA10,CF10,CK10) -> 0 | K10: =SUM(Q10,V10,AA10,AL10,AQ10,AV10,BG10,BL10,BQ10,CB10,CG10,CL10) -> 0 | L10: =SUM(R10,W10,AB10,AM10,AR10,AW10,BH10,BM10,BR10,CC10,CH10,CM10) -> 0 | M10: =SUM(S10,X10,AC10,AN10,AS10,AX10,BI10,BN10,BS10,CD10,CI10,CN10) -> 0 | N10: =SUM(T10,Y10,AD10,AO10,AT10,AY10,BJ10,BO10,BT10,CE10,CJ10,CO10) -> 0 | S10: =P10-Q10 -> 0 | X10: =U10-V10 -> 0 | AD10: =AA10-AB10 -> 0 | AH10: =AE10-AF10 -> 0 | AN10: =AK10-AL10 -> 0 | AS10: =AP10-AQ10 -> 0 | AX10: =AU10-AV10 -> 0 | BC10: =AZ10-BA10 -> 0 | BI10: =BF10-BG10 -> 0 | BN10: =BK10-BL10 -> 0 | BS10: =BP10-BQ10 -> 0 | BX10: =BU10-BV10 -> 0 | CD10: =CA10-CB10 -> 0 | CI10: =CF10-CG10 -> 0 | CN10: =CK10-CL10 -> 0 | CS10: =CP10-CQ10 -> 0
A11: 2 | B11: 自新直顧客数 | J11: =SUM(P11,U11,Z11,AK11,AP11,AU11,BF11,BK11,BP11,CA11,CF11,CK11) -> 0 | K11: =SUM(Q11,V11,AA11,AL11,AQ11,AV11,BG11,BL11,BQ11,CB11,CG11,CL11) -> 0 | L11: =SUM(R11,W11,AB11,AM11,AR11,AW11,BH11,BM11,BR11,CC11,CH11,CM11) -> 0 | M11: =SUM(S11,X11,AC11,AN11,AS11,AX11,BI11,BN11,BS11,CD11,CI11,CN11) -> 0 | N11: =SUM(T11,Y11,AD11,AO11,AT11,AY11,BJ11,BO11,BT11,CE11,CJ11,CO11) -> 0 | S11: =P11-Q11 -> 0 | X11: =U11-V11 -> 0 | AD11: =AA11-AB11 -> 0 | AH11: =AE11-AF11 -> 0 | AN11: =AK11-AL11 -> 0 | AS11: =AP11-AQ11 -> 0 | AX11: =AU11-AV11 -> 0 | BC11: =AZ11-BA11 -> 0 | BI11: =BF11-BG11 -> 0 | BN11: =BK11-BL11 -> 0 | BS11: =BP11-BQ11 -> 0 | BX11: =BU11-BV11 -> 0 | CD11: =CA11-CB11 -> 0 | CI11: =CF11-CG11 -> 0 | CN11: =CK11-CL11 -> 0 | CS11: =CP11-CQ11 -> 0
A12: 3 | B12: 顧客代替台数 | J12: =SUM(P12,U12,Z12,AK12,AP12,AU12,BF12,BK12,BP12,CA12,CF12,CK12) -> 0 | K12: =SUM(Q12,V12,AA12,AL12,AQ12,AV12,BG12,BL12,BQ12,CB12,CG12,CL12) -> 0 | L12: =SUM(R12,W12,AB12,AM12,AR12,AW12,BH12,BM12,BR12,CC12,CH12,CM12) -> 0 | M12: =SUM(S12,X12,AC12,AN12,AS12,AX12,BI12,BN12,BS12,CD12,CI12,CN12) -> 0 | N12: =SUM(T12,Y12,AD12,AO12,AT12,AY12,BJ12,BO12,BT12,CE12,CJ12,CO12) -> 0 | S12: =P12-Q12 -> 0 | X12: =U12-V12 -> 0 | AD12: =AA12-AB12 -> 0 | AH12: =AE12-AF12 -> 0 | AN12: =AK12-AL12 -> 0 | AS12: =AP12-AQ12 -> 0 | AX12: =AU12-AV12 -> 0 | BC12: =AZ12-BA12 -> 0 | BI12: =BF12-BG12 -> 0 | BN12: =BK12-BL12 -> 0 | BS12: =BP12-BQ12 -> 0 | BX12: =BU12-BV12 -> 0 | CD12: =CA12-CB12 -> 0 | CI12: =CF12-CG12 -> 0 | CN12: =CK12-CL12 -> 0 | CS12: =CP12-CQ12 -> 0
A13: 4 | B13: 自中直顧客数 | J13: =SUM(P13,U13,Z13,AK13,AP13,AU13,BF13,BK13,BP13,CA13,CF13,CK13) -> 0 | K13: =SUM(Q13,V13,AA13,AL13,AQ13,AV13,BG13,BL13,BQ13,CB13,CG13,CL13) -> 0 | L13: =SUM(R13,W13,AB13,AM13,AR13,AW13,BH13,BM13,BR13,CC13,CH13,CM13) -> 0 | M13: =SUM(S13,X13,AC13,AN13,AS13,AX13,BI13,BN13,BS13,CD13,CI13,CN13) -> 0 | N13: =SUM(T13,Y13,AD13,AO13,AT13,AY13,BJ13,BO13,BT13,CE13,CJ13,CO13) -> 0 | S13: =P13-Q13 -> 0 | X13: =U13-V13 -> 0 | AD13: =AA13-AB13 -> 0 | AH13: =AE13-AF13 -> 0 | AN13: =AK13-AL13 -> 0 | AS13: =AP13-AQ13 -> 0 | AX13: =AU13-AV13 -> 0 | BC13: =AZ13-BA13 -> 0 | BI13: =BF13-BG13 -> 0 | BN13: =BK13-BL13 -> 0 | BS13: =BP13-BQ13 -> 0 | BX13: =BU13-BV13 -> 0 | CD13: =CA13-CB13 -> 0 | CI13: =CF13-CG13 -> 0 | CN13: =CK13-CL13 -> 0 | CS13: =CP13-CQ13 -> 0
A14: 5 | B14: サービス直人員 | J14: =SUM(P14,U14,Z14,AK14,AP14,AU14,BF14,BK14,BP14,CA14,CF14,CK14) -> 0 | K14: =SUM(Q14,V14,AA14,AL14,AQ14,AV14,BG14,BL14,BQ14,CB14,CG14,CL14) -> 0 | L14: =SUM(R14,W14,AB14,AM14,AR14,AW14,BH14,BM14,BR14,CC14,CH14,CM14) -> 0 | M14: =SUM(S14,X14,AC14,AN14,AS14,AX14,BI14,BN14,BS14,CD14,CI14,CN14) -> 0 | N14: =SUM(T14,Y14,AD14,AO14,AT14,AY14,BJ14,BO14,BT14,CE14,CJ14,CO14) -> 0 | S14: =P14-Q14 -> 0 | X14: =U14-V14 -> 0 | AD14: =AA14-AB14 -> 0 | AH14: =AE14-AF14 -> 0 | AN14: =AK14-AL14 -> 0 | AS14: =AP14-AQ14 -> 0 | AX14: =AU14-AV14 -> 0 | BC14: =AZ14-BA14 -> 0 | BI14: =BF14-BG14 -> 0 | BN14: =BK14-BL14 -> 0 | BS14: =BP14-BQ14 -> 0 | BX14: =BU14-BV14 -> 0 | CD14: =CA14-CB14 -> 0 | CI14: =CF14-CG14 -> 0 | CN14: =CK14-CL14 -> 0 | CS14: =CP14-CQ14 -> 0
A15: 6 | B15: サービス管理顧客数 | J15: =SUM(P15,U15,Z15,AK15,AP15,AU15,BF15,BK15,BP15,CA15,CF15,CK15) -> 0 | K15: =SUM(Q15,V15,AA15,AL15,AQ15,AV15,BG15,BL15,BQ15,CB15,CG15,CL15) -> 0 | L15: =SUM(R15,W15,AB15,AM15,AR15,AW15,BH15,BM15,BR15,CC15,CH15,CM15) -> 0 | M15: =SUM(S15,X15,AC15,AN15,AS15,AX15,BI15,BN15,BS15,CD15,CI15,CN15) -> 0 | N15: =SUM(T15,Y15,AD15,AO15,AT15,AY15,BJ15,BO15,BT15,CE15,CJ15,CO15) -> 0 | S15: =P15-Q15 -> 0 | X15: =U15-V15 -> 0 | AD15: =AA15-AB15 -> 0 | AH15: =AE15-AF15 -> 0 | AN15: =AK15-AL15 -> 0 | AS15: =AP15-AQ15 -> 0 | AX15: =AU15-AV15 -> 0 | BC15: =AZ15-BA15 -> 0 | BI15: =BF15-BG15 -> 0 | BN15: =BK15-BL15 -> 0 | BS15: =BP15-BQ15 -> 0 | BX15: =BU15-BV15 -> 0 | CD15: =CA15-CB15 -> 0 | CI15: =CF15-CG15 -> 0 | CN15: =CK15-CL15 -> 0 | CS15: =CP15-CQ15 -> 0
A16: 7 | B16: 車検対象台数 | J16: =SUM(P16,U16,Z16,AK16,AP16,AU16,BF16,BK16,BP16,CA16,CF16,CK16) -> 0 | K16: =SUM(Q16,V16,AA16,AL16,AQ16,AV16,BG16,BL16,BQ16,CB16,CG16,CL16) -> 0 | L16: =SUM(R16,W16,AB16,AM16,AR16,AW16,BH16,BM16,BR16,CC16,CH16,CM16) -> 0 | M16: =SUM(S16,X16,AC16,AN16,AS16,AX16,BI16,BN16,BS16,CD16,CI16,CN16) -> 0 | N16: =SUM(T16,Y16,AD16,AO16,AT16,AY16,BJ16,BO16,BT16,CE16,CJ16,CO16) -> 0 | S16: =P16-Q16 -> 0 | X16: =U16-V16 -> 0 | AD16: =AA16-AB16 -> 0 | AH16: =AE16-AF16 -> 0 | AN16: =AK16-AL16 -> 0 | AS16: =AP16-AQ16 -> 0 | AX16: =AU16-AV16 -> 0 | BC16: =AZ16-BA16 -> 0 | BI16: =BF16-BG16 -> 0 | BN16: =BK16-BL16 -> 0 | BS16: =BP16-BQ16 -> 0 | BX16: =BU16-BV16 -> 0 | CD16: =CA16-CB16 -> 0 | CI16: =CF16-CG16 -> 0 | CN16: =CK16-CL16 -> 0 | CS16: =CP16-CQ16 -> 0
A17: 8 | C17: 内初回車検対象台数 | J17: =SUM(P17,U17,Z17,AK17,AP17,AU17,BF17,BK17,BP17,CA17,CF17,CK17) -> 0 | K17: =SUM(Q17,V17,AA17,AL17,AQ17,AV17,BG17,BL17,BQ17,CB17,CG17,CL17) -> 0 | L17: =SUM(R17,W17,AB17,AM17,AR17,AW17,BH17,BM17,BR17,CC17,CH17,CM17) -> 0 | M17: =SUM(S17,X17,AC17,AN17,AS17,AX17,BI17,BN17,BS17,CD17,CI17,CN17) -> 0 | N17: =SUM(T17,Y17,AD17,AO17,AT17,AY17,BJ17,BO17,BT17,CE17,CJ17,CO17) -> 0 | S17: =P17-Q17 -> 0 | X17: =U17-V17 -> 0 | AD17: =AA17-AB17 -> 0 | AH17: =AE17-AF17 -> 0 | AN17: =AK17-AL17 -> 0 | AS17: =AP17-AQ17 -> 0 | AX17: =AU17-AV17 -> 0 | BC17: =AZ17-BA17 -> 0 | BI17: =BF17-BG17 -> 0 | BN17: =BK17-BL17 -> 0 | BS17: =BP17-BQ17 -> 0 | BX17: =BU17-BV17 -> 0 | CD17: =CA17-CB17 -> 0 | CI17: =CF17-CG17 -> 0 | CN17: =CK17-CL17 -> 0 | CS17: =CP17-CQ17 -> 0
A18: 9 | B18: 初回車検入庫 | J18: =SUM(P18,U18,Z18,AK18,AP18,AU18,BF18,BK18,BP18,CA18,CF18,CK18) -> 0 | K18: =SUM(Q18,V18,AA18,AL18,AQ18,AV18,BG18,BL18,BQ18,CB18,CG18,CL18) -> 0 | L18: =SUM(R18,W18,AB18,AM18,AR18,AW18,BH18,BM18,BR18,CC18,CH18,CM18) -> 0 | M18: =SUM(S18,X18,AC18,AN18,AS18,AX18,BI18,BN18,BS18,CD18,CI18,CN18) -> 0 | N18: =SUM(T18,Y18,AD18,AO18,AT18,AY18,BJ18,BO18,BT18,CE18,CJ18,CO18) -> 0 | S18: =P18-Q18 -> 0 | X18: =U18-V18 -> 0 | AD18: =AA18-AB18 -> 0 | AH18: =AE18-AF18 -> 0 | AN18: =AK18-AL18 -> 0 | AS18: =AP18-AQ18 -> 0 | AX18: =AU18-AV18 -> 0 | BC18: =AZ18-BA18 -> 0 | BI18: =BF18-BG18 -> 0 | BN18: =BK18-BL18 -> 0 | BS18: =BP18-BQ18 -> 0 | BX18: =BU18-BV18 -> 0 | CD18: =CA18-CB18 -> 0 | CI18: =CF18-CG18 -> 0 | CN18: =CK18-CL18 -> 0 | CS18: =CP18-CQ18 -> 0
A19: 10 | B19: 有償入庫台数 | J19: =SUM(P19,U19,Z19,AK19,AP19,AU19,BF19,BK19,BP19,CA19,CF19,CK19) -> 0 | K19: =SUM(Q19,V19,AA19,AL19,AQ19,AV19,BG19,BL19,BQ19,CB19,CG19,CL19) -> 0 | L19: =SUM(R19,W19,AB19,AM19,AR19,AW19,BH19,BM19,BR19,CC19,CH19,CM19) -> 0 | M19: =SUM(S19,X19,AC19,AN19,AS19,AX19,BI19,BN19,BS19,CD19,CI19,CN19) -> 0 | N19: =SUM(T19,Y19,AD19,AO19,AT19,AY19,BJ19,BO19,BT19,CE19,CJ19,CO19) -> 0 | S19: =P19-Q19 -> 0 | X19: =U19-V19 -> 0 | AD19: =AA19-AB19 -> 0 | AH19: =AE19-AF19 -> 0 | AN19: =AK19-AL19 -> 0 | AS19: =AP19-AQ19 -> 0 | AX19: =AU19-AV19 -> 0 | BC19: =AZ19-BA19 -> 0 | BI19: =BF19-BG19 -> 0 | BN19: =BK19-BL19 -> 0 | BS19: =BP19-BQ19 -> 0 | BX19: =BU19-BV19 -> 0 | CD19: =CA19-CB19 -> 0 | CI19: =CF19-CG19 -> 0 | CN19: =CK19-CL19 -> 0 | CS19: =CP19-CQ19 -> 0
A20: 11 | B20: 新規獲得件数 | J20: =SUM(P20,U20,Z20,AK20,AP20,AU20,BF20,BK20,BP20,CA20,CF20,CK20) -> 0 | K20: =SUM(Q20,V20,AA20,AL20,AQ20,AV20,BG20,BL20,BQ20,CB20,CG20,CL20) -> 0 | L20: =SUM(R20,W20,AB20,AM20,AR20,AW20,BH20,BM20,BR20,CC20,CH20,CM20) -> 0 | M20: =SUM(S20,X20,AC20,AN20,AS20,AX20,BI20,BN20,BS20,CD20,CI20,CN20) -> 0 | N20: =SUM(T20,Y20,AD20,AO20,AT20,AY20,BJ20,BO20,BT20,CE20,CJ20,CO20) -> 0 | S20: =P20-Q20 -> 0 | X20: =U20-V20 -> 0 | AD20: =AA20-AB20 -> 0 | AH20: =AE20-AF20 -> 0 | AN20: =AK20-AL20 -> 0 | AS20: =AP20-AQ20 -> 0 | AX20: =AU20-AV20 -> 0 | BC20: =AZ20-BA20 -> 0 | BI20: =BF20-BG20 -> 0 | BN20: =BK20-BL20 -> 0 | BS20: =BP20-BQ20 -> 0 | BX20: =BU20-BV20 -> 0 | CD20: =CA20-CB20 -> 0 | CI20: =CF20-CG20 -> 0 | CN20: =CK20-CL20 -> 0 | CS20: =CP20-CQ20 -> 0
A21: 12 | B21: 継続対象件数 | J21: =SUM(P21,U21,Z21,AK21,AP21,AU21,BF21,BK21,BP21,CA21,CF21,CK21) -> 0 | K21: =SUM(Q21,V21,AA21,AL21,AQ21,AV21,BG21,BL21,BQ21,CB21,CG21,CL21) -> 0 | L21: =SUM(R21,W21,AB21,AM21,AR21,AW21,BH21,BM21,BR21,CC21,CH21,CM21) -> 0 | M21: =SUM(S21,X21,AC21,AN21,AS21,AX21,BI21,BN21,BS21,CD21,CI21,CN21) -> 0 | N21: =SUM(T21,Y21,AD21,AO21,AT21,AY21,BJ21,BO21,BT21,CE21,CJ21,CO21) -> 0 | S21: =P21-Q21 -> 0 | X21: =U21-V21 -> 0 | AD21: =AA21-AB21 -> 0 | AH21: =AE21-AF21 -> 0 | AN21: =AK21-AL21 -> 0 | AS21: =AP21-AQ21 -> 0 | AX21: =AU21-AV21 -> 0 | BC21: =AZ21-BA21 -> 0 | BI21: =BF21-BG21 -> 0 | BN21: =BK21-BL21 -> 0 | BS21: =BP21-BQ21 -> 0 | BX21: =BU21-BV21 -> 0 | CD21: =CA21-CB21 -> 0 | CI21: =CF21-CG21 -> 0 | CN21: =CK21-CL21 -> 0 | CS21: =CP21-CQ21 -> 0
A22: 13 | B22: 継続件数 | J22: =SUM(P22,U22,Z22,AK22,AP22,AU22,BF22,BK22,BP22,CA22,CF22,CK22) -> 0 | K22: =SUM(Q22,V22,AA22,AL22,AQ22,AV22,BG22,BL22,BQ22,CB22,CG22,CL22) -> 0 | L22: =SUM(R22,W22,AB22,AM22,AR22,AW22,BH22,BM22,BR22,CC22,CH22,CM22) -> 0 | M22: =SUM(S22,X22,AC22,AN22,AS22,AX22,BI22,BN22,BS22,CD22,CI22,CN22) -> 0 | N22: =SUM(T22,Y22,AD22,AO22,AT22,AY22,BJ22,BO22,BT22,CE22,CJ22,CO22) -> 0 | S22: =P22-Q22 -> 0 | X22: =U22-V22 -> 0 | AD22: =AA22-AB22 -> 0 | AH22: =AE22-AF22 -> 0 | AN22: =AK22-AL22 -> 0 | AS22: =AP22-AQ22 -> 0 | AX22: =AU22-AV22 -> 0 | BC22: =AZ22-BA22 -> 0 | BI22: =BF22-BG22 -> 0 | BN22: =BK22-BL22 -> 0 | BS22: =BP22-BQ22 -> 0 | BX22: =BU22-BV22 -> 0 | CD22: =CA22-CB22 -> 0 | CI22: =CF22-CG22 -> 0 | CN22: =CK22-CL22 -> 0 | CS22: =CP22-CQ22 -> 0
A23: 14 | B23: 車両保険件数 | J23: =SUM(P23,U23,Z23,AK23,AP23,AU23,BF23,BK23,BP23,CA23,CF23,CK23) -> 0 | K23: =SUM(Q23,V23,AA23,AL23,AQ23,AV23,BG23,BL23,BQ23,CB23,CG23,CL23) -> 0 | L23: =SUM(R23,W23,AB23,AM23,AR23,AW23,BH23,BM23,BR23,CC23,CH23,CM23) -> 0 | M23: =SUM(S23,X23,AC23,AN23,AS23,AX23,BI23,BN23,BS23,CD23,CI23,CN23) -> 0 | N23: =SUM(T23,Y23,AD23,AO23,AT23,AY23,BJ23,BO23,BT23,CE23,CJ23,CO23) -> 0 | S23: =P23-Q23 -> 0 | X23: =U23-V23 -> 0 | AD23: =AA23-AB23 -> 0 | AH23: =AE23-AF23 -> 0 | AN23: =AK23-AL23 -> 0 | AS23: =AP23-AQ23 -> 0 | AX23: =AU23-AV23 -> 0 | BC23: =AZ23-BA23 -> 0 | BI23: =BF23-BG23 -> 0 | BN23: =BK23-BL23 -> 0 | BS23: =BP23-BQ23 -> 0 | BX23: =BU23-BV23 -> 0 | CD23: =CA23-CB23 -> 0 | CI23: =CF23-CG23 -> 0 | CN23: =CK23-CL23 -> 0 | CS23: =CP23-CQ23 -> 0
A24: 15 | B24: 収保 | J24: =SUM(P24,U24,Z24,AK24,AP24,AU24,BF24,BK24,BP24,CA24,CF24,CK24) -> 0 | K24: =SUM(Q24,V24,AA24,AL24,AQ24,AV24,BG24,BL24,BQ24,CB24,CG24,CL24) -> 0 | L24: =SUM(R24,W24,AB24,AM24,AR24,AW24,BH24,BM24,BR24,CC24,CH24,CM24) -> 0 | M24: =SUM(S24,X24,AC24,AN24,AS24,AX24,BI24,BN24,BS24,CD24,CI24,CN24) -> 0 | N24: =SUM(T24,Y24,AD24,AO24,AT24,AY24,BJ24,BO24,BT24,CE24,CJ24,CO24) -> 0 | S24: =P24-Q24 -> 0 | X24: =U24-V24 -> 0 | AD24: =AA24-AB24 -> 0 | AH24: =AE24-AF24 -> 0 | AN24: =AK24-AL24 -> 0 | AS24: =AP24-AQ24 -> 0 | AX24: =AU24-AV24 -> 0 | BC24: =AZ24-BA24 -> 0 | BI24: =BF24-BG24 -> 0 | BN24: =BK24-BL24 -> 0 | BS24: =BP24-BQ24 -> 0 | BX24: =BU24-BV24 -> 0 | CD24: =CA24-CB24 -> 0 | CI24: =CF24-CG24 -> 0 | CN24: =CK24-CL24 -> 0 | CS24: =CP24-CQ24 -> 0
A25: 16 | B25: 総限界利益 | C25: 総利益合計 | D25: 新車 | E25: 新車台数 | J25: =SUM(P25,U25,Z25,AK25,AP25,AU25,BF25,BK25,BP25,CA25,CF25,CK25) -> 0 | K25: =SUM(Q25,V25,AA25,AL25,AQ25,AV25,BG25,BL25,BQ25,CB25,CG25,CL25) -> 0 | L25: =SUM(R25,W25,AB25,AM25,AR25,AW25,BH25,BM25,BR25,CC25,CH25,CM25) -> 0 | M25: =SUM(S25,X25,AC25,AN25,AS25,AX25,BI25,BN25,BS25,CD25,CI25,CN25) -> 0 | N25: =SUM(T25,Y25,AD25,AO25,AT25,AY25,BJ25,BO25,BT25,CE25,CJ25,CO25) -> 0 | S25: =P25-Q25 -> 0 | X25: =U25-V25 -> 0 | AD25: =AA25-AB25 -> 0 | AH25: =AE25-AF25 -> 0 | AN25: =AK25-AL25 -> 0 | AS25: =AP25-AQ25 -> 0 | AX25: =AU25-AV25 -> 0 | BC25: =AZ25-BA25 -> 0 | BI25: =BF25-BG25 -> 0 | BN25: =BK25-BL25 -> 0 | BS25: =BP25-BQ25 -> 0 | BX25: =BU25-BV25 -> 0 | CD25: =CA25-CB25 -> 0 | CI25: =CF25-CG25 -> 0 | CN25: =CK25-CL25 -> 0 | CS25: =CP25-CQ25 -> 0
A26: 17 | E26: 売上金額（架装売上含む） | J26: =SUM(P26,U26,Z26,AK26,AP26,AU26,BF26,BK26,BP26,CA26,CF26,CK26) -> 0 | K26: =SUM(Q26,V26,AA26,AL26,AQ26,AV26,BG26,BL26,BQ26,CB26,CG26,CL26) -> 0 | L26: =SUM(R26,W26,AB26,AM26,AR26,AW26,BH26,BM26,BR26,CC26,CH26,CM26) -> 0 | M26: =SUM(S26,X26,AC26,AN26,AS26,AX26,BI26,BN26,BS26,CD26,CI26,CN26) -> 0 | N26: =SUM(T26,Y26,AD26,AO26,AT26,AY26,BJ26,BO26,BT26,CE26,CJ26,CO26) -> 0 | S26: =P26-Q26 -> 0 | X26: =U26-V26 -> 0 | AD26: =AA26-AB26 -> 0 | AH26: =AE26-AF26 -> 0 | AN26: =AK26-AL26 -> 0 | AS26: =AP26-AQ26 -> 0 | AX26: =AU26-AV26 -> 0 | BC26: =AZ26-BA26 -> 0 | BI26: =BF26-BG26 -> 0 | BN26: =BK26-BL26 -> 0 | BS26: =BP26-BQ26 -> 0 | BX26: =BU26-BV26 -> 0 | CD26: =CA26-CB26 -> 0 | CI26: =CF26-CG26 -> 0 | CN26: =CK26-CL26 -> 0 | CS26: =CP26-CQ26 -> 0
A27: 18 | F27: ＜内車両値引＞ | J27: =SUM(P27,U27,Z27,AK27,AP27,AU27,BF27,BK27,BP27,CA27,CF27,CK27) -> 0 | K27: =SUM(Q27,V27,AA27,AL27,AQ27,AV27,BG27,BL27,BQ27,CB27,CG27,CL27) -> 0 | L27: =SUM(R27,W27,AB27,AM27,AR27,AW27,BH27,BM27,BR27,CC27,CH27,CM27) -> 0 | M27: =SUM(S27,X27,AC27,AN27,AS27,AX27,BI27,BN27,BS27,CD27,CI27,CN27) -> 0 | N27: =SUM(T27,Y27,AD27,AO27,AT27,AY27,BJ27,BO27,BT27,CE27,CJ27,CO27) -> 0 | S27: =P27-Q27 -> 0 | X27: =U27-V27 -> 0 | AD27: =AA27-AB27 -> 0 | AH27: =AE27-AF27 -> 0 | AN27: =AK27-AL27 -> 0 | AS27: =AP27-AQ27 -> 0 | AX27: =AU27-AV27 -> 0 | BC27: =AZ27-BA27 -> 0 | BI27: =BF27-BG27 -> 0 | BN27: =BK27-BL27 -> 0 | BS27: =BP27-BQ27 -> 0 | BX27: =BU27-BV27 -> 0 | CD27: =CA27-CB27 -> 0 | CI27: =CF27-CG27 -> 0 | CN27: =CK27-CL27 -> 0 | CS27: =CP27-CQ27 -> 0
A28: 19 | F28: 車両本体利益 | J28: =SUM(P28,U28,Z28,AK28,AP28,AU28,BF28,BK28,BP28,CA28,CF28,CK28) -> 0 | K28: =SUM(Q28,V28,AA28,AL28,AQ28,AV28,BG28,BL28,BQ28,CB28,CG28,CL28) -> 0 | L28: =SUM(R28,W28,AB28,AM28,AR28,AW28,BH28,BM28,BR28,CC28,CH28,CM28) -> 0 | M28: =SUM(S28,X28,AC28,AN28,AS28,AX28,BI28,BN28,BS28,CD28,CI28,CN28) -> 0 | N28: =SUM(T28,Y28,AD28,AO28,AT28,AY28,BJ28,BO28,BT28,CE28,CJ28,CO28) -> 0 | S28: =P28-Q28 -> 0 | X28: =U28-V28 -> 0 | AD28: =AA28-AB28 -> 0 | AH28: =AE28-AF28 -> 0 | AN28: =AK28-AL28 -> 0 | AS28: =AP28-AQ28 -> 0 | AX28: =AU28-AV28 -> 0 | BC28: =AZ28-BA28 -> 0 | BI28: =BF28-BG28 -> 0 | BN28: =BK28-BL28 -> 0 | BS28: =BP28-BQ28 -> 0 | BX28: =BU28-BV28 -> 0 | CD28: =CA28-CB28 -> 0 | CI28: =CF28-CG28 -> 0 | CN28: =CK28-CL28 -> 0 | CS28: =CP28-CQ28 -> 0
A29: 20 | F29: 架装付属品利益 | J29: =SUM(P29,U29,Z29,AK29,AP29,AU29,BF29,BK29,BP29,CA29,CF29,CK29) -> 0 | K29: =SUM(Q29,V29,AA29,AL29,AQ29,AV29,BG29,BL29,BQ29,CB29,CG29,CL29) -> 0 | L29: =SUM(R29,W29,AB29,AM29,AR29,AW29,BH29,BM29,BR29,CC29,CH29,CM29) -> 0 | M29: =SUM(S29,X29,AC29,AN29,AS29,AX29,BI29,BN29,BS29,CD29,CI29,CN29) -> 0 | N29: =SUM(T29,Y29,AD29,AO29,AT29,AY29,BJ29,BO29,BT29,CE29,CJ29,CO29) -> 0 | S29: =P29-Q29 -> 0 | X29: =U29-V29 -> 0 | AD29: =AA29-AB29 -> 0 | AH29: =AE29-AF29 -> 0 | AN29: =AK29-AL29 -> 0 | AS29: =AP29-AQ29 -> 0 | AX29: =AU29-AV29 -> 0 | BC29: =AZ29-BA29 -> 0 | BI29: =BF29-BG29 -> 0 | BN29: =BK29-BL29 -> 0 | BS29: =BP29-BQ29 -> 0 | BX29: =BU29-BV29 -> 0 | CD29: =CA29-CB29 -> 0 | CI29: =CF29-CG29 -> 0 | CN29: =CK29-CL29 -> 0 | CS29: =CP29-CQ29 -> 0
A30: 21 | F30: 車両収入手数料 | J30: =SUM(P30,U30,Z30,AK30,AP30,AU30,BF30,BK30,BP30,CA30,CF30,CK30) -> 0 | K30: =SUM(Q30,V30,AA30,AL30,AQ30,AV30,BG30,BL30,BQ30,CB30,CG30,CL30) -> 0 | L30: =SUM(R30,W30,AB30,AM30,AR30,AW30,BH30,BM30,BR30,CC30,CH30,CM30) -> 0 | M30: =SUM(S30,X30,AC30,AN30,AS30,AX30,BI30,BN30,BS30,CD30,CI30,CN30) -> 0 | N30: =SUM(T30,Y30,AD30,AO30,AT30,AY30,BJ30,BO30,BT30,CE30,CJ30,CO30) -> 0 | S30: =P30-Q30 -> 0 | X30: =U30-V30 -> 0 | AD30: =AA30-AB30 -> 0 | AH30: =AE30-AF30 -> 0 | AN30: =AK30-AL30 -> 0 | AS30: =AP30-AQ30 -> 0 | AX30: =AU30-AV30 -> 0 | BC30: =AZ30-BA30 -> 0 | BI30: =BF30-BG30 -> 0 | BN30: =BK30-BL30 -> 0 | BS30: =BP30-BQ30 -> 0 | BX30: =BU30-BV30 -> 0 | CD30: =CA30-CB30 -> 0 | CI30: =CF30-CG30 -> 0 | CN30: =CK30-CL30 -> 0 | CS30: =CP30-CQ30 -> 0
A31: 22 | F31: 登録収入手数料 | J31: =SUM(P31,U31,Z31,AK31,AP31,AU31,BF31,BK31,BP31,CA31,CF31,CK31) -> 0 | K31: =SUM(Q31,V31,AA31,AL31,AQ31,AV31,BG31,BL31,BQ31,CB31,CG31,CL31) -> 0 | L31: =SUM(R31,W31,AB31,AM31,AR31,AW31,BH31,BM31,BR31,CC31,CH31,CM31) -> 0 | M31: =SUM(S31,X31,AC31,AN31,AS31,AX31,BI31,BN31,BS31,CD31,CI31,CN31) -> 0 | N31: =SUM(T31,Y31,AD31,AO31,AT31,AY31,BJ31,BO31,BT31,CE31,CJ31,CO31) -> 0 | S31: =P31-Q31 -> 0 | X31: =U31-V31 -> 0 | AD31: =AA31-AB31 -> 0 | AH31: =AE31-AF31 -> 0 | AN31: =AK31-AL31 -> 0 | AS31: =AP31-AQ31 -> 0 | AX31: =AU31-AV31 -> 0 | BC31: =AZ31-BA31 -> 0 | BI31: =BF31-BG31 -> 0 | BN31: =BK31-BL31 -> 0 | BS31: =BP31-BQ31 -> 0 | BX31: =BU31-BV31 -> 0 | CD31: =CA31-CB31 -> 0 | CI31: =CF31-CG31 -> 0 | CN31: =CK31-CL31 -> 0 | CS31: =CP31-CQ31 -> 0
A32: 23 | F32: クレジット利益 | J32: =SUM(P32,U32,Z32,AK32,AP32,AU32,BF32,BK32,BP32,CA32,CF32,CK32) -> 0 | K32: =SUM(Q32,V32,AA32,AL32,AQ32,AV32,BG32,BL32,BQ32,CB32,CG32,CL32) -> 0 | L32: =SUM(R32,W32,AB32,AM32,AR32,AW32,BH32,BM32,BR32,CC32,CH32,CM32) -> 0 | M32: =SUM(S32,X32,AC32,AN32,AS32,AX32,BI32,BN32,BS32,CD32,CI32,CN32) -> 0 | N32: =SUM(T32,Y32,AD32,AO32,AT32,AY32,BJ32,BO32,BT32,CE32,CJ32,CO32) -> 0 | S32: =P32-Q32 -> 0 | X32: =U32-V32 -> 0 | AD32: =AA32-AB32 -> 0 | AH32: =AE32-AF32 -> 0 | AN32: =AK32-AL32 -> 0 | AS32: =AP32-AQ32 -> 0 | AX32: =AU32-AV32 -> 0 | BC32: =AZ32-BA32 -> 0 | BI32: =BF32-BG32 -> 0 | BN32: =BK32-BL32 -> 0 | BS32: =BP32-BQ32 -> 0 | BX32: =BU32-BV32 -> 0 | CD32: =CA32-CB32 -> 0 | CI32: =CF32-CG32 -> 0 | CN32: =CK32-CL32 -> 0 | CS32: =CP32-CQ32 -> 0
A33: 24 | F33: 販売手数料 | J33: =SUM(P33,U33,Z33,AK33,AP33,AU33,BF33,BK33,BP33,CA33,CF33,CK33) -> 0 | K33: =SUM(Q33,V33,AA33,AL33,AQ33,AV33,BG33,BL33,BQ33,CB33,CG33,CL33) -> 0 | L33: =SUM(R33,W33,AB33,AM33,AR33,AW33,BH33,BM33,BR33,CC33,CH33,CM33) -> 0 | M33: =SUM(S33,X33,AC33,AN33,AS33,AX33,BI33,BN33,BS33,CD33,CI33,CN33) -> 0 | N33: =SUM(T33,Y33,AD33,AO33,AT33,AY33,BJ33,BO33,BT33,CE33,CJ33,CO33) -> 0 | S33: =P33-Q33 -> 0 | X33: =U33-V33 -> 0 | AD33: =AA33-AB33 -> 0 | AH33: =AE33-AF33 -> 0 | AN33: =AK33-AL33 -> 0 | AS33: =AP33-AQ33 -> 0 | AX33: =AU33-AV33 -> 0 | BC33: =AZ33-BA33 -> 0 | BI33: =BF33-BG33 -> 0 | BN33: =BK33-BL33 -> 0 | BS33: =BP33-BQ33 -> 0 | BX33: =BU33-BV33 -> 0 | CD33: =CA33-CB33 -> 0 | CI33: =CF33-CG33 -> 0 | CN33: =CK33-CL33 -> 0 | CS33: =CP33-CQ33 -> 0
A34: 25 | E34: 新車総粗利 | J34: =SUM(P34,U34,Z34,AK34,AP34,AU34,BF34,BK34,BP34,CA34,CF34,CK34) -> 0 | K34: =SUM(Q34,V34,AA34,AL34,AQ34,AV34,BG34,BL34,BQ34,CB34,CG34,CL34) -> 0 | L34: =SUM(R34,W34,AB34,AM34,AR34,AW34,BH34,BM34,BR34,CC34,CH34,CM34) -> 0 | M34: =SUM(S34,X34,AC34,AN34,AS34,AX34,BI34,BN34,BS34,CD34,CI34,CN34) -> 0 | N34: =SUM(T34,Y34,AD34,AO34,AT34,AY34,BJ34,BO34,BT34,CE34,CJ34,CO34) -> 0 | S34: =P34-Q34 -> 0 | X34: =U34-V34 -> 0 | AD34: =AA34-AB34 -> 0 | AH34: =AE34-AF34 -> 0 | AN34: =AK34-AL34 -> 0 | AS34: =AP34-AQ34 -> 0 | AX34: =AU34-AV34 -> 0 | BC34: =AZ34-BA34 -> 0 | BI34: =BF34-BG34 -> 0 | BN34: =BK34-BL34 -> 0 | BS34: =BP34-BQ34 -> 0 | BX34: =BU34-BV34 -> 0 | CD34: =CA34-CB34 -> 0 | CI34: =CF34-CG34 -> 0 | CN34: =CK34-CL34 -> 0 | CS34: =CP34-CQ34 -> 0
A35: 26 | E35: 販売費 | F35: 販手・サービス・雑費 | J35: =SUM(P35,U35,Z35,AK35,AP35,AU35,BF35,BK35,BP35,CA35,CF35,CK35) -> 0 | K35: =SUM(Q35,V35,AA35,AL35,AQ35,AV35,BG35,BL35,BQ35,CB35,CG35,CL35) -> 0 | L35: =SUM(R35,W35,AB35,AM35,AR35,AW35,BH35,BM35,BR35,CC35,CH35,CM35) -> 0 | M35: =SUM(S35,X35,AC35,AN35,AS35,AX35,BI35,BN35,BS35,CD35,CI35,CN35) -> 0 | N35: =SUM(T35,Y35,AD35,AO35,AT35,AY35,BJ35,BO35,BT35,CE35,CJ35,CO35) -> 0 | S35: =P35-Q35 -> 0 | X35: =U35-V35 -> 0 | AD35: =AA35-AB35 -> 0 | AH35: =AE35-AF35 -> 0 | AN35: =AK35-AL35 -> 0 | AS35: =AP35-AQ35 -> 0 | AX35: =AU35-AV35 -> 0 | BC35: =AZ35-BA35 -> 0 | BI35: =BF35-BG35 -> 0 | BN35: =BK35-BL35 -> 0 | BS35: =BP35-BQ35 -> 0 | BX35: =BU35-BV35 -> 0 | CD35: =CA35-CB35 -> 0 | CI35: =CF35-CG35 -> 0 | CN35: =CK35-CL35 -> 0 | CS35: =CP35-CQ35 -> 0
A36: 27 | F36: 納車費・運送保管費 | J36: =SUM(P36,U36,Z36,AK36,AP36,AU36,BF36,BK36,BP36,CA36,CF36,CK36) -> 0 | K36: =SUM(Q36,V36,AA36,AL36,AQ36,AV36,BG36,BL36,BQ36,CB36,CG36,CL36) -> 0 | L36: =SUM(R36,W36,AB36,AM36,AR36,AW36,BH36,BM36,BR36,CC36,CH36,CM36) -> 0 | M36: =SUM(S36,X36,AC36,AN36,AS36,AX36,BI36,BN36,BS36,CD36,CI36,CN36) -> 0 | N36: =SUM(T36,Y36,AD36,AO36,AT36,AY36,BJ36,BO36,BT36,CE36,CJ36,CO36) -> 0 | S36: =P36-Q36 -> 0 | X36: =U36-V36 -> 0 | AD36: =AA36-AB36 -> 0 | AH36: =AE36-AF36 -> 0 | AN36: =AK36-AL36 -> 0 | AS36: =AP36-AQ36 -> 0 | AX36: =AU36-AV36 -> 0 | BC36: =AZ36-BA36 -> 0 | BI36: =BF36-BG36 -> 0 | BN36: =BK36-BL36 -> 0 | BS36: =BP36-BQ36 -> 0 | BX36: =BU36-BV36 -> 0 | CD36: =CA36-CB36 -> 0 | CI36: =CF36-CG36 -> 0 | CN36: =CK36-CL36 -> 0 | CS36: =CP36-CQ36 -> 0
A37: 28 | F37: 広告宣伝費 | J37: =SUM(P37,U37,Z37,AK37,AP37,AU37,BF37,BK37,BP37,CA37,CF37,CK37) -> 0 | K37: =SUM(Q37,V37,AA37,AL37,AQ37,AV37,BG37,BL37,BQ37,CB37,CG37,CL37) -> 0 | L37: =SUM(R37,W37,AB37,AM37,AR37,AW37,BH37,BM37,BR37,CC37,CH37,CM37) -> 0 | M37: =SUM(S37,X37,AC37,AN37,AS37,AX37,BI37,BN37,BS37,CD37,CI37,CN37) -> 0 | N37: =SUM(T37,Y37,AD37,AO37,AT37,AY37,BJ37,BO37,BT37,CE37,CJ37,CO37) -> 0 | S37: =P37-Q37 -> 0 | X37: =U37-V37 -> 0 | AD37: =AA37-AB37 -> 0 | AH37: =AE37-AF37 -> 0 | AN37: =AK37-AL37 -> 0 | AS37: =AP37-AQ37 -> 0 | AX37: =AU37-AV37 -> 0 | BC37: =AZ37-BA37 -> 0 | BI37: =BF37-BG37 -> 0 | BN37: =BK37-BL37 -> 0 | BS37: =BP37-BQ37 -> 0 | BX37: =BU37-BV37 -> 0 | CD37: =CA37-CB37 -> 0 | CI37: =CF37-CG37 -> 0 | CN37: =CK37-CL37 -> 0 | CS37: =CP37-CQ37 -> 0
A38: 29 | F38: デモカー・代車費 | J38: =SUM(P38,U38,Z38,AK38,AP38,AU38,BF38,BK38,BP38,CA38,CF38,CK38) -> 0 | K38: =SUM(Q38,V38,AA38,AL38,AQ38,AV38,BG38,BL38,BQ38,CB38,CG38,CL38) -> 0 | L38: =SUM(R38,W38,AB38,AM38,AR38,AW38,BH38,BM38,BR38,CC38,CH38,CM38) -> 0 | M38: =SUM(S38,X38,AC38,AN38,AS38,AX38,BI38,BN38,BS38,CD38,CI38,CN38) -> 0 | N38: =SUM(T38,Y38,AD38,AO38,AT38,AY38,BJ38,BO38,BT38,CE38,CJ38,CO38) -> 0 | S38: =P38-Q38 -> 0 | X38: =U38-V38 -> 0 | AD38: =AA38-AB38 -> 0 | AH38: =AE38-AF38 -> 0 | AN38: =AK38-AL38 -> 0 | AS38: =AP38-AQ38 -> 0 | AX38: =AU38-AV38 -> 0 | BC38: =AZ38-BA38 -> 0 | BI38: =BF38-BG38 -> 0 | BN38: =BK38-BL38 -> 0 | BS38: =BP38-BQ38 -> 0 | BX38: =BU38-BV38 -> 0 | CD38: =CA38-CB38 -> 0 | CI38: =CF38-CG38 -> 0 | CN38: =CK38-CL38 -> 0 | CS38: =CP38-CQ38 -> 0
A39: 30 | F39: 本部負担金 | J39: =SUM(P39,U39,Z39,AK39,AP39,AU39,BF39,BK39,BP39,CA39,CF39,CK39) -> 0 | K39: =SUM(Q39,V39,AA39,AL39,AQ39,AV39,BG39,BL39,BQ39,CB39,CG39,CL39) -> 0 | L39: =SUM(R39,W39,AB39,AM39,AR39,AW39,BH39,BM39,BR39,CC39,CH39,CM39) -> 0 | M39: =SUM(S39,X39,AC39,AN39,AS39,AX39,BI39,BN39,BS39,CD39,CI39,CN39) -> 0 | N39: =SUM(T39,Y39,AD39,AO39,AT39,AY39,BJ39,BO39,BT39,CE39,CJ39,CO39) -> 0 | S39: =P39-Q39 -> 0 | X39: =U39-V39 -> 0 | AD39: =AA39-AB39 -> 0 | AH39: =AE39-AF39 -> 0 | AN39: =AK39-AL39 -> 0 | AS39: =AP39-AQ39 -> 0 | AX39: =AU39-AV39 -> 0 | BC39: =AZ39-BA39 -> 0 | BI39: =BF39-BG39 -> 0 | BN39: =BK39-BL39 -> 0 | BS39: =BP39-BQ39 -> 0 | BX39: =BU39-BV39 -> 0 | CD39: =CA39-CB39 -> 0 | CI39: =CF39-CG39 -> 0 | CN39: =CK39-CL39 -> 0 | CS39: =CP39-CQ39 -> 0
A40: 31 | F40: 小計 | J40: =SUM(P40,U40,Z40,AK40,AP40,AU40,BF40,BK40,BP40,CA40,CF40,CK40) -> 0 | K40: =SUM(Q40,V40,AA40,AL40,AQ40,AV40,BG40,BL40,BQ40,CB40,CG40,CL40) -> 0 | L40: =SUM(R40,W40,AB40,AM40,AR40,AW40,BH40,BM40,BR40,CC40,CH40,CM40) -> 0 | M40: =SUM(S40,X40,AC40,AN40,AS40,AX40,BI40,BN40,BS40,CD40,CI40,CN40) -> 0 | N40: =SUM(T40,Y40,AD40,AO40,AT40,AY40,BJ40,BO40,BT40,CE40,CJ40,CO40) -> 0 | S40: =P40-Q40 -> 0 | X40: =U40-V40 -> 0 | AD40: =AA40-AB40 -> 0 | AH40: =AE40-AF40 -> 0 | AN40: =AK40-AL40 -> 0 | AS40: =AP40-AQ40 -> 0 | AX40: =AU40-AV40 -> 0 | BC40: =AZ40-BA40 -> 0 | BI40: =BF40-BG40 -> 0 | BN40: =BK40-BL40 -> 0 | BS40: =BP40-BQ40 -> 0 | BX40: =BU40-BV40 -> 0 | CD40: =CA40-CB40 -> 0 | CI40: =CF40-CG40 -> 0 | CN40: =CK40-CL40 -> 0 | CS40: =CP40-CQ40 -> 0
A41: 32 | E41: 新車限界利益 | J41: =SUM(P41,U41,Z41,AK41,AP41,AU41,BF41,BK41,BP41,CA41,CF41,CK41) -> 0 | K41: =SUM(Q41,V41,AA41,AL41,AQ41,AV41,BG41,BL41,BQ41,CB41,CG41,CL41) -> 0 | L41: =SUM(R41,W41,AB41,AM41,AR41,AW41,BH41,BM41,BR41,CC41,CH41,CM41) -> 0 | M41: =SUM(S41,X41,AC41,AN41,AS41,AX41,BI41,BN41,BS41,CD41,CI41,CN41) -> 0 | N41: =SUM(T41,Y41,AD41,AO41,AT41,AY41,BJ41,BO41,BT41,CE41,CJ41,CO41) -> 0 | S41: =P41-Q41 -> 0 | X41: =U41-V41 -> 0 | AD41: =AA41-AB41 -> 0 | AH41: =AE41-AF41 -> 0 | AN41: =AK41-AL41 -> 0 | AS41: =AP41-AQ41 -> 0 | AX41: =AU41-AV41 -> 0 | BC41: =AZ41-BA41 -> 0 | BI41: =BF41-BG41 -> 0 | BN41: =BK41-BL41 -> 0 | BS41: =BP41-BQ41 -> 0 | BX41: =BU41-BV41 -> 0 | CD41: =CA41-CB41 -> 0 | CI41: =CF41-CG41 -> 0 | CN41: =CK41-CL41 -> 0 | CS41: =CP41-CQ41 -> 0
A42: 33 | D42: 中古車 | E42: 直売 | F42: 直売台数 | J42: =SUM(P42,U42,Z42,AK42,AP42,AU42,BF42,BK42,BP42,CA42,CF42,CK42) -> 0 | K42: =SUM(Q42,V42,AA42,AL42,AQ42,AV42,BG42,BL42,BQ42,CB42,CG42,CL42) -> 0 | L42: =SUM(R42,W42,AB42,AM42,AR42,AW42,BH42,BM42,BR42,CC42,CH42,CM42) -> 0 | M42: =SUM(S42,X42,AC42,AN42,AS42,AX42,BI42,BN42,BS42,CD42,CI42,CN42) -> 0 | N42: =SUM(T42,Y42,AD42,AO42,AT42,AY42,BJ42,BO42,BT42,CE42,CJ42,CO42) -> 0 | S42: =P42-Q42 -> 0 | X42: =U42-V42 -> 0 | AD42: =AA42-AB42 -> 0 | AH42: =AE42-AF42 -> 0 | AN42: =AK42-AL42 -> 0 | AS42: =AP42-AQ42 -> 0 | AX42: =AU42-AV42 -> 0 | BC42: =AZ42-BA42 -> 0 | BI42: =BF42-BG42 -> 0 | BN42: =BK42-BL42 -> 0 | BS42: =BP42-BQ42 -> 0 | BX42: =BU42-BV42 -> 0 | CD42: =CA42-CB42 -> 0 | CI42: =CF42-CG42 -> 0 | CN42: =CK42-CL42 -> 0 | CS42: =CP42-CQ42 -> 0
A43: 34 | F43: 売上金額 | J43: =SUM(P43,U43,Z43,AK43,AP43,AU43,BF43,BK43,BP43,CA43,CF43,CK43) -> 0 | K43: =SUM(Q43,V43,AA43,AL43,AQ43,AV43,BG43,BL43,BQ43,CB43,CG43,CL43) -> 0 | L43: =SUM(R43,W43,AB43,AM43,AR43,AW43,BH43,BM43,BR43,CC43,CH43,CM43) -> 0 | M43: =SUM(S43,X43,AC43,AN43,AS43,AX43,BI43,BN43,BS43,CD43,CI43,CN43) -> 0 | N43: =SUM(T43,Y43,AD43,AO43,AT43,AY43,BJ43,BO43,BT43,CE43,CJ43,CO43) -> 0 | S43: =P43-Q43 -> 0 | X43: =U43-V43 -> 0 | AD43: =AA43-AB43 -> 0 | AH43: =AE43-AF43 -> 0 | AN43: =AK43-AL43 -> 0 | AS43: =AP43-AQ43 -> 0 | AX43: =AU43-AV43 -> 0 | BC43: =AZ43-BA43 -> 0 | BI43: =BF43-BG43 -> 0 | BN43: =BK43-BL43 -> 0 | BS43: =BP43-BQ43 -> 0 | BX43: =BU43-BV43 -> 0 | CD43: =CA43-CB43 -> 0 | CI43: =CF43-CG43 -> 0 | CN43: =CK43-CL43 -> 0 | CS43: =CP43-CQ43 -> 0
A44: 35 | F44: 車両本体利益 | J44: =SUM(P44,U44,Z44,AK44,AP44,AU44,BF44,BK44,BP44,CA44,CF44,CK44) -> 0 | K44: =SUM(Q44,V44,AA44,AL44,AQ44,AV44,BG44,BL44,BQ44,CB44,CG44,CL44) -> 0 | L44: =SUM(R44,W44,AB44,AM44,AR44,AW44,BH44,BM44,BR44,CC44,CH44,CM44) -> 0 | M44: =SUM(S44,X44,AC44,AN44,AS44,AX44,BI44,BN44,BS44,CD44,CI44,CN44) -> 0 | N44: =SUM(T44,Y44,AD44,AO44,AT44,AY44,BJ44,BO44,BT44,CE44,CJ44,CO44) -> 0 | S44: =P44-Q44 -> 0 | X44: =U44-V44 -> 0 | AD44: =AA44-AB44 -> 0 | AH44: =AE44-AF44 -> 0 | AN44: =AK44-AL44 -> 0 | AS44: =AP44-AQ44 -> 0 | AX44: =AU44-AV44 -> 0 | BC44: =AZ44-BA44 -> 0 | BI44: =BF44-BG44 -> 0 | BN44: =BK44-BL44 -> 0 | BS44: =BP44-BQ44 -> 0 | BX44: =BU44-BV44 -> 0 | CD44: =CA44-CB44 -> 0 | CI44: =CF44-CG44 -> 0 | CN44: =CK44-CL44 -> 0 | CS44: =CP44-CQ44 -> 0
A45: 36 | F45: 車両収入手数料 | J45: =SUM(P45,U45,Z45,AK45,AP45,AU45,BF45,BK45,BP45,CA45,CF45,CK45) -> 0 | K45: =SUM(Q45,V45,AA45,AL45,AQ45,AV45,BG45,BL45,BQ45,CB45,CG45,CL45) -> 0 | L45: =SUM(R45,W45,AB45,AM45,AR45,AW45,BH45,BM45,BR45,CC45,CH45,CM45) -> 0 | M45: =SUM(S45,X45,AC45,AN45,AS45,AX45,BI45,BN45,BS45,CD45,CI45,CN45) -> 0 | N45: =SUM(T45,Y45,AD45,AO45,AT45,AY45,BJ45,BO45,BT45,CE45,CJ45,CO45) -> 0 | S45: =P45-Q45 -> 0 | X45: =U45-V45 -> 0 | AD45: =AA45-AB45 -> 0 | AH45: =AE45-AF45 -> 0 | AN45: =AK45-AL45 -> 0 | AS45: =AP45-AQ45 -> 0 | AX45: =AU45-AV45 -> 0 | BC45: =AZ45-BA45 -> 0 | BI45: =BF45-BG45 -> 0 | BN45: =BK45-BL45 -> 0 | BS45: =BP45-BQ45 -> 0 | BX45: =BU45-BV45 -> 0 | CD45: =CA45-CB45 -> 0 | CI45: =CF45-CG45 -> 0 | CN45: =CK45-CL45 -> 0 | CS45: =CP45-CQ45 -> 0
A46: 37 | F46: 登録収入手数料 | J46: =SUM(P46,U46,Z46,AK46,AP46,AU46,BF46,BK46,BP46,CA46,CF46,CK46) -> 0 | K46: =SUM(Q46,V46,AA46,AL46,AQ46,AV46,BG46,BL46,BQ46,CB46,CG46,CL46) -> 0 | L46: =SUM(R46,W46,AB46,AM46,AR46,AW46,BH46,BM46,BR46,CC46,CH46,CM46) -> 0 | M46: =SUM(S46,X46,AC46,AN46,AS46,AX46,BI46,BN46,BS46,CD46,CI46,CN46) -> 0 | N46: =SUM(T46,Y46,AD46,AO46,AT46,AY46,BJ46,BO46,BT46,CE46,CJ46,CO46) -> 0 | S46: =P46-Q46 -> 0 | X46: =U46-V46 -> 0 | AD46: =AA46-AB46 -> 0 | AH46: =AE46-AF46 -> 0 | AN46: =AK46-AL46 -> 0 | AS46: =AP46-AQ46 -> 0 | AX46: =AU46-AV46 -> 0 | BC46: =AZ46-BA46 -> 0 | BI46: =BF46-BG46 -> 0 | BN46: =BK46-BL46 -> 0 | BS46: =BP46-BQ46 -> 0 | BX46: =BU46-BV46 -> 0 | CD46: =CA46-CB46 -> 0 | CI46: =CF46-CG46 -> 0 | CN46: =CK46-CL46 -> 0 | CS46: =CP46-CQ46 -> 0
A47: 38 | F47: クレジット利益 | J47: =SUM(P47,U47,Z47,AK47,AP47,AU47,BF47,BK47,BP47,CA47,CF47,CK47) -> 0 | K47: =SUM(Q47,V47,AA47,AL47,AQ47,AV47,BG47,BL47,BQ47,CB47,CG47,CL47) -> 0 | L47: =SUM(R47,W47,AB47,AM47,AR47,AW47,BH47,BM47,BR47,CC47,CH47,CM47) -> 0 | M47: =SUM(S47,X47,AC47,AN47,AS47,AX47,BI47,BN47,BS47,CD47,CI47,CN47) -> 0 | N47: =SUM(T47,Y47,AD47,AO47,AT47,AY47,BJ47,BO47,BT47,CE47,CJ47,CO47) -> 0 | S47: =P47-Q47 -> 0 | X47: =U47-V47 -> 0 | AD47: =AA47-AB47 -> 0 | AH47: =AE47-AF47 -> 0 | AN47: =AK47-AL47 -> 0 | AS47: =AP47-AQ47 -> 0 | AX47: =AU47-AV47 -> 0 | BC47: =AZ47-BA47 -> 0 | BI47: =BF47-BG47 -> 0 | BN47: =BK47-BL47 -> 0 | BS47: =BP47-BQ47 -> 0 | BX47: =BU47-BV47 -> 0 | CD47: =CA47-CB47 -> 0 | CI47: =CF47-CG47 -> 0 | CN47: =CK47-CL47 -> 0 | CS47: =CP47-CQ47 -> 0
A48: 39 | F48: 直売総粗利 | J48: =SUM(P48,U48,Z48,AK48,AP48,AU48,BF48,BK48,BP48,CA48,CF48,CK48) -> 0 | K48: =SUM(Q48,V48,AA48,AL48,AQ48,AV48,BG48,BL48,BQ48,CB48,CG48,CL48) -> 0 | L48: =SUM(R48,W48,AB48,AM48,AR48,AW48,BH48,BM48,BR48,CC48,CH48,CM48) -> 0 | M48: =SUM(S48,X48,AC48,AN48,AS48,AX48,BI48,BN48,BS48,CD48,CI48,CN48) -> 0 | N48: =SUM(T48,Y48,AD48,AO48,AT48,AY48,BJ48,BO48,BT48,CE48,CJ48,CO48) -> 0 | S48: =P48-Q48 -> 0 | X48: =U48-V48 -> 0 | AD48: =AA48-AB48 -> 0 | AH48: =AE48-AF48 -> 0 | AN48: =AK48-AL48 -> 0 | AS48: =AP48-AQ48 -> 0 | AX48: =AU48-AV48 -> 0 | BC48: =AZ48-BA48 -> 0 | BI48: =BF48-BG48 -> 0 | BN48: =BK48-BL48 -> 0 | BS48: =BP48-BQ48 -> 0 | BX48: =BU48-BV48 -> 0 | CD48: =CA48-CB48 -> 0 | CI48: =CF48-CG48 -> 0 | CN48: =CK48-CL48 -> 0 | CS48: =CP48-CQ48 -> 0
A49: 40 | E49: 業売 | F49: 業売台数 | J49: =SUM(P49,U49,Z49,AK49,AP49,AU49,BF49,BK49,BP49,CA49,CF49,CK49) -> 0 | K49: =SUM(Q49,V49,AA49,AL49,AQ49,AV49,BG49,BL49,BQ49,CB49,CG49,CL49) -> 0 | L49: =SUM(R49,W49,AB49,AM49,AR49,AW49,BH49,BM49,BR49,CC49,CH49,CM49) -> 0 | M49: =SUM(S49,X49,AC49,AN49,AS49,AX49,BI49,BN49,BS49,CD49,CI49,CN49) -> 0 | N49: =SUM(T49,Y49,AD49,AO49,AT49,AY49,BJ49,BO49,BT49,CE49,CJ49,CO49) -> 0 | S49: =P49-Q49 -> 0 | X49: =U49-V49 -> 0 | AD49: =AA49-AB49 -> 0 | AH49: =AE49-AF49 -> 0 | AN49: =AK49-AL49 -> 0 | AS49: =AP49-AQ49 -> 0 | AX49: =AU49-AV49 -> 0 | BC49: =AZ49-BA49 -> 0 | BI49: =BF49-BG49 -> 0 | BN49: =BK49-BL49 -> 0 | BS49: =BP49-BQ49 -> 0 | BX49: =BU49-BV49 -> 0 | CD49: =CA49-CB49 -> 0 | CI49: =CF49-CG49 -> 0 | CN49: =CK49-CL49 -> 0 | CS49: =CP49-CQ49 -> 0
A50: 41 | F50: 業売売上 | J50: =SUM(P50,U50,Z50,AK50,AP50,AU50,BF50,BK50,BP50,CA50,CF50,CK50) -> 0 | K50: =SUM(Q50,V50,AA50,AL50,AQ50,AV50,BG50,BL50,BQ50,CB50,CG50,CL50) -> 0 | L50: =SUM(R50,W50,AB50,AM50,AR50,AW50,BH50,BM50,BR50,CC50,CH50,CM50) -> 0 | M50: =SUM(S50,X50,AC50,AN50,AS50,AX50,BI50,BN50,BS50,CD50,CI50,CN50) -> 0 | N50: =SUM(T50,Y50,AD50,AO50,AT50,AY50,BJ50,BO50,BT50,CE50,CJ50,CO50) -> 0 | S50: =P50-Q50 -> 0 | X50: =U50-V50 -> 0 | AD50: =AA50-AB50 -> 0 | AH50: =AE50-AF50 -> 0 | AN50: =AK50-AL50 -> 0 | AS50: =AP50-AQ50 -> 0 | AX50: =AU50-AV50 -> 0 | BC50: =AZ50-BA50 -> 0 | BI50: =BF50-BG50 -> 0 | BN50: =BK50-BL50 -> 0 | BS50: =BP50-BQ50 -> 0 | BX50: =BU50-BV50 -> 0 | CD50: =CA50-CB50 -> 0 | CI50: =CF50-CG50 -> 0 | CN50: =CK50-CL50 -> 0 | CS50: =CP50-CQ50 -> 0
A51: 42 | F51: 業売放出台数 | J51: =SUM(P51,U51,Z51,AK51,AP51,AU51,BF51,BK51,BP51,CA51,CF51,CK51) -> 0 | K51: =SUM(Q51,V51,AA51,AL51,AQ51,AV51,BG51,BL51,BQ51,CB51,CG51,CL51) -> 0 | L51: =SUM(R51,W51,AB51,AM51,AR51,AW51,BH51,BM51,BR51,CC51,CH51,CM51) -> 0 | M51: =SUM(S51,X51,AC51,AN51,AS51,AX51,BI51,BN51,BS51,CD51,CI51,CN51) -> 0 | N51: =SUM(T51,Y51,AD51,AO51,AT51,AY51,BJ51,BO51,BT51,CE51,CJ51,CO51) -> 0 | S51: =P51-Q51 -> 0 | X51: =U51-V51 -> 0 | AD51: =AA51-AB51 -> 0 | AH51: =AE51-AF51 -> 0 | AN51: =AK51-AL51 -> 0 | AS51: =AP51-AQ51 -> 0 | AX51: =AU51-AV51 -> 0 | BC51: =AZ51-BA51 -> 0 | BI51: =BF51-BG51 -> 0 | BN51: =BK51-BL51 -> 0 | BS51: =BP51-BQ51 -> 0 | BX51: =BU51-BV51 -> 0 | CD51: =CA51-CB51 -> 0 | CI51: =CF51-CG51 -> 0 | CN51: =CK51-CL51 -> 0 | CS51: =CP51-CQ51 -> 0
A52: 43 | F52: 業売放出売上 | J52: =SUM(P52,U52,Z52,AK52,AP52,AU52,BF52,BK52,BP52,CA52,CF52,CK52) -> 0 | K52: =SUM(Q52,V52,AA52,AL52,AQ52,AV52,BG52,BL52,BQ52,CB52,CG52,CL52) -> 0 | L52: =SUM(R52,W52,AB52,AM52,AR52,AW52,BH52,BM52,BR52,CC52,CH52,CM52) -> 0 | M52: =SUM(S52,X52,AC52,AN52,AS52,AX52,BI52,BN52,BS52,CD52,CI52,CN52) -> 0 | N52: =SUM(T52,Y52,AD52,AO52,AT52,AY52,BJ52,BO52,BT52,CE52,CJ52,CO52) -> 0 | S52: =P52-Q52 -> 0 | X52: =U52-V52 -> 0 | AD52: =AA52-AB52 -> 0 | AH52: =AE52-AF52 -> 0 | AN52: =AK52-AL52 -> 0 | AS52: =AP52-AQ52 -> 0 | AX52: =AU52-AV52 -> 0 | BC52: =AZ52-BA52 -> 0 | BI52: =BF52-BG52 -> 0 | BN52: =BK52-BL52 -> 0 | BS52: =BP52-BQ52 -> 0 | BX52: =BU52-BV52 -> 0 | CD52: =CA52-CB52 -> 0 | CI52: =CF52-CG52 -> 0 | CN52: =CK52-CL52 -> 0 | CS52: =CP52-CQ52 -> 0
A53: 44 | F53: 業売スクラップ台数 | J53: =SUM(P53,U53,Z53,AK53,AP53,AU53,BF53,BK53,BP53,CA53,CF53,CK53) -> 0 | K53: =SUM(Q53,V53,AA53,AL53,AQ53,AV53,BG53,BL53,BQ53,CB53,CG53,CL53) -> 0 | L53: =SUM(R53,W53,AB53,AM53,AR53,AW53,BH53,BM53,BR53,CC53,CH53,CM53) -> 0 | M53: =SUM(S53,X53,AC53,AN53,AS53,AX53,BI53,BN53,BS53,CD53,CI53,CN53) -> 0 | N53: =SUM(T53,Y53,AD53,AO53,AT53,AY53,BJ53,BO53,BT53,CE53,CJ53,CO53) -> 0 | S53: =P53-Q53 -> 0 | X53: =U53-V53 -> 0 | AD53: =AA53-AB53 -> 0 | AH53: =AE53-AF53 -> 0 | AN53: =AK53-AL53 -> 0 | AS53: =AP53-AQ53 -> 0 | AX53: =AU53-AV53 -> 0 | BC53: =AZ53-BA53 -> 0 | BI53: =BF53-BG53 -> 0 | BN53: =BK53-BL53 -> 0 | BS53: =BP53-BQ53 -> 0 | BX53: =BU53-BV53 -> 0 | CD53: =CA53-CB53 -> 0 | CI53: =CF53-CG53 -> 0 | CN53: =CK53-CL53 -> 0 | CS53: =CP53-CQ53 -> 0
A54: 45 | F54: 業売スクラップ売上 | J54: =SUM(P54,U54,Z54,AK54,AP54,AU54,BF54,BK54,BP54,CA54,CF54,CK54) -> 0 | K54: =SUM(Q54,V54,AA54,AL54,AQ54,AV54,BG54,BL54,BQ54,CB54,CG54,CL54) -> 0 | L54: =SUM(R54,W54,AB54,AM54,AR54,AW54,BH54,BM54,BR54,CC54,CH54,CM54) -> 0 | M54: =SUM(S54,X54,AC54,AN54,AS54,AX54,BI54,BN54,BS54,CD54,CI54,CN54) -> 0 | N54: =SUM(T54,Y54,AD54,AO54,AT54,AY54,BJ54,BO54,BT54,CE54,CJ54,CO54) -> 0 | S54: =P54-Q54 -> 0 | X54: =U54-V54 -> 0 | AD54: =AA54-AB54 -> 0 | AH54: =AE54-AF54 -> 0 | AN54: =AK54-AL54 -> 0 | AS54: =AP54-AQ54 -> 0 | AX54: =AU54-AV54 -> 0 | BC54: =AZ54-BA54 -> 0 | BI54: =BF54-BG54 -> 0 | BN54: =BK54-BL54 -> 0 | BS54: =BP54-BQ54 -> 0 | BX54: =BU54-BV54 -> 0 | CD54: =CA54-CB54 -> 0 | CI54: =CF54-CG54 -> 0 | CN54: =CK54-CL54 -> 0 | CS54: =CP54-CQ54 -> 0
A55: 46 | F55: 業販粗利益 | J55: =SUM(P55,U55,Z55,AK55,AP55,AU55,BF55,BK55,BP55,CA55,CF55,CK55) -> 0 | K55: =SUM(Q55,V55,AA55,AL55,AQ55,AV55,BG55,BL55,BQ55,CB55,CG55,CL55) -> 0 | L55: =SUM(R55,W55,AB55,AM55,AR55,AW55,BH55,BM55,BR55,CC55,CH55,CM55) -> 0 | M55: =SUM(S55,X55,AC55,AN55,AS55,AX55,BI55,BN55,BS55,CD55,CI55,CN55) -> 0 | N55: =SUM(T55,Y55,AD55,AO55,AT55,AY55,BJ55,BO55,BT55,CE55,CJ55,CO55) -> 0 | S55: =P55-Q55 -> 0 | X55: =U55-V55 -> 0 | AD55: =AA55-AB55 -> 0 | AH55: =AE55-AF55 -> 0 | AN55: =AK55-AL55 -> 0 | AS55: =AP55-AQ55 -> 0 | AX55: =AU55-AV55 -> 0 | BC55: =AZ55-BA55 -> 0 | BI55: =BF55-BG55 -> 0 | BN55: =BK55-BL55 -> 0 | BS55: =BP55-BQ55 -> 0 | BX55: =BU55-BV55 -> 0 | CD55: =CA55-CB55 -> 0 | CI55: =CF55-CG55 -> 0 | CN55: =CK55-CL55 -> 0 | CS55: =CP55-CQ55 -> 0
A56: 47 | E56: 台数合計 | J56: =SUM(P56,U56,Z56,AK56,AP56,AU56,BF56,BK56,BP56,CA56,CF56,CK56) -> 0 | K56: =SUM(Q56,V56,AA56,AL56,AQ56,AV56,BG56,BL56,BQ56,CB56,CG56,CL56) -> 0 | L56: =SUM(R56,W56,AB56,AM56,AR56,AW56,BH56,BM56,BR56,CC56,CH56,CM56) -> 0 | M56: =SUM(S56,X56,AC56,AN56,AS56,AX56,BI56,BN56,BS56,CD56,CI56,CN56) -> 0 | N56: =SUM(T56,Y56,AD56,AO56,AT56,AY56,BJ56,BO56,BT56,CE56,CJ56,CO56) -> 0 | S56: =P56-Q56 -> 0 | X56: =U56-V56 -> 0 | AD56: =AA56-AB56 -> 0 | AH56: =AE56-AF56 -> 0 | AN56: =AK56-AL56 -> 0 | AS56: =AP56-AQ56 -> 0 | AX56: =AU56-AV56 -> 0 | BC56: =AZ56-BA56 -> 0 | BI56: =BF56-BG56 -> 0 | BN56: =BK56-BL56 -> 0 | BS56: =BP56-BQ56 -> 0 | BX56: =BU56-BV56 -> 0 | CD56: =CA56-CB56 -> 0 | CI56: =CF56-CG56 -> 0 | CN56: =CK56-CL56 -> 0 | CS56: =CP56-CQ56 -> 0
A57: 48 | E57: 粗利益計 | J57: =SUM(P57,U57,Z57,AK57,AP57,AU57,BF57,BK57,BP57,CA57,CF57,CK57) -> 0 | K57: =SUM(Q57,V57,AA57,AL57,AQ57,AV57,BG57,BL57,BQ57,CB57,CG57,CL57) -> 0 | L57: =SUM(R57,W57,AB57,AM57,AR57,AW57,BH57,BM57,BR57,CC57,CH57,CM57) -> 0 | M57: =SUM(S57,X57,AC57,AN57,AS57,AX57,BI57,BN57,BS57,CD57,CI57,CN57) -> 0 | N57: =SUM(T57,Y57,AD57,AO57,AT57,AY57,BJ57,BO57,BT57,CE57,CJ57,CO57) -> 0 | S57: =P57-Q57 -> 0 | X57: =U57-V57 -> 0 | AD57: =AA57-AB57 -> 0 | AH57: =AE57-AF57 -> 0 | AN57: =AK57-AL57 -> 0 | AS57: =AP57-AQ57 -> 0 | AX57: =AU57-AV57 -> 0 | BC57: =AZ57-BA57 -> 0 | BI57: =BF57-BG57 -> 0 | BN57: =BK57-BL57 -> 0 | BS57: =BP57-BQ57 -> 0 | BX57: =BU57-BV57 -> 0 | CD57: =CA57-CB57 -> 0 | CI57: =CF57-CG57 -> 0 | CN57: =CK57-CL57 -> 0 | CS57: =CP57-CQ57 -> 0
A58: 49 | E58: 車両収入手数料計 | J58: =SUM(P58,U58,Z58,AK58,AP58,AU58,BF58,BK58,BP58,CA58,CF58,CK58) -> 0 | K58: =SUM(Q58,V58,AA58,AL58,AQ58,AV58,BG58,BL58,BQ58,CB58,CG58,CL58) -> 0 | L58: =SUM(R58,W58,AB58,AM58,AR58,AW58,BH58,BM58,BR58,CC58,CH58,CM58) -> 0 | M58: =SUM(S58,X58,AC58,AN58,AS58,AX58,BI58,BN58,BS58,CD58,CI58,CN58) -> 0 | N58: =SUM(T58,Y58,AD58,AO58,AT58,AY58,BJ58,BO58,BT58,CE58,CJ58,CO58) -> 0 | S58: =P58-Q58 -> 0 | X58: =U58-V58 -> 0 | AD58: =AA58-AB58 -> 0 | AH58: =AE58-AF58 -> 0 | AN58: =AK58-AL58 -> 0 | AS58: =AP58-AQ58 -> 0 | AX58: =AU58-AV58 -> 0 | BC58: =AZ58-BA58 -> 0 | BI58: =BF58-BG58 -> 0 | BN58: =BK58-BL58 -> 0 | BS58: =BP58-BQ58 -> 0 | BX58: =BU58-BV58 -> 0 | CD58: =CA58-CB58 -> 0 | CI58: =CF58-CG58 -> 0 | CN58: =CK58-CL58 -> 0 | CS58: =CP58-CQ58 -> 0
A59: 50 | E59: 登録収入手数料計 | J59: =SUM(P59,U59,Z59,AK59,AP59,AU59,BF59,BK59,BP59,CA59,CF59,CK59) -> 0 | K59: =SUM(Q59,V59,AA59,AL59,AQ59,AV59,BG59,BL59,BQ59,CB59,CG59,CL59) -> 0 | L59: =SUM(R59,W59,AB59,AM59,AR59,AW59,BH59,BM59,BR59,CC59,CH59,CM59) -> 0 | M59: =SUM(S59,X59,AC59,AN59,AS59,AX59,BI59,BN59,BS59,CD59,CI59,CN59) -> 0 | N59: =SUM(T59,Y59,AD59,AO59,AT59,AY59,BJ59,BO59,BT59,CE59,CJ59,CO59) -> 0 | S59: =P59-Q59 -> 0 | X59: =U59-V59 -> 0 | AD59: =AA59-AB59 -> 0 | AH59: =AE59-AF59 -> 0 | AN59: =AK59-AL59 -> 0 | AS59: =AP59-AQ59 -> 0 | AX59: =AU59-AV59 -> 0 | BC59: =AZ59-BA59 -> 0 | BI59: =BF59-BG59 -> 0 | BN59: =BK59-BL59 -> 0 | BS59: =BP59-BQ59 -> 0 | BX59: =BU59-BV59 -> 0 | CD59: =CA59-CB59 -> 0 | CI59: =CF59-CG59 -> 0 | CN59: =CK59-CL59 -> 0 | CS59: =CP59-CQ59 -> 0
A60: 51 | E60: クレジット利益計 | J60: =SUM(P60,U60,Z60,AK60,AP60,AU60,BF60,BK60,BP60,CA60,CF60,CK60) -> 0 | K60: =SUM(Q60,V60,AA60,AL60,AQ60,AV60,BG60,BL60,BQ60,CB60,CG60,CL60) -> 0 | L60: =SUM(R60,W60,AB60,AM60,AR60,AW60,BH60,BM60,BR60,CC60,CH60,CM60) -> 0 | M60: =SUM(S60,X60,AC60,AN60,AS60,AX60,BI60,BN60,BS60,CD60,CI60,CN60) -> 0 | N60: =SUM(T60,Y60,AD60,AO60,AT60,AY60,BJ60,BO60,BT60,CE60,CJ60,CO60) -> 0 | S60: =P60-Q60 -> 0 | X60: =U60-V60 -> 0 | AD60: =AA60-AB60 -> 0 | AH60: =AE60-AF60 -> 0 | AN60: =AK60-AL60 -> 0 | AS60: =AP60-AQ60 -> 0 | AX60: =AU60-AV60 -> 0 | BC60: =AZ60-BA60 -> 0 | BI60: =BF60-BG60 -> 0 | BN60: =BK60-BL60 -> 0 | BS60: =BP60-BQ60 -> 0 | BX60: =BU60-BV60 -> 0 | CD60: =CA60-CB60 -> 0 | CI60: =CF60-CG60 -> 0 | CN60: =CK60-CL60 -> 0 | CS60: =CP60-CQ60 -> 0
A61: 52 | E61: 再生員給与 | J61: =SUM(P61,U61,Z61,AK61,AP61,AU61,BF61,BK61,BP61,CA61,CF61,CK61) -> 0 | K61: =SUM(Q61,V61,AA61,AL61,AQ61,AV61,BG61,BL61,BQ61,CB61,CG61,CL61) -> 0 | L61: =SUM(R61,W61,AB61,AM61,AR61,AW61,BH61,BM61,BR61,CC61,CH61,CM61) -> 0 | M61: =SUM(S61,X61,AC61,AN61,AS61,AX61,BI61,BN61,BS61,CD61,CI61,CN61) -> 0 | N61: =SUM(T61,Y61,AD61,AO61,AT61,AY61,BJ61,BO61,BT61,CE61,CJ61,CO61) -> 0 | S61: =P61-Q61 -> 0 | X61: =U61-V61 -> 0 | AD61: =AA61-AB61 -> 0 | AH61: =AE61-AF61 -> 0 | AN61: =AK61-AL61 -> 0 | AS61: =AP61-AQ61 -> 0 | AX61: =AU61-AV61 -> 0 | BC61: =AZ61-BA61 -> 0 | BI61: =BF61-BG61 -> 0 | BN61: =BK61-BL61 -> 0 | BS61: =BP61-BQ61 -> 0 | BX61: =BU61-BV61 -> 0 | CD61: =CA61-CB61 -> 0 | CI61: =CF61-CG61 -> 0 | CN61: =CK61-CL61 -> 0 | CS61: =CP61-CQ61 -> 0
A62: 53 | E62: 中古車粗利合計 | J62: =SUM(P62,U62,Z62,AK62,AP62,AU62,BF62,BK62,BP62,CA62,CF62,CK62) -> 0 | K62: =SUM(Q62,V62,AA62,AL62,AQ62,AV62,BG62,BL62,BQ62,CB62,CG62,CL62) -> 0 | L62: =SUM(R62,W62,AB62,AM62,AR62,AW62,BH62,BM62,BR62,CC62,CH62,CM62) -> 0 | M62: =SUM(S62,X62,AC62,AN62,AS62,AX62,BI62,BN62,BS62,CD62,CI62,CN62) -> 0 | N62: =SUM(T62,Y62,AD62,AO62,AT62,AY62,BJ62,BO62,BT62,CE62,CJ62,CO62) -> 0 | S62: =P62-Q62 -> 0 | X62: =U62-V62 -> 0 | AD62: =AA62-AB62 -> 0 | AH62: =AE62-AF62 -> 0 | AN62: =AK62-AL62 -> 0 | AS62: =AP62-AQ62 -> 0 | AX62: =AU62-AV62 -> 0 | BC62: =AZ62-BA62 -> 0 | BI62: =BF62-BG62 -> 0 | BN62: =BK62-BL62 -> 0 | BS62: =BP62-BQ62 -> 0 | BX62: =BU62-BV62 -> 0 | CD62: =CA62-CB62 -> 0 | CI62: =CF62-CG62 -> 0 | CN62: =CK62-CL62 -> 0 | CS62: =CP62-CQ62 -> 0
A63: 54 | E63: 販売費 | F63: 販手・サービス・雑費 | J63: =SUM(P63,U63,Z63,AK63,AP63,AU63,BF63,BK63,BP63,CA63,CF63,CK63) -> 0 | K63: =SUM(Q63,V63,AA63,AL63,AQ63,AV63,BG63,BL63,BQ63,CB63,CG63,CL63) -> 0 | L63: =SUM(R63,W63,AB63,AM63,AR63,AW63,BH63,BM63,BR63,CC63,CH63,CM63) -> 0 | M63: =SUM(S63,X63,AC63,AN63,AS63,AX63,BI63,BN63,BS63,CD63,CI63,CN63) -> 0 | N63: =SUM(T63,Y63,AD63,AO63,AT63,AY63,BJ63,BO63,BT63,CE63,CJ63,CO63) -> 0 | S63: =P63-Q63 -> 0 | X63: =U63-V63 -> 0 | AD63: =AA63-AB63 -> 0 | AH63: =AE63-AF63 -> 0 | AN63: =AK63-AL63 -> 0 | AS63: =AP63-AQ63 -> 0 | AX63: =AU63-AV63 -> 0 | BC63: =AZ63-BA63 -> 0 | BI63: =BF63-BG63 -> 0 | BN63: =BK63-BL63 -> 0 | BS63: =BP63-BQ63 -> 0 | BX63: =BU63-BV63 -> 0 | CD63: =CA63-CB63 -> 0 | CI63: =CF63-CG63 -> 0 | CN63: =CK63-CL63 -> 0 | CS63: =CP63-CQ63 -> 0
A64: 55 | F64: 納車費・運送保管費 | J64: =SUM(P64,U64,Z64,AK64,AP64,AU64,BF64,BK64,BP64,CA64,CF64,CK64) -> 0 | K64: =SUM(Q64,V64,AA64,AL64,AQ64,AV64,BG64,BL64,BQ64,CB64,CG64,CL64) -> 0 | L64: =SUM(R64,W64,AB64,AM64,AR64,AW64,BH64,BM64,BR64,CC64,CH64,CM64) -> 0 | M64: =SUM(S64,X64,AC64,AN64,AS64,AX64,BI64,BN64,BS64,CD64,CI64,CN64) -> 0 | N64: =SUM(T64,Y64,AD64,AO64,AT64,AY64,BJ64,BO64,BT64,CE64,CJ64,CO64) -> 0 | S64: =P64-Q64 -> 0 | X64: =U64-V64 -> 0 | AD64: =AA64-AB64 -> 0 | AH64: =AE64-AF64 -> 0 | AN64: =AK64-AL64 -> 0 | AS64: =AP64-AQ64 -> 0 | AX64: =AU64-AV64 -> 0 | BC64: =AZ64-BA64 -> 0 | BI64: =BF64-BG64 -> 0 | BN64: =BK64-BL64 -> 0 | BS64: =BP64-BQ64 -> 0 | BX64: =BU64-BV64 -> 0 | CD64: =CA64-CB64 -> 0 | CI64: =CF64-CG64 -> 0 | CN64: =CK64-CL64 -> 0 | CS64: =CP64-CQ64 -> 0
A65: 56 | F65: 広告宣伝費 | J65: =SUM(P65,U65,Z65,AK65,AP65,AU65,BF65,BK65,BP65,CA65,CF65,CK65) -> 0 | K65: =SUM(Q65,V65,AA65,AL65,AQ65,AV65,BG65,BL65,BQ65,CB65,CG65,CL65) -> 0 | L65: =SUM(R65,W65,AB65,AM65,AR65,AW65,BH65,BM65,BR65,CC65,CH65,CM65) -> 0 | M65: =SUM(S65,X65,AC65,AN65,AS65,AX65,BI65,BN65,BS65,CD65,CI65,CN65) -> 0 | N65: =SUM(T65,Y65,AD65,AO65,AT65,AY65,BJ65,BO65,BT65,CE65,CJ65,CO65) -> 0 | S65: =P65-Q65 -> 0 | X65: =U65-V65 -> 0 | AD65: =AA65-AB65 -> 0 | AH65: =AE65-AF65 -> 0 | AN65: =AK65-AL65 -> 0 | AS65: =AP65-AQ65 -> 0 | AX65: =AU65-AV65 -> 0 | BC65: =AZ65-BA65 -> 0 | BI65: =BF65-BG65 -> 0 | BN65: =BK65-BL65 -> 0 | BS65: =BP65-BQ65 -> 0 | BX65: =BU65-BV65 -> 0 | CD65: =CA65-CB65 -> 0 | CI65: =CF65-CG65 -> 0 | CN65: =CK65-CL65 -> 0 | CS65: =CP65-CQ65 -> 0
A66: 57 | F66: デモカー・代車費 | J66: =SUM(P66,U66,Z66,AK66,AP66,AU66,BF66,BK66,BP66,CA66,CF66,CK66) -> 0 | K66: =SUM(Q66,V66,AA66,AL66,AQ66,AV66,BG66,BL66,BQ66,CB66,CG66,CL66) -> 0 | L66: =SUM(R66,W66,AB66,AM66,AR66,AW66,BH66,BM66,BR66,CC66,CH66,CM66) -> 0 | M66: =SUM(S66,X66,AC66,AN66,AS66,AX66,BI66,BN66,BS66,CD66,CI66,CN66) -> 0 | N66: =SUM(T66,Y66,AD66,AO66,AT66,AY66,BJ66,BO66,BT66,CE66,CJ66,CO66) -> 0 | S66: =P66-Q66 -> 0 | X66: =U66-V66 -> 0 | AD66: =AA66-AB66 -> 0 | AH66: =AE66-AF66 -> 0 | AN66: =AK66-AL66 -> 0 | AS66: =AP66-AQ66 -> 0 | AX66: =AU66-AV66 -> 0 | BC66: =AZ66-BA66 -> 0 | BI66: =BF66-BG66 -> 0 | BN66: =BK66-BL66 -> 0 | BS66: =BP66-BQ66 -> 0 | BX66: =BU66-BV66 -> 0 | CD66: =CA66-CB66 -> 0 | CI66: =CF66-CG66 -> 0 | CN66: =CK66-CL66 -> 0 | CS66: =CP66-CQ66 -> 0
A67: 58 | F67: 本部負担金 | J67: =SUM(P67,U67,Z67,AK67,AP67,AU67,BF67,BK67,BP67,CA67,CF67,CK67) -> 0 | K67: =SUM(Q67,V67,AA67,AL67,AQ67,AV67,BG67,BL67,BQ67,CB67,CG67,CL67) -> 0 | L67: =SUM(R67,W67,AB67,AM67,AR67,AW67,BH67,BM67,BR67,CC67,CH67,CM67) -> 0 | M67: =SUM(S67,X67,AC67,AN67,AS67,AX67,BI67,BN67,BS67,CD67,CI67,CN67) -> 0 | N67: =SUM(T67,Y67,AD67,AO67,AT67,AY67,BJ67,BO67,BT67,CE67,CJ67,CO67) -> 0 | S67: =P67-Q67 -> 0 | X67: =U67-V67 -> 0 | AD67: =AA67-AB67 -> 0 | AH67: =AE67-AF67 -> 0 | AN67: =AK67-AL67 -> 0 | AS67: =AP67-AQ67 -> 0 | AX67: =AU67-AV67 -> 0 | BC67: =AZ67-BA67 -> 0 | BI67: =BF67-BG67 -> 0 | BN67: =BK67-BL67 -> 0 | BS67: =BP67-BQ67 -> 0 | BX67: =BU67-BV67 -> 0 | CD67: =CA67-CB67 -> 0 | CI67: =CF67-CG67 -> 0 | CN67: =CK67-CL67 -> 0 | CS67: =CP67-CQ67 -> 0
A68: 59 | F68: 小計 | J68: =SUM(P68,U68,Z68,AK68,AP68,AU68,BF68,BK68,BP68,CA68,CF68,CK68) -> 0 | K68: =SUM(Q68,V68,AA68,AL68,AQ68,AV68,BG68,BL68,BQ68,CB68,CG68,CL68) -> 0 | L68: =SUM(R68,W68,AB68,AM68,AR68,AW68,BH68,BM68,BR68,CC68,CH68,CM68) -> 0 | M68: =SUM(S68,X68,AC68,AN68,AS68,AX68,BI68,BN68,BS68,CD68,CI68,CN68) -> 0 | N68: =SUM(T68,Y68,AD68,AO68,AT68,AY68,BJ68,BO68,BT68,CE68,CJ68,CO68) -> 0 | S68: =P68-Q68 -> 0 | X68: =U68-V68 -> 0 | AD68: =AA68-AB68 -> 0 | AH68: =AE68-AF68 -> 0 | AN68: =AK68-AL68 -> 0 | AS68: =AP68-AQ68 -> 0 | AX68: =AU68-AV68 -> 0 | BC68: =AZ68-BA68 -> 0 | BI68: =BF68-BG68 -> 0 | BN68: =BK68-BL68 -> 0 | BS68: =BP68-BQ68 -> 0 | BX68: =BU68-BV68 -> 0 | CD68: =CA68-CB68 -> 0 | CI68: =CF68-CG68 -> 0 | CN68: =CK68-CL68 -> 0 | CS68: =CP68-CQ68 -> 0
A69: 60 | E69: 中古車限界利益 | J69: =SUM(P69,U69,Z69,AK69,AP69,AU69,BF69,BK69,BP69,CA69,CF69,CK69) -> 0 | K69: =SUM(Q69,V69,AA69,AL69,AQ69,AV69,BG69,BL69,BQ69,CB69,CG69,CL69) -> 0 | L69: =SUM(R69,W69,AB69,AM69,AR69,AW69,BH69,BM69,BR69,CC69,CH69,CM69) -> 0 | M69: =SUM(S69,X69,AC69,AN69,AS69,AX69,BI69,BN69,BS69,CD69,CI69,CN69) -> 0 | N69: =SUM(T69,Y69,AD69,AO69,AT69,AY69,BJ69,BO69,BT69,CE69,CJ69,CO69) -> 0 | S69: =P69-Q69 -> 0 | X69: =U69-V69 -> 0 | AD69: =AA69-AB69 -> 0 | AH69: =AE69-AF69 -> 0 | AN69: =AK69-AL69 -> 0 | AS69: =AP69-AQ69 -> 0 | AX69: =AU69-AV69 -> 0 | BC69: =AZ69-BA69 -> 0 | BI69: =BF69-BG69 -> 0 | BN69: =BK69-BL69 -> 0 | BS69: =BP69-BQ69 -> 0 | BX69: =BU69-BV69 -> 0 | CD69: =CA69-CB69 -> 0 | CI69: =CF69-CG69 -> 0 | CN69: =CK69-CL69 -> 0 | CS69: =CP69-CQ69 -> 0
A70: 61 | D70: 整備 | E70: 売上金額 | J70: =SUM(P70,U70,Z70,AK70,AP70,AU70,BF70,BK70,BP70,CA70,CF70,CK70) -> 0 | K70: =SUM(Q70,V70,AA70,AL70,AQ70,AV70,BG70,BL70,BQ70,CB70,CG70,CL70) -> 0 | L70: =SUM(R70,W70,AB70,AM70,AR70,AW70,BH70,BM70,BR70,CC70,CH70,CM70) -> 0 | M70: =SUM(S70,X70,AC70,AN70,AS70,AX70,BI70,BN70,BS70,CD70,CI70,CN70) -> 0 | N70: =SUM(T70,Y70,AD70,AO70,AT70,AY70,BJ70,BO70,BT70,CE70,CJ70,CO70) -> 0 | S70: =P70-Q70 -> 0 | X70: =U70-V70 -> 0 | AD70: =AA70-AB70 -> 0 | AH70: =AE70-AF70 -> 0 | AN70: =AK70-AL70 -> 0 | AS70: =AP70-AQ70 -> 0 | AX70: =AU70-AV70 -> 0 | BC70: =AZ70-BA70 -> 0 | BI70: =BF70-BG70 -> 0 | BN70: =BK70-BL70 -> 0 | BS70: =BP70-BQ70 -> 0 | BX70: =BU70-BV70 -> 0 | CD70: =CA70-CB70 -> 0 | CI70: =CF70-CG70 -> 0 | CN70: =CK70-CL70 -> 0 | CS70: =CP70-CQ70 -> 0
A71: 62 | F71: ＜内車両値引＞ | J71: =SUM(P71,U71,Z71,AK71,AP71,AU71,BF71,BK71,BP71,CA71,CF71,CK71) -> 0 | K71: =SUM(Q71,V71,AA71,AL71,AQ71,AV71,BG71,BL71,BQ71,CB71,CG71,CL71) -> 0 | L71: =SUM(R71,W71,AB71,AM71,AR71,AW71,BH71,BM71,BR71,CC71,CH71,CM71) -> 0 | M71: =SUM(S71,X71,AC71,AN71,AS71,AX71,BI71,BN71,BS71,CD71,CI71,CN71) -> 0 | N71: =SUM(T71,Y71,AD71,AO71,AT71,AY71,BJ71,BO71,BT71,CE71,CJ71,CO71) -> 0 | S71: =P71-Q71 -> 0 | X71: =U71-V71 -> 0 | AD71: =AA71-AB71 -> 0 | AH71: =AE71-AF71 -> 0 | AN71: =AK71-AL71 -> 0 | AS71: =AP71-AQ71 -> 0 | AX71: =AU71-AV71 -> 0 | BC71: =AZ71-BA71 -> 0 | BI71: =BF71-BG71 -> 0 | BN71: =BK71-BL71 -> 0 | BS71: =BP71-BQ71 -> 0 | BX71: =BU71-BV71 -> 0 | CD71: =CA71-CB71 -> 0 | CI71: =CF71-CG71 -> 0 | CN71: =CK71-CL71 -> 0 | CS71: =CP71-CQ71 -> 0
